{
  "updated_at": "2026-03-11T10:50:18.761290Z",
  "protocols": [
    {
      "protocol": "Drift Trade",
      "volume_24h": 64060099,
      "volume_7d": 393727132,
      "change_1d": 46.71,
      "change_7d": -23.52,
      "transactions": 900,
      "traders": 2123,
      "fees": 32030.0495
    },
    {
      "protocol": "Jupiter Perpetual Exchange",
      "volume_24h": 284267743,
      "volume_7d": 1788339312,
      "change_1d": 8.78,
      "change_7d": -21.05,
      "transactions": 0,
      "traders": 2976,
      "fees": 170560.6458
    },
    {
      "protocol": "FlashTrade",
      "volume_24h": 25539360,
      "volume_7d": 73854171,
      "change_1d": 131.84,
      "change_7d": 89.21,
      "transactions": 1000,
      "traders": 1018,
      "fees": 12769.68
    },
    {
      "protocol": "Adrena Protocol",
      "volume_24h": 2467,
      "volume_7d": 23165,
      "change_1d": 285.47,
      "change_7d": -88.28,
      "transactions": 0,
      "traders": 16,
      "fees": 1.2335
    },
    {
      "protocol": "Pacifica",
      "volume_24h": 484904286,
      "volume_7d": 2863355077,
      "change_1d": -15.15,
      "change_7d": 30.49,
      "transactions": 0,
      "traders": 2225,
      "fees": 242452.143
    },
    {
      "protocol": "Tread.fi Perps",
      "volume_24h": 93248515,
      "volume_7d": 530583057,
      "change_1d": 53.3,
      "change_7d": -50.31,
      "transactions": 0,
      "traders": 0,
      "fees": 46624.2575
    },
    {
      "protocol": "GMTrade",
      "volume_24h": 198714834,
      "volume_7d": 792470102,
      "change_1d": 46.29,
      "change_7d": 8,
      "transactions": 0,
      "traders": 0,
      "fees": 99357.417
    },
    {
      "protocol": "FlowBot Perps",
      "volume_24h": 433099,
      "volume_7d": 7984403,
      "change_1d": -26.82,
      "change_7d": -80.8,
      "transactions": 0,
      "traders": 0,
      "fees": 216.5495
    }
  ],
  "drift_markets": {
    "SOL-PERP": {
      "volume": 27715841.565808,
      "open_interest": 856413.71,
      "funding_rate": -0.001380577,
      "next_funding_rate": -0.000885,
      "last_price": 85.370397,
      "price_high": 89.014289,
      "price_low": 84.5605,
      "index_price": 85.404899
    },
    "BTC-PERP": {
      "volume": 13546993.717674,
      "open_interest": 546.0691,
      "funding_rate": -0.000335731,
      "next_funding_rate": -0.000479,
      "last_price": 69574.29067,
      "price_high": 71725.9,
      "price_low": 69275.1,
      "index_price": 69602.427502
    },
    "ETH-PERP": {
      "volume": 2080671.882902,
      "open_interest": 7687.059,
      "funding_rate": -0.000551355,
      "next_funding_rate": -0.000521,
      "last_price": 2019.390964,
      "price_high": 2087.2265,
      "price_low": 2008.27,
      "index_price": 2027.495001
    },
    "APT-PERP": {
      "volume": 13401.890629,
      "open_interest": 41713.2,
      "funding_rate": 0.000557171,
      "next_funding_rate": 0.00061,
      "last_price": 0.943509,
      "price_high": 0.986,
      "price_low": 0.937864,
      "index_price": 0.943548
    },
    "1MBONK-PERP": {
      "volume": 26628.066537,
      "open_interest": 22537.3,
      "funding_rate": 0.001740717,
      "next_funding_rate": 0.002214,
      "last_price": 5.926955,
      "price_high": 6.19787,
      "price_low": 5.8993,
      "index_price": 5.9243
    },
    "POL-PERP": {
      "volume": 3436.721865,
      "open_interest": 110881.0,
      "funding_rate": -0.004565284,
      "next_funding_rate": -0.004645,
      "last_price": 0.096695,
      "price_high": 0.0981,
      "price_low": 0.096725,
      "index_price": 0.096819
    },
    "ARB-PERP": {
      "volume": 5477.199328,
      "open_interest": 320966.0,
      "funding_rate": -0.003792514,
      "next_funding_rate": -0.004082,
      "last_price": 0.099538,
      "price_high": 0.101307,
      "price_low": 0.0976,
      "index_price": 0.099639
    },
    "DOGE-PERP": {
      "volume": 35398.449589,
      "open_interest": 4083566.0,
      "funding_rate": 0.0,
      "next_funding_rate": 0.000271,
      "last_price": 0.092136,
      "price_high": 0.10094,
      "price_low": 0.09148,
      "index_price": 0.092138
    },
    "BNB-PERP": {
      "volume": 16241.638272,
      "open_interest": 377.78,
      "funding_rate": -0.003094127,
      "next_funding_rate": -0.003255,
      "last_price": 643.376513,
      "price_high": 648.74915,
      "price_low": 639.33,
      "index_price": 644.035
    },
    "SUI-PERP": {
      "volume": 150620.017087,
      "open_interest": 783749.0,
      "funding_rate": 0.00060919,
      "next_funding_rate": 0.000657,
      "last_price": 0.955604,
      "price_high": 1.0065,
      "price_low": 0.9449,
      "index_price": 0.955636
    },
    "1MPEPE-PERP": {
      "volume": 2893.682222,
      "open_interest": 5018.0,
      "funding_rate": -0.004840421,
      "next_funding_rate": -0.004798,
      "last_price": 3.271458,
      "price_high": 0.0,
      "price_low": 0.0,
      "index_price": 3.2759
    },
    "OP-PERP": {
      "volume": 2061.347619,
      "open_interest": 97049.0,
      "funding_rate": -0.004507791,
      "next_funding_rate": -0.004467,
      "last_price": 0.119978,
      "price_high": 0.123425,
      "price_low": 0.1185,
      "index_price": 0.120152
    },
    "RENDER-PERP": {
      "volume": 30771.107145,
      "open_interest": 91176.0,
      "funding_rate": -0.006412105,
      "next_funding_rate": -0.005874,
      "last_price": 1.493225,
      "price_high": 1.5708,
      "price_low": 1.4574,
      "index_price": 1.4955
    },
    "XRP-PERP": {
      "volume": 123829.42131,
      "open_interest": 520073.0,
      "funding_rate": 0.000716977,
      "next_funding_rate": 0.000738,
      "last_price": 1.378752,
      "price_high": 1.4395,
      "price_low": 1.3752,
      "index_price": 1.37875
    },
    "HNT-PERP": {
      "volume": 6.819935,
      "open_interest": 10558.0,
      "funding_rate": -0.003393641,
      "next_funding_rate": -0.003369,
      "last_price": 1.204169,
      "price_high": 0.0,
      "price_low": 0.0,
      "index_price": 1.206647
    },
    "INJ-PERP": {
      "volume": 2987.249674,
      "open_interest": 26781.0,
      "funding_rate": -0.003517923,
      "next_funding_rate": -0.003487,
      "last_price": 2.940265,
      "price_high": 2.989,
      "price_low": 2.899,
      "index_price": 2.943295
    },
    "LINK-PERP": {
      "volume": 4255.733771,
      "open_interest": 12570.0,
      "funding_rate": 0.000826456,
      "next_funding_rate": 0.000859,
      "last_price": 8.955413,
      "price_high": 9.176,
      "price_low": 8.90749,
      "index_price": 8.955534
    },
    "RLB-PERP": {
      "volume": 64.817978,
      "open_interest": 500.0,
      "funding_rate": -0.000247909,
      "next_funding_rate": 0.000887,
      "last_price": 0.061019,
      "price_high": 0.0,
      "price_low": 0.0,
      "index_price": 0.06102
    },
    "PYTH-PERP": {
      "volume": 4869.580777,
      "open_interest": 3205168.0,
      "funding_rate": -0.001274289,
      "next_funding_rate": -0.001547,
      "last_price": 0.045844,
      "price_high": 0.047986,
      "price_low": 0.045444,
      "index_price": 0.045845
    },
    "TIA-PERP": {
      "volume": 3200.972478,
      "open_interest": 13335.0,
      "funding_rate": -0.003049412,
      "next_funding_rate": -0.003236,
      "last_price": 0.330334,
      "price_high": 0.333,
      "price_low": 0.332071,
      "index_price": 0.330667
    },
    "JTO-PERP": {
      "volume": 9575.913563,
      "open_interest": 267992.0,
      "funding_rate": -0.00385923,
      "next_funding_rate": -0.003886,
      "last_price": 0.259842,
      "price_high": 0.265374,
      "price_low": 0.256442,
      "index_price": 0.260148
    },
    "SEI-PERP": {
      "volume": 159.619191,
      "open_interest": 248979.0,
      "funding_rate": 0.004238541,
      "next_funding_rate": 0.00484,
      "last_price": 0.06372,
      "price_high": 0.0,
      "price_low": 0.0,
      "index_price": 0.063649
    },
    "AVAX-PERP": {
      "volume": 25019.959372,
      "open_interest": 8305.5,
      "funding_rate": 0.000864347,
      "next_funding_rate": 0.001066,
      "last_price": 9.587481,
      "price_high": 9.883,
      "price_low": 9.320556,
      "index_price": 9.585541
    },
    "WIF-PERP": {
      "volume": 304501.355705,
      "open_interest": 1720229.0,
      "funding_rate": -0.002724073,
      "next_funding_rate": -0.00201,
      "last_price": 0.163321,
      "price_high": 0.173989,
      "price_low": 0.1617,
      "index_price": 0.16347
    },
    "JUP-PERP": {
      "volume": 76321.310001,
      "open_interest": 2309962.0,
      "funding_rate": -0.001355083,
      "next_funding_rate": -0.000664,
      "last_price": 0.163216,
      "price_high": 0.1801,
      "price_low": 0.1614,
      "index_price": 0.163196
    },
    "DYM-PERP": {
      "volume": 97.934407,
      "open_interest": 547.0,
      "funding_rate": -0.001130882,
      "next_funding_rate": -0.085323,
      "last_price": 0.053616,
      "price_high": 0.0,
      "price_low": 0.0,
      "index_price": 0.059791
    },
    "TAO-PERP": {
      "volume": 20977.133519,
      "open_interest": 2183.66,
      "funding_rate": -0.00146171,
      "next_funding_rate": -0.001413,
      "last_price": 197.438192,
      "price_high": 207.4226,
      "price_low": 195.9959,
      "index_price": 197.544286
    },
    "W-PERP": {
      "volume": 52.743196,
      "open_interest": 734545.0,
      "funding_rate": -0.001131911,
      "next_funding_rate": 0.00068,
      "last_price": 0.018361,
      "price_high": 0.018641,
      "price_low": 0.01817,
      "index_price": 0.018362
    },
    "KMNO-PERP": {
      "volume": 12138.757635,
      "open_interest": 7016798.0,
      "funding_rate": 0.007774756,
      "next_funding_rate": 0.006452,
      "last_price": 0.018701,
      "price_high": 0.0196,
      "price_low": 0.0186,
      "index_price": 0.018658
    },
    "TNSR-PERP": {
      "volume": 5033.198677,
      "open_interest": 1482040.0,
      "funding_rate": 0.005727854,
      "next_funding_rate": 0.004343,
      "last_price": 0.047944,
      "price_high": 0.0524,
      "price_low": 0.045949,
      "index_price": 0.047857
    },
    "DRIFT-PERP": {
      "volume": 11423.638402,
      "open_interest": 4301914.0,
      "funding_rate": -0.003388368,
      "next_funding_rate": -0.005894,
      "last_price": 0.081135,
      "price_high": 0.0828,
      "price_low": 0.0806,
      "index_price": 0.081401
    },
    "CLOUD-PERP": {
      "volume": 51.198346,
      "open_interest": 47116.0,
      "funding_rate": -0.005308137,
      "next_funding_rate": -0.005851,
      "last_price": 0.037632,
      "price_high": 0.038291,
      "price_low": 0.03776,
      "index_price": 0.037735
    },
    "IO-PERP": {
      "volume": 1639.828223,
      "open_interest": 20.0,
      "funding_rate": 0.033784348,
      "next_funding_rate": -0.049482,
      "last_price": 0.142941,
      "price_high": 0.0,
      "price_low": 0.0,
      "index_price": 0.144478
    },
    "ZEX-PERP": {
      "volume": 7.84,
      "open_interest": 14.0,
      "funding_rate": -0.008775444,
      "next_funding_rate": 0.000789,
      "last_price": 0.073829,
      "price_high": 0.0,
      "price_low": 0.0,
      "index_price": 0.073914
    },
    "POPCAT-PERP": {
      "volume": 104.210316,
      "open_interest": 511988.0,
      "funding_rate": 0.002866974,
      "next_funding_rate": 0.002951,
      "last_price": 0.05092,
      "price_high": 0.052669,
      "price_low": 0.050335,
      "index_price": 0.050852
    },
    "1KWEN-PERP": {
      "volume": 1159.733264,
      "open_interest": 460.0,
      "funding_rate": -0.001614511,
      "next_funding_rate": 0.000953,
      "last_price": 0.026213,
      "price_high": 0.0,
      "price_low": 0.0,
      "index_price": 0.026228
    },
    "TRUMP-WIN-2024-BET": {
      "volume": 1381506.479951,
      "open_interest": 0.0,
      "funding_rate": 0.0,
      "next_funding_rate": 0.000829,
      "last_price": 0.980427,
      "price_high": 0.0,
      "price_low": 0.0,
      "index_price": 0.979815
    },
    "KAMALA-POPULAR-VOTE-2024-BET": {
      "volume": 202.763016,
      "open_interest": 0.0,
      "funding_rate": 0.0,
      "next_funding_rate": 0.0,
      "last_price": 2e-06,
      "price_high": 0.0,
      "price_low": 0.0,
      "index_price": 2e-06
    },
    "FED-CUT-50-SEPT-2024-BET": {
      "volume": 61921.214356,
      "open_interest": 0.0,
      "funding_rate": 0.0,
      "next_funding_rate": 0.000833,
      "last_price": 0.990633,
      "price_high": 0.0,
      "price_low": 0.0,
      "index_price": 0.990015
    },
    "REPUBLICAN-POPULAR-AND-WIN-BET": {
      "volume": 793.263281,
      "open_interest": 0.0,
      "funding_rate": 0.0,
      "next_funding_rate": 0.000831,
      "last_price": 0.998245,
      "price_high": 0.0,
      "price_low": 0.0,
      "index_price": 0.997622
    },
    "BREAKPOINT-IGGYERIC-BET": {
      "volume": 3.894168,
      "open_interest": 0.0,
      "funding_rate": 0.0,
      "next_funding_rate": -0.320512,
      "last_price": 0.0,
      "price_high": 0.0,
      "price_low": 0.0,
      "index_price": 1e-06
    },
    "DEMOCRATS-WIN-MICHIGAN-BET": {
      "volume": 2234.536867,
      "open_interest": 0.0,
      "funding_rate": 0.0,
      "next_funding_rate": 0.0,
      "last_price": 0.0,
      "price_high": 0.0,
      "price_low": 0.0,
      "index_price": 1e-06
    },
    "TON-PERP": {
      "volume": 21592.082409,
      "open_interest": 13463.0,
      "funding_rate": -0.0054629,
      "next_funding_rate": -0.005153,
      "last_price": 1.294692,
      "price_high": 1.345473,
      "price_low": 1.31862,
      "index_price": 1.296572
    },
    "LANDO-F1-SGP-WIN-BET": {
      "volume": 99853.432168,
      "open_interest": 0.0,
      "funding_rate": 0.0,
      "next_funding_rate": 0.000829,
      "last_price": 0.974759,
      "price_high": 0.0,
      "price_low": 0.0,
      "index_price": 0.974151
    },
    "MOTHER-PERP": {
      "volume": 11723.884157,
      "open_interest": 3646.0,
      "funding_rate": 0.116474809,
      "next_funding_rate": -0.148657,
      "last_price": 0.001207,
      "price_high": 0.0,
      "price_low": 0.0,
      "index_price": 0.000945
    },
    "MOODENG-PERP": {
      "volume": 2497.306321,
      "open_interest": 3148.0,
      "funding_rate": 0.017000782,
      "next_funding_rate": -0.005796,
      "last_price": 0.0877,
      "price_high": 0.0,
      "price_low": 0.0,
      "index_price": 0.086109
    },
    "WARWICK-FIGHT-WIN-BET": {
      "volume": 2971.94903,
      "open_interest": 0.0,
      "funding_rate": 0.0,
      "next_funding_rate": 0.0,
      "last_price": 0.0,
      "price_high": 0.0,
      "price_low": 0.0,
      "index_price": 1e-06
    },
    "DBR-PERP": {
      "volume": 32.253978,
      "open_interest": 0.0,
      "funding_rate": -0.001345943,
      "next_funding_rate": 0.000702,
      "last_price": 0.023722,
      "price_high": 0.0,
      "price_low": 0.0,
      "index_price": 0.023723
    },
    "WLF-5B-1W-BET": {
      "volume": 2.45,
      "open_interest": 779.0,
      "funding_rate": 0.0,
      "next_funding_rate": 0.000829,
      "last_price": 1.09756,
      "price_high": 0.0,
      "price_low": 0.0,
      "index_price": 0.713525
    },
    "VRSTPN-WIN-F1-24-DRVRS-CHMP-BET": {
      "volume": 8068.712266,
      "open_interest": 0.0,
      "funding_rate": 0.0,
      "next_funding_rate": 0.000829,
      "last_price": 1.000623,
      "price_high": 0.0,
      "price_low": 0.0,
      "index_price": 0.999999
    },
    "LNDO-WIN-F1-24-US-GP-BET": {
      "volume": 16.516678,
      "open_interest": 0.0,
      "funding_rate": 0.0,
      "next_funding_rate": 0.0,
      "last_price": 0.0,
      "price_high": 0.0,
      "price_low": 0.0,
      "index_price": 1e-06
    },
    "1KMEW-PERP": {
      "volume": 245409.217363,
      "open_interest": 0.0,
      "funding_rate": 0.003754899,
      "next_funding_rate": -0.040121,
      "last_price": 0.936556,
      "price_high": 0.0,
      "price_low": 0.0,
      "index_price": 0.93655
    },
    "MICHI-PERP": {
      "volume": 0.0,
      "open_interest": 272.0,
      "funding_rate": 0.002807306,
      "next_funding_rate": 0.000826,
      "last_price": 0.025216,
      "price_high": 0.0,
      "price_low": 0.0,
      "index_price": 0.025217
    },
    "GOAT-PERP": {
      "volume": 8149.772287,
      "open_interest": 60.0,
      "funding_rate": 0.009174447,
      "next_funding_rate": -0.011508,
      "last_price": 0.039858,
      "price_high": 0.0,
      "price_low": 0.0,
      "index_price": 0.04042
    },
    "FWOG-PERP": {
      "volume": 7816.61287,
      "open_interest": 13687.0,
      "funding_rate": -0.006039425,
      "next_funding_rate": -0.012609,
      "last_price": 0.016252,
      "price_high": 0.0,
      "price_low": 0.0,
      "index_price": 0.015806
    },
    "PNUT-PERP": {
      "volume": 319.544061,
      "open_interest": 226.0,
      "funding_rate": 0.012804868,
      "next_funding_rate": -0.030813,
      "last_price": 0.065715,
      "price_high": 0.0,
      "price_low": 0.0,
      "index_price": 0.070149
    },
    "RAY-PERP": {
      "volume": 23649.618089,
      "open_interest": 257170.0,
      "funding_rate": 0.000556836,
      "next_funding_rate": 0.001262,
      "last_price": 0.592536,
      "price_high": 0.6149,
      "price_low": 0.5883,
      "index_price": 0.592438
    },
    "SUPERBOWL-LIX-LIONS-BET": {
      "volume": 418.575512,
      "open_interest": 0.0,
      "funding_rate": 0.0,
      "next_funding_rate": 0.0,
      "last_price": 0.0,
      "price_high": 0.0,
      "price_low": 0.0,
      "index_price": 1e-06
    },
    "SUPERBOWL-LIX-CHIEFS-BET": {
      "volume": 1637.317715,
      "open_interest": 0.0,
      "funding_rate": 0.0,
      "next_funding_rate": 0.0,
      "last_price": 0.0,
      "price_high": 0.0,
      "price_low": 0.0,
      "index_price": 1e-06
    },
    "HYPE-PERP": {
      "volume": 2101194.243278,
      "open_interest": 93591.8,
      "funding_rate": 0.002288268,
      "next_funding_rate": 0.002388,
      "last_price": 34.599959,
      "price_high": 35.1681,
      "price_low": 33.624011,
      "index_price": 34.57025
    },
    "LTC-PERP": {
      "volume": 64312.803883,
      "open_interest": 1899.2,
      "funding_rate": 0.001272244,
      "next_funding_rate": 0.002115,
      "last_price": 53.987522,
      "price_high": 55.136357,
      "price_low": 53.583977,
      "index_price": 53.95644
    },
    "ME-PERP": {
      "volume": 27.043884,
      "open_interest": 110940.0,
      "funding_rate": 0.000883563,
      "next_funding_rate": 0.000846,
      "last_price": 0.113246,
      "price_high": 0.0,
      "price_low": 0.0,
      "index_price": 0.113245
    },
    "PENGU-PERP": {
      "volume": 10528.098892,
      "open_interest": 4368266.0,
      "funding_rate": 0.0,
      "next_funding_rate": 0.000597,
      "last_price": 0.006971,
      "price_high": 0.007272,
      "price_low": 0.006948,
      "index_price": 0.006971
    },
    "AI16Z-PERP": {
      "volume": 6793.415642,
      "open_interest": 1091.0,
      "funding_rate": 0.017565257,
      "next_funding_rate": -0.100455,
      "last_price": 0.015748,
      "price_high": 0.0,
      "price_low": 0.0,
      "index_price": 0.01625
    },
    "TRUMP-PERP": {
      "volume": 478.434507,
      "open_interest": 5860.3,
      "funding_rate": -0.010551249,
      "next_funding_rate": -0.014962,
      "last_price": 2.896453,
      "price_high": 2.976192,
      "price_low": 2.865997,
      "index_price": 2.913639
    },
    "MELANIA-PERP": {
      "volume": 2811.061656,
      "open_interest": 0.0,
      "funding_rate": 0.002109164,
      "next_funding_rate": -0.001513,
      "last_price": 0.107262,
      "price_high": 0.0,
      "price_low": 0.0,
      "index_price": 0.107263
    },
    "BERA-PERP": {
      "volume": 241.225026,
      "open_interest": 44959.7,
      "funding_rate": -0.004236197,
      "next_funding_rate": -0.003846,
      "last_price": 0.555275,
      "price_high": 0.5525,
      "price_low": 0.519115,
      "index_price": 0.555698
    },
    "NBAFINALS25-OKC-BET": {
      "volume": 1439.398655,
      "open_interest": 20.0,
      "funding_rate": 0.0,
      "next_funding_rate": 0.00083,
      "last_price": 0.968746,
      "price_high": 0.0,
      "price_low": 0.0,
      "index_price": 0.968495
    },
    "NBAFINALS25-BOS-BET": {
      "volume": 1.971608,
      "open_interest": 97.0,
      "funding_rate": 0.0,
      "next_funding_rate": 0.0,
      "last_price": 0.0,
      "price_high": 0.0,
      "price_low": 0.0,
      "index_price": 1e-06
    },
    "KAITO-PERP": {
      "volume": 907.881758,
      "open_interest": 9081.0,
      "funding_rate": -0.001143102,
      "next_funding_rate": -0.001178,
      "last_price": 0.348555,
      "price_high": 0.0,
      "price_low": 0.0,
      "index_price": 0.348715
    },
    "IP-PERP": {
      "volume": 245.524468,
      "open_interest": 24032.4,
      "funding_rate": -0.006540077,
      "next_funding_rate": -0.006795,
      "last_price": 0.777085,
      "price_high": 0.799737,
      "price_low": 0.789949,
      "index_price": 0.778465
    },
    "FARTCOIN-PERP": {
      "volume": 18466.813557,
      "open_interest": 1327355.0,
      "funding_rate": 0.002507654,
      "next_funding_rate": 0.00259,
      "last_price": 0.153714,
      "price_high": 0.158298,
      "price_low": 0.1525,
      "index_price": 0.153574
    },
    "ADA-PERP": {
      "volume": 1305.334102,
      "open_interest": 185786.0,
      "funding_rate": 0.00319023,
      "next_funding_rate": 0.003191,
      "last_price": 0.259861,
      "price_high": 0.0,
      "price_low": 0.0,
      "index_price": 0.259646
    },
    "PAXG-PERP": {
      "volume": 126295.911008,
      "open_interest": 129.458,
      "funding_rate": 0.001215394,
      "next_funding_rate": 0.001215,
      "last_price": 5188.079114,
      "price_high": 5236.6746,
      "price_low": 5179.218294,
      "index_price": 5187.648514
    },
    "LAUNCHCOIN-PERP": {
      "volume": 25287.201769,
      "open_interest": 0.0,
      "funding_rate": 0.33118948,
      "next_funding_rate": -0.41425,
      "last_price": 0.000589,
      "price_high": 0.0,
      "price_low": 0.0,
      "index_price": 0.000588
    },
    "PUMP-PERP": {
      "volume": 522367.104292,
      "open_interest": 0.0,
      "funding_rate": -0.275531724,
      "next_funding_rate": -0.017821,
      "last_price": 0.001956,
      "price_high": 0.0,
      "price_low": 0.0,
      "index_price": 0.001985
    },
    "ASTER-PERP": {
      "volume": 28751.732195,
      "open_interest": 121320.0,
      "funding_rate": 0.001736638,
      "next_funding_rate": 0.001737,
      "last_price": 0.693259,
      "price_high": 0.709326,
      "price_low": 0.6923,
      "index_price": 0.693072
    },
    "XPL-PERP": {
      "volume": 1166.88231,
      "open_interest": 93935.0,
      "funding_rate": -0.000465163,
      "next_funding_rate": -0.000507,
      "last_price": 0.099328,
      "price_high": 0.1054,
      "price_low": 0.0947,
      "index_price": 0.09934
    },
    "2Z-PERP": {
      "volume": 697.578519,
      "open_interest": 25960.0,
      "funding_rate": 0.007114645,
      "next_funding_rate": 0.007779,
      "last_price": 0.077223,
      "price_high": 0.0,
      "price_low": 0.0,
      "index_price": 0.077068
    },
    "ZEC-PERP": {
      "volume": 182444.760468,
      "open_interest": 3021.0,
      "funding_rate": 0.00076978,
      "next_funding_rate": 0.00078,
      "last_price": 212.816056,
      "price_high": 230.5,
      "price_low": 213.63,
      "index_price": 212.830109
    },
    "MNT-PERP": {
      "volume": 6.986943,
      "open_interest": 31691.0,
      "funding_rate": -0.01105207,
      "next_funding_rate": -0.010601,
      "last_price": 0.691486,
      "price_high": 0.699418,
      "price_low": 0.676454,
      "index_price": 0.693474
    },
    "1KPUMP-PERP": {
      "volume": 228414.964037,
      "open_interest": 61847.0,
      "funding_rate": -0.006618243,
      "next_funding_rate": -0.006068,
      "last_price": 1.983618,
      "price_high": 2.12152,
      "price_low": 1.9673,
      "index_price": 1.98537
    },
    "MET-PERP": {
      "volume": 3.809824,
      "open_interest": 156225.0,
      "funding_rate": 0.011066218,
      "next_funding_rate": 0.011618,
      "last_price": 0.162057,
      "price_high": 0.1607,
      "price_low": 0.158478,
      "index_price": 0.159441
    },
    "1KMON-PERP": {
      "volume": 2813.42049,
      "open_interest": 2261.0,
      "funding_rate": 0.001187655,
      "next_funding_rate": 0.001203,
      "last_price": 21.157018,
      "price_high": 21.6732,
      "price_low": 21.317369,
      "index_price": 21.15502
    },
    "LIT-PERP": {
      "volume": 5640.464675,
      "open_interest": 37435.0,
      "funding_rate": -0.007621375,
      "next_funding_rate": -0.007601,
      "last_price": 1.032221,
      "price_high": 1.046,
      "price_low": 1.029585,
      "index_price": 1.034308
    }
  },
  "jupiter_markets": {
    "trades": {
      "SOL": 1196,
      "BTC": 132,
      "ETH": 88,
      "OTHER": 87,
      "USDC": 1
    },
    "volumes": {
      "SOL": 226053338.18351063,
      "BTC": 24949030.635638297,
      "ETH": 16632687.090425532,
      "OTHER": 16443679.282579787,
      "USDC": 189007.80784574468
    }
  },
  "pacifica_markets": {
    "SOL": {
      "volume": 638445.299659017,
      "trades": 0,
      "funding_rate": 3.33e-06,
      "max_leverage": 20
    },
    "ETH": {
      "volume": 638445.299659017,
      "trades": 0,
      "funding_rate": 9.02e-06,
      "max_leverage": 50
    },
    "BTC": {
      "volume": 638445.299659017,
      "trades": 0,
      "funding_rate": 9.62e-06,
      "max_leverage": 50
    },
    "PUMP": {
      "volume": 638445.299659017,
      "trades": 0,
      "funding_rate": -9.2e-07,
      "max_leverage": 5
    },
    "XRP": {
      "volume": 638445.299659017,
      "trades": 0,
      "funding_rate": -2.04e-05,
      "max_leverage": 20
    },
    "HYPE": {
      "volume": 638445.299659017,
      "trades": 0,
      "funding_rate": -1.485e-05,
      "max_leverage": 20
    },
    "DOGE": {
      "volume": 638445.299659017,
      "trades": 0,
      "funding_rate": 1.15e-05,
      "max_leverage": 15
    },
    "FARTCOIN": {
      "volume": 638445.299659017,
      "trades": 0,
      "funding_rate": 1.5e-05,
      "max_leverage": 10
    },
    "ENA": {
      "volume": 638445.299659017,
      "trades": 0,
      "funding_rate": -2.168e-05,
      "max_leverage": 10
    },
    "BNB": {
      "volume": 638445.299659017,
      "trades": 0,
      "funding_rate": -2.982e-05,
      "max_leverage": 10
    },
    "SUI": {
      "volume": 638445.299659017,
      "trades": 0,
      "funding_rate": 1.5e-05,
      "max_leverage": 10
    },
    "kBONK": {
      "volume": 638445.299659017,
      "trades": 0,
      "funding_rate": 7.22e-06,
      "max_leverage": 10
    },
    "PENGU": {
      "volume": 638445.299659017,
      "trades": 0,
      "funding_rate": -3.895e-05,
      "max_leverage": 5
    },
    "AAVE": {
      "volume": 638445.299659017,
      "trades": 0,
      "funding_rate": 9.04e-06,
      "max_leverage": 10
    },
    "LINK": {
      "volume": 638445.299659017,
      "trades": 0,
      "funding_rate": 1.5e-05,
      "max_leverage": 10
    },
    "kPEPE": {
      "volume": 638445.299659017,
      "trades": 0,
      "funding_rate": -3.488e-05,
      "max_leverage": 10
    },
    "LTC": {
      "volume": 638445.299659017,
      "trades": 0,
      "funding_rate": -1.37e-05,
      "max_leverage": 10
    },
    "LDO": {
      "volume": 638445.299659017,
      "trades": 0,
      "funding_rate": 1.5e-05,
      "max_leverage": 10
    },
    "UNI": {
      "volume": 638445.299659017,
      "trades": 0,
      "funding_rate": 1.22e-05,
      "max_leverage": 10
    },
    "CRV": {
      "volume": 638445.299659017,
      "trades": 0,
      "funding_rate": 1.5e-05,
      "max_leverage": 10
    },
    "WLFI": {
      "volume": 638445.299659017,
      "trades": 0,
      "funding_rate": 1.5e-05,
      "max_leverage": 5
    },
    "AVAX": {
      "volume": 638445.299659017,
      "trades": 0,
      "funding_rate": 1.5e-05,
      "max_leverage": 10
    },
    "ASTER": {
      "volume": 638445.299659017,
      "trades": 0,
      "funding_rate": 1.5e-05,
      "max_leverage": 5
    },
    "XPL": {
      "volume": 638445.299659017,
      "trades": 0,
      "funding_rate": 1.5e-05,
      "max_leverage": 10
    },
    "2Z": {
      "volume": 638445.299659017,
      "trades": 0,
      "funding_rate": -6.598e-05,
      "max_leverage": 3
    },
    "PAXG": {
      "volume": 638445.299659017,
      "trades": 0,
      "funding_rate": 1.62e-06,
      "max_leverage": 10
    },
    "ZEC": {
      "volume": 638445.299659017,
      "trades": 0,
      "funding_rate": 5.87e-06,
      "max_leverage": 10
    },
    "MON": {
      "volume": 638445.299659017,
      "trades": 0,
      "funding_rate": 1.077e-05,
      "max_leverage": 3
    },
    "VIRTUAL": {
      "volume": 638445.299659017,
      "trades": 0,
      "funding_rate": 1.5e-05,
      "max_leverage": 5
    },
    "TAO": {
      "volume": 638445.299659017,
      "trades": 0,
      "funding_rate": 2.3e-06,
      "max_leverage": 10
    },
    "ZK": {
      "volume": 638445.299659017,
      "trades": 0,
      "funding_rate": 1.5e-05,
      "max_leverage": 5
    },
    "STRK": {
      "volume": 638445.299659017,
      "trades": 0,
      "funding_rate": 1.5e-05,
      "max_leverage": 5
    },
    "NEAR": {
      "volume": 638445.299659017,
      "trades": 0,
      "funding_rate": 1.5e-05,
      "max_leverage": 10
    },
    "TRUMP": {
      "volume": 638445.299659017,
      "trades": 0,
      "funding_rate": -5.091e-05,
      "max_leverage": 10
    },
    "ICP": {
      "volume": 638445.299659017,
      "trades": 0,
      "funding_rate": -0.00183064,
      "max_leverage": 5
    },
    "BCH": {
      "volume": 638445.299659017,
      "trades": 0,
      "funding_rate": 1.015e-05,
      "max_leverage": 10
    },
    "XMR": {
      "volume": 638445.299659017,
      "trades": 0,
      "funding_rate": 1.5e-05,
      "max_leverage": 10
    },
    "ADA": {
      "volume": 638445.299659017,
      "trades": 0,
      "funding_rate": 2.74e-06,
      "max_leverage": 10
    },
    "ARB": {
      "volume": 638445.299659017,
      "trades": 0,
      "funding_rate": 9.83e-06,
      "max_leverage": 10
    },
    "LIT": {
      "volume": 638445.299659017,
      "trades": 0,
      "funding_rate": 1.5e-05,
      "max_leverage": 5
    },
    "NVDA": {
      "volume": 638445.299659017,
      "trades": 0,
      "funding_rate": 1.5e-05,
      "max_leverage": 10
    },
    "XAG": {
      "volume": 638445.299659017,
      "trades": 0,
      "funding_rate": 1.5e-05,
      "max_leverage": 10
    },
    "WLD": {
      "volume": 638445.299659017,
      "trades": 0,
      "funding_rate": 1.5e-05,
      "max_leverage": 5
    },
    "JUP": {
      "volume": 638445.299659017,
      "trades": 0,
      "funding_rate": 1.5e-05,
      "max_leverage": 10
    },
    "WIF": {
      "volume": 638445.299659017,
      "trades": 0,
      "funding_rate": -0.00014573,
      "max_leverage": 5
    },
    "PIPPIN": {
      "volume": 638445.299659017,
      "trades": 0,
      "funding_rate": -8.791e-05,
      "max_leverage": 3
    },
    "CL": {
      "volume": 638445.299659017,
      "trades": 0,
      "funding_rate": 1.5e-05,
      "max_leverage": 10
    },
    "USDJPY": {
      "volume": 638445.299659017,
      "trades": 0,
      "funding_rate": -1.13e-06,
      "max_leverage": 50
    },
    "TSLA": {
      "volume": 638445.299659017,
      "trades": 0,
      "funding_rate": 1.5e-05,
      "max_leverage": 10
    },
    "MEGA": {
      "volume": 638445.299659017,
      "trades": 0,
      "funding_rate": 1.5e-05,
      "max_leverage": 3
    },
    "BP": {
      "volume": 638445.299659017,
      "trades": 0,
      "funding_rate": 1.5e-05,
      "max_leverage": 3
    },
    "ZRO": {
      "volume": 638445.299659017,
      "trades": 0,
      "funding_rate": 1.5e-05,
      "max_leverage": 5
    },
    "GOOGL": {
      "volume": 638445.299659017,
      "trades": 0,
      "funding_rate": 1.5e-05,
      "max_leverage": 10
    },
    "COPPER": {
      "volume": 638445.299659017,
      "trades": 0,
      "funding_rate": 1.5e-05,
      "max_leverage": 10
    },
    "XAU": {
      "volume": 638445.299659017,
      "trades": 0,
      "funding_rate": 1.5e-05,
      "max_leverage": 10
    },
    "EURUSD": {
      "volume": 638445.299659017,
      "trades": 0,
      "funding_rate": 1.5e-05,
      "max_leverage": 50
    },
    "PLTR": {
      "volume": 638445.299659017,
      "trades": 0,
      "funding_rate": 1.5e-05,
      "max_leverage": 10
    },
    "NATGAS": {
      "volume": 638445.299659017,
      "trades": 0,
      "funding_rate": 1.5e-05,
      "max_leverage": 10
    },
    "URNM": {
      "volume": 638445.299659017,
      "trades": 0,
      "funding_rate": 1.5e-05,
      "max_leverage": 10
    }
  },
  "total_open_interest": 136832896.0586579,
  "global_derivatives": [
    {
      "name": "Hyperliquid Perps",
      "chains": [
        "Hyperliquid L1"
      ],
      "volume_24h": 7953730778,
      "volume_7d": 51159976692,
      "change_1d": -21.08,
      "change_7d": -17.43
    },
    {
      "name": "edgeX Perps",
      "chains": [
        "edgeX"
      ],
      "volume_24h": 2670675439,
      "volume_7d": 16684877815,
      "change_1d": 5.21,
      "change_7d": 39.94
    },
    {
      "name": "Aster Perps",
      "chains": [
        "Off Chain"
      ],
      "volume_24h": 2593764356,
      "volume_7d": 17976619020,
      "change_1d": -5.04,
      "change_7d": -4.39
    },
    {
      "name": "tradeXYZ",
      "chains": [
        "Hyperliquid L1"
      ],
      "volume_24h": 2324571325,
      "volume_7d": 12474574050,
      "change_1d": -34.2,
      "change_7d": -15.76
    },
    {
      "name": "Lighter Perps",
      "chains": [
        "zkLighter"
      ],
      "volume_24h": 2280525607,
      "volume_7d": 14954784828,
      "change_1d": 2.13,
      "change_7d": -2.85
    },
    {
      "name": "Grvt Perps",
      "chains": [
        "GRVT"
      ],
      "volume_24h": 1468313783,
      "volume_7d": 10001025643,
      "change_1d": 7.34,
      "change_7d": -12.36
    },
    {
      "name": "Apex Omni",
      "chains": [
        "Ethereum"
      ],
      "volume_24h": 1248951704,
      "volume_7d": 8290925084,
      "change_1d": -2.24,
      "change_7d": 1.19
    },
    {
      "name": "Reya Perps",
      "chains": [
        "ReyaChain"
      ],
      "volume_24h": 956640595,
      "volume_7d": 3120493717,
      "change_1d": 16.08,
      "change_7d": 636.2
    },
    {
      "name": "Variational",
      "chains": [
        "Arbitrum"
      ],
      "volume_24h": 922148210,
      "volume_7d": 6026542782,
      "change_1d": 3.27,
      "change_7d": -30.5
    },
    {
      "name": "StandX Perps",
      "chains": [
        "StandX"
      ],
      "volume_24h": 652738282,
      "volume_7d": 4272186837,
      "change_1d": -19.21,
      "change_7d": 27.62
    },
    {
      "name": "Pacifica",
      "chains": [
        "Solana"
      ],
      "volume_24h": 484904286,
      "volume_7d": 2863355077,
      "change_1d": -15.15,
      "change_7d": 30.49
    },
    {
      "name": "Extended",
      "chains": [
        "Ethereum",
        "Starknet"
      ],
      "volume_24h": 415695147,
      "volume_7d": 2856392358,
      "change_1d": -27.41,
      "change_7d": -5.62
    },
    {
      "name": "Ostium",
      "chains": [
        "Arbitrum"
      ],
      "volume_24h": 407155219,
      "volume_7d": 1418987239,
      "change_1d": 2.1,
      "change_7d": 34.77
    },
    {
      "name": "Nado Perps",
      "chains": [
        "Ink"
      ],
      "volume_24h": 404815219,
      "volume_7d": 2590561007,
      "change_1d": -6.69,
      "change_7d": 5.54
    },
    {
      "name": "Jupiter Perpetual Exchange",
      "chains": [
        "Solana"
      ],
      "volume_24h": 284267743,
      "volume_7d": 1788339312,
      "change_1d": 8.78,
      "change_7d": -21.05
    }
  ],
  "time_windows": {
    "24h": {
      "pacifica_traders": 2225,
      "flashtrade_traders": 1018,
      "jupiter_traders": 2976,
      "adrena_traders": 16,
      "wallet_overlap": {
        "drift_only": 3976,
        "jupiter_only": 2743,
        "pacifica_only": 7667,
        "drift_jupiter": 18,
        "drift_pacifica": 2,
        "jupiter_pacifica": 6,
        "all_three": 1,
        "multi_platform": 27
      },
      "drift_traders": 2123,
      "liquidations": {
        "count": 0,
        "txns": 0,
        "error": "No historical data"
      }
    },
    "1h": {
      "pacifica_traders": 222,
      "jupiter_traders": 213,
      "flashtrade_traders": 64,
      "adrena_traders": 3,
      "drift_traders": 371,
      "wallet_overlap": {
        "drift_only": 3976,
        "jupiter_only": 2743,
        "pacifica_only": 7667,
        "drift_jupiter": 18,
        "drift_pacifica": 2,
        "jupiter_pacifica": 6,
        "all_three": 1,
        "multi_platform": 27
      },
      "liquidations": {
        "count": 0,
        "txns": 0,
        "error": "Query timeout"
      }
    },
    "8h": {
      "pacifica_traders": 890,
      "flashtrade_traders": 316,
      "jupiter_traders": 1089,
      "adrena_traders": 5,
      "drift_traders": 919,
      "liquidations": {
        "count": 0,
        "txns": 0,
        "error": "Query timeout"
      },
      "wallet_overlap": {
        "drift_only": 3976,
        "jupiter_only": 2743,
        "pacifica_only": 7667,
        "drift_jupiter": 18,
        "drift_pacifica": 2,
        "jupiter_pacifica": 6,
        "all_three": 1,
        "multi_platform": 27
      }
    },
    "4h": {
      "pacifica_traders": 556,
      "jupiter_traders": 569,
      "adrena_traders": 4,
      "flashtrade_traders": 179,
      "drift_traders": 660,
      "liquidations": {
        "count": 0,
        "txns": 0,
        "error": "Query timeout"
      },
      "wallet_overlap": {
        "drift_only": 3976,
        "jupiter_only": 2743,
        "pacifica_only": 7667,
        "drift_jupiter": 18,
        "drift_pacifica": 2,
        "jupiter_pacifica": 6,
        "all_three": 1,
        "multi_platform": 27
      }
    }
  },
  "whale_activity": {
    "whales": [
      {
        "address": "9wfZgKKk6ppDAxtbBP2hPgYHpbGU7oVscaGCkhZJAhXn",
        "source": "pacifica",
        "pnl_24h": 12295.196916,
        "volume": 0.0,
        "recent_txns": [
          {
            "signature": "ksGSWpnsSkzgBhfhKHHfDAUmsrbxpo6kaJHPc6DXvLGfg8kaMiBPS5SWw6GgReBXmuXJyuUqAHqxeJxJYqpPLyF",
            "timestamp": "2026-03-09T13:45:32",
            "success": true,
            "slot": 405264935
          },
          {
            "signature": "3yTNZbHiEdrtyTweUXtFLydKs2QLduKbmsERMDht8vnrhh8T851nXTUtC6jYK15S995ioMVRGyaxv5J57BWyPqHK",
            "timestamp": "2026-03-09T13:45:16",
            "success": true,
            "slot": 405264895
          },
          {
            "signature": "2CHPxzTXFe9YdMCpt7yCAXGgP8MMxGJW5E9UU1Ai4FJeLhtJzRheuu4VYrUYbpywwMcJFuxg1zkpfukixN8BQ65J",
            "timestamp": "2026-03-08T19:15:26",
            "success": true,
            "slot": 405095624
          },
          {
            "signature": "4fqpwxgqT4mq92uor4ziewvqegHdaxqngpaTBKFsHfnaMjscDpkUPcVvuuTcjXenLiGi2S2iewCp7KMshxTLtGMz",
            "timestamp": "2026-03-08T19:15:10",
            "success": true,
            "slot": 405095581
          },
          {
            "signature": "4ZHqoNWDdPHrkfYv2B8i3jBwDsKKGCj8RuAhtrLexBQPCJZ8K8vNgVyQ9vDvC6jNTJGZ98sMSM7YBYMuf7cV6mJN",
            "timestamp": "2026-03-06T14:26:22",
            "success": true,
            "slot": 404614035
          }
        ],
        "txn_count_1h": 0,
        "is_active": false
      },
      {
        "address": "BEE2vnGCXdt8x1PyaKBjghBEKJhzsnHEXLAkBkvbTFL4",
        "source": "pacifica",
        "pnl_24h": 7590.549244,
        "volume": 190065.248009,
        "recent_txns": [],
        "txn_count_1h": 0,
        "is_active": false
      },
      {
        "address": "8AsJfKorQc1Wz8DABe9FZH18cgLd43bYwFST5JBJYSit",
        "source": "pacifica",
        "pnl_24h": 7072.341212,
        "volume": 0.0,
        "recent_txns": [],
        "txn_count_1h": 0,
        "is_active": false
      },
      {
        "address": "24q6voXjHkM3hZmMJPikHTJ7KmEuYyr1tJGLrT8CNWe3",
        "source": "pacifica",
        "pnl_24h": 6948.183907,
        "volume": 0.0,
        "recent_txns": [],
        "txn_count_1h": 0,
        "is_active": false
      },
      {
        "address": "6nkGPkKjJJqJRZQj1rCFUyfftFRzyKPGpfSZDXr5YuGd",
        "source": "pacifica",
        "pnl_24h": 5414.720796,
        "volume": 0.0,
        "recent_txns": [],
        "txn_count_1h": 0,
        "is_active": false
      },
      {
        "address": "Eu12Nqn4v2atnTqNb8MwYnC4kxDpv7dVgnhxPcru1bGt",
        "source": "pacifica",
        "pnl_24h": 5381.026332,
        "volume": 241044.464274,
        "recent_txns": [],
        "txn_count_1h": 0,
        "is_active": false
      },
      {
        "address": "4X1i2FRVBH6gU3psoLW6AirJSCeRi8eKsBHTyrizL1gJ",
        "source": "pacifica",
        "pnl_24h": 5036.401021,
        "volume": 0.0,
        "recent_txns": [],
        "txn_count_1h": 0,
        "is_active": false
      },
      {
        "address": "BtGmu8gixQcNzADq4JHy9qpHUfwXDNoAo6CvUwTMNA3D",
        "source": "pacifica",
        "pnl_24h": 4843.673827,
        "volume": 40111.67674,
        "recent_txns": [],
        "txn_count_1h": 0,
        "is_active": false
      },
      {
        "address": "5RX2DD425DHj3VAouTbJWHtmBmzi2oUmuErwmfwgxs8n",
        "source": "pacifica",
        "pnl_24h": 4802.091179,
        "volume": 184212.0,
        "recent_txns": [],
        "txn_count_1h": 0,
        "is_active": false
      },
      {
        "address": "JPLaNo52siAC6KDv66VP9y4eKKtNhwx6yKd8GFcjFGP",
        "source": "pacifica",
        "pnl_24h": 4575.757517,
        "volume": 0.0,
        "recent_txns": [],
        "txn_count_1h": 0,
        "is_active": false
      }
    ],
    "total_whales": 10,
    "active_last_1h": 0,
    "timestamp": "2026-03-11T10:57:17.385128Z"
  },
  "liquidations_rpc": {
    "drift": {
      "liquidations": [],
      "count": 0,
      "count_1h": 0,
      "checked_transactions": 45,
      "timestamp": "2026-03-11T11:01:22.188933Z"
    },
    "jupiter": {
      "liquidations": [],
      "count": 0,
      "count_1h": 0,
      "checked_transactions": 14,
      "timestamp": "2026-03-11T11:03:03.584187Z"
    },
    "total_count": 0,
    "total_count_1h": 0,
    "timestamp": "2026-03-11T11:03:03.584549Z"
  },
  "drift_traders_1h": 371,
  "jupiter_traders_1h": 213,
  "liquidations_1h": {
    "count": 0,
    "txns": 0,
    "error": "Query timeout"
  },
  "wallet_overlap": {
    "drift_only": 3976,
    "jupiter_only": 2743,
    "pacifica_only": 7667,
    "drift_jupiter": 18,
    "drift_pacifica": 2,
    "jupiter_pacifica": 6,
    "all_three": 1,
    "multi_platform": 27
  },
  "pnl_leaderboard": {
    "jupiter": {
      "top_winners": [
        {
          "address": "ELKzK9zoQ82hpuGmKtCUMWxcJmXg5mzHzBX8UQF9XSwu",
          "pnl_weekly": 39409.090564,
          "volume_weekly": 21646701.164896,
          "markets": [
            "SOL",
            "ETH"
          ]
        },
        {
          "address": "3DcBEVDt5yoyxt2rxXZNqbSdRzGF3By8wkMiPo9cHrJf",
          "pnl_weekly": 32513.197985,
          "volume_weekly": 852672.861107,
          "markets": [
            "SOL"
          ]
        },
        {
          "address": "3SjKGZJhQxCGYZfAFTSgwfPf9XkeQ8YAp82wuxDKxRun",
          "pnl_weekly": 30344.814901,
          "volume_weekly": 30382351.541686,
          "markets": [
            "BTC"
          ]
        },
        {
          "address": "3nKcFenbyzn7tLTuHEKUz93eEF2VXLS2v8N8pDd3Qxdw",
          "pnl_weekly": 24785.668155,
          "volume_weekly": 32713357.068243,
          "markets": [
            "BTC"
          ]
        },
        {
          "address": "HDHifNWcCWkovBTUcVJCNBFGhHGshTsC22Nq6z9w5bDj",
          "pnl_weekly": 20849.12093,
          "volume_weekly": 2706978.154404,
          "markets": [
            "SOL"
          ]
        },
        {
          "address": "BJiBCwx1EvEiGoQc7Yc36jQzU5iSyF4dsuQY8DkgftoX",
          "pnl_weekly": 18389.972403,
          "volume_weekly": 3018946.149482,
          "markets": [
            "ETH"
          ]
        },
        {
          "address": "3dqwqVUpc3y4L9ESryUfAr6ouUDTsZs3VEj25iEoXhcm",
          "pnl_weekly": 15243.374824999999,
          "volume_weekly": 2336540.56753,
          "markets": [
            "SOL",
            "BTC"
          ]
        },
        {
          "address": "3f6YvTGoe9nvoMiBSUCjpJkvw5Yoo6i7TZYL8dggaPCs",
          "pnl_weekly": 13169.464324,
          "volume_weekly": 3970210.071287,
          "markets": [
            "BTC"
          ]
        },
        {
          "address": "A88uMtYGRx5CF4TT8L4L7KxjbPeW1o21mKMwfNcmH1db",
          "pnl_weekly": 12214.174273,
          "volume_weekly": 1674341.393494,
          "markets": [
            "SOL"
          ]
        },
        {
          "address": "8JiAdUj4ArJRbbwJz5ESSVCew3B8Mw6nFGSAFV1Zav5g",
          "pnl_weekly": 11306.519572,
          "volume_weekly": 3103966.195597,
          "markets": [
            "SOL"
          ]
        },
        {
          "address": "DtgRnRA2UWdsRnq9mwc3ir8exBZpbJAsNgbXRHBPUmov",
          "pnl_weekly": 11265.764122999999,
          "volume_weekly": 2842802.010101,
          "markets": [
            "SOL",
            "BTC"
          ]
        },
        {
          "address": "H3ogGm2QeDiELWVVo5pyn9ddZhZyxpoGzgEFe6Wng4BQ",
          "pnl_weekly": 10188.393339,
          "volume_weekly": 1521816.466952,
          "markets": [
            "BTC"
          ]
        },
        {
          "address": "Ed5iwDCZrq8P744F6UprVKMJnWr5M6Rudg3jiDYf5K7x",
          "pnl_weekly": 9723.936094,
          "volume_weekly": 535084.03624,
          "markets": [
            "BTC"
          ]
        },
        {
          "address": "5TdTFGzKKmjQ1XEenkjwg8mEB4D9g3hwtXHDxoVtNLYU",
          "pnl_weekly": 8922.826668,
          "volume_weekly": 2442858.097002,
          "markets": [
            "SOL"
          ]
        },
        {
          "address": "CmabgHMvCjPoeox9qoeXefAehCbAo1bwoAGypUxTcKYZ",
          "pnl_weekly": 8865.822889,
          "volume_weekly": 1075358.675534,
          "markets": [
            "BTC"
          ]
        },
        {
          "address": "8LSbht8vP6eWoQsA3VKwx37Sjq9VtJYfHCjvD3JcJG2s",
          "pnl_weekly": 8772.218239,
          "volume_weekly": 599223.27584,
          "markets": [
            "SOL"
          ]
        },
        {
          "address": "8S5NL2RdAh33VddCNR68QtKK7MJDNpzdBeGsFKkJFo4W",
          "pnl_weekly": 8471.513011,
          "volume_weekly": 542793.535464,
          "markets": [
            "SOL"
          ]
        },
        {
          "address": "GwaexMeUDzFZ25mPR9ze16SNZA6pUyvG41twjXWxqD9e",
          "pnl_weekly": 7986.018281,
          "volume_weekly": 448234.041557,
          "markets": [
            "SOL"
          ]
        },
        {
          "address": "6tMkuGcKr2sF1k9x8GfpWkYxqCz17QvWwMB3bxbXPucr",
          "pnl_weekly": 7940.461347,
          "volume_weekly": 2890223.248004,
          "markets": [
            "BTC",
            "ETH"
          ]
        },
        {
          "address": "Gnm7e1Gq2SVNRRiK2NyjA4Y8vUZ3Ptu2N9Bn7Hx98wGb",
          "pnl_weekly": 7751.317607,
          "volume_weekly": 16984844.176566,
          "markets": [
            "SOL"
          ]
        },
        {
          "address": "6jzAeBgd5SEpP2yVE2us5pmzvg1y4D2XUG6yP6zrRpe3",
          "pnl_weekly": 7651.50861,
          "volume_weekly": 580502.781144,
          "markets": [
            "BTC"
          ]
        },
        {
          "address": "DDi82f6PX6F4LM5UVEZ557783FEohvxWKL4gtz2rcppw",
          "pnl_weekly": 7535.425241,
          "volume_weekly": 420728.305518,
          "markets": [
            "SOL"
          ]
        },
        {
          "address": "EcVSiiR3DFbTB9kUHWRiN4gJUd6TrxKofKjk4t6JoqV",
          "pnl_weekly": 7173.952542,
          "volume_weekly": 6977454.39035,
          "markets": [
            "SOL"
          ]
        },
        {
          "address": "51RCSrHE2sirEtEHmZUHFrZoHnBznXmUHAcyjYGxmm8D",
          "pnl_weekly": 6638.12819,
          "volume_weekly": 1961975.178732,
          "markets": [
            "SOL"
          ]
        },
        {
          "address": "97u89o2Kafqh6StNvrHBUJNvuATAQJZP7FeQCKfuUEy3",
          "pnl_weekly": 6405.216258,
          "volume_weekly": 10039416.236818,
          "markets": [
            "SOL"
          ]
        },
        {
          "address": "HqvFqVrdBJpUNpvGWU38vargogtgokaWo8wNaVpah5rA",
          "pnl_weekly": 6014.465604,
          "volume_weekly": 1954227.454246,
          "markets": [
            "SOL"
          ]
        },
        {
          "address": "GKT2j5gPqY2ZKfhaGB5cn5bTHLSKTUrULe8wG1QwmLpt",
          "pnl_weekly": 5854.060303,
          "volume_weekly": 337704.593412,
          "markets": [
            "SOL",
            "BTC",
            "ETH"
          ]
        },
        {
          "address": "4SuVPsK9wrCpxnW8Do2a2bEJVoosG9WfVeRqMiFhp7yq",
          "pnl_weekly": 5620.725121,
          "volume_weekly": 553943.293261,
          "markets": [
            "SOL",
            "BTC"
          ]
        },
        {
          "address": "8Gx2j96gJvFSFP9zfwXhmCHfsWskL7Ym9dUBgcbVmCKz",
          "pnl_weekly": 5422.179261,
          "volume_weekly": 13459.617636,
          "markets": [
            "SOL"
          ]
        },
        {
          "address": "GpEfJgYawNYAznQbReu6sDdB6RcFF9o8TQanUSZBq8ST",
          "pnl_weekly": 5403.152669,
          "volume_weekly": 898750.636686,
          "markets": [
            "BTC"
          ]
        },
        {
          "address": "HHXuNANV9fLZzd1ga9GJingeceLHyT9Q7vHX1GDY8XVa",
          "pnl_weekly": 5363.914958,
          "volume_weekly": 4030237.326524,
          "markets": [
            "SOL"
          ]
        },
        {
          "address": "4Qb4oekTkM6DXTtH9FrvhKMcsC3aR758i8LnsshzFPnU",
          "pnl_weekly": 5354.837971,
          "volume_weekly": 682454.290206,
          "markets": [
            "BTC"
          ]
        },
        {
          "address": "AfCwBaCk1Gsh2MKZoXzm44VLZAGDVikPwPS6YXuHen2g",
          "pnl_weekly": 5128.553233,
          "volume_weekly": 295616.824736,
          "markets": [
            "SOL"
          ]
        },
        {
          "address": "6KDJ2pP32JtjYCCDHWqSMauKUfGbX4w6MXkkUEYpcgTt",
          "pnl_weekly": 5096.227034,
          "volume_weekly": 880995.601131,
          "markets": [
            "BTC"
          ]
        },
        {
          "address": "6Nyfd6nxV4FxvpHc1368uMcZhJYBpUKxFEeEByGrWk9S",
          "pnl_weekly": 4995.104091,
          "volume_weekly": 362033.39866,
          "markets": [
            "SOL"
          ]
        },
        {
          "address": "J89jkZJKD75FDkQpbw27qT1fefZocEFScfbFpMyqkpBU",
          "pnl_weekly": 4937.490391,
          "volume_weekly": 567744.701755,
          "markets": [
            "BTC"
          ]
        },
        {
          "address": "QZtvuPdyk5xTV8VbQkWxdc9EV7Bpd9J4KEpy6rzucyN",
          "pnl_weekly": 4650.740449,
          "volume_weekly": 540205.044121,
          "markets": [
            "SOL"
          ]
        },
        {
          "address": "64NqLKgMPQvcJoD27Mu9Zzb6s5dBpmTWR9JnCjNSgvKJ",
          "pnl_weekly": 4413.7856790000005,
          "volume_weekly": 438508.761266,
          "markets": [
            "SOL",
            "BTC"
          ]
        },
        {
          "address": "BLoGbQztmVScom7ZHhYA3KYjDjwpW68iG7KiybbKygaw",
          "pnl_weekly": 4294.238424,
          "volume_weekly": 757744.377649,
          "markets": [
            "SOL"
          ]
        },
        {
          "address": "65RbREKP7P5xF5cNNhHu2RYMid9hMxbFv7TNpWNceFqp",
          "pnl_weekly": 4238.25759,
          "volume_weekly": 281356.14668,
          "markets": [
            "BTC"
          ]
        },
        {
          "address": "Aa4Y2KR2tECbtDCfv9c6tukjSUFC98ToHwTvq7hqjw9o",
          "pnl_weekly": 4133.065819,
          "volume_weekly": 1580731.931639,
          "markets": [
            "SOL"
          ]
        },
        {
          "address": "EHFYDB9MTc9yxdJ3MESGNFgpdmmMSTwAGJwvPGbbok5K",
          "pnl_weekly": 4042.16829,
          "volume_weekly": 557525.788445,
          "markets": [
            "ETH"
          ]
        },
        {
          "address": "7RkHDnsthgxVYZARFtPrq3bDv2T65419eUK2MiDjdQkB",
          "pnl_weekly": 4038.414951,
          "volume_weekly": 59877.142785,
          "markets": [
            "SOL"
          ]
        },
        {
          "address": "GJtNZfTqyioZpeNCMzm2DwxDvJFqSKUdQEGoQBpY71Yj",
          "pnl_weekly": 3912.884729,
          "volume_weekly": 2104630.348844,
          "markets": [
            "SOL"
          ]
        },
        {
          "address": "43S5gbuHtC3UQxhdEzJpts1S1afmCqoGUEFx5iUhMznM",
          "pnl_weekly": 3706.267943,
          "volume_weekly": 168432.99111,
          "markets": [
            "SOL"
          ]
        },
        {
          "address": "6BYbywhoyt6Dy31TULdMJ6c53JHhVQ1hyYY6w9Kk6mEw",
          "pnl_weekly": 3462.691421,
          "volume_weekly": 579191.27256,
          "markets": [
            "BTC"
          ]
        },
        {
          "address": "7q1FMC5NVUhiuCMfs8D6pFaWjj8rGWGVLbsi2EuLrXe3",
          "pnl_weekly": 3378.744986,
          "volume_weekly": 2910761.613346,
          "markets": [
            "BTC"
          ]
        },
        {
          "address": "FP5XrBnLKHLjtDegztUpKgvv4km4cGsyZUWU2tPodaDp",
          "pnl_weekly": 3357.998612,
          "volume_weekly": 169792.114069,
          "markets": [
            "SOL"
          ]
        },
        {
          "address": "3bhB6Szp8ox6AThnW1BEMqSFmUQ7CxQ5WfTQYyQBaV4M",
          "pnl_weekly": 3258.513839,
          "volume_weekly": 3815201.267434,
          "markets": [
            "SOL"
          ]
        },
        {
          "address": "FGYoZNf5QfKndJ1vXeUPN4cfwjhomemKHM4DGbxeYkCx",
          "pnl_weekly": 3250.369622,
          "volume_weekly": 1419877.39242,
          "markets": [
            "BTC"
          ]
        }
      ],
      "top_losers": [],
      "total_traders": 142
    },
    "pacifica": {
      "top_winners": [
        {
          "address": "9wfZgKKk6ppDAxtbBP2hPgYHpbGU7oVscaGCkhZJAhXn",
          "pnl_24h": 12295.196916,
          "pnl_7d": 19117.239034,
          "pnl_30d": -44387.224843,
          "pnl_all_time": -44387.224843,
          "volume_24h": 0.0,
          "volume_7d": 66.51356,
          "equity": 90799.466447
        },
        {
          "address": "BEE2vnGCXdt8x1PyaKBjghBEKJhzsnHEXLAkBkvbTFL4",
          "pnl_24h": 7590.549244,
          "pnl_7d": 14899.099579,
          "pnl_30d": -41997.138858,
          "pnl_all_time": -136628.15647,
          "volume_24h": 190065.248009,
          "volume_7d": 1462520.936703,
          "equity": 149248.94353
        },
        {
          "address": "8AsJfKorQc1Wz8DABe9FZH18cgLd43bYwFST5JBJYSit",
          "pnl_24h": 7072.341212,
          "pnl_7d": 11788.140404,
          "pnl_30d": -18316.922604,
          "pnl_all_time": -54743.106772,
          "volume_24h": 0.0,
          "volume_7d": 137.99603,
          "equity": 70103.395456
        },
        {
          "address": "24q6voXjHkM3hZmMJPikHTJ7KmEuYyr1tJGLrT8CNWe3",
          "pnl_24h": 6948.183907,
          "pnl_7d": 10801.493835,
          "pnl_30d": -7618.242784,
          "pnl_all_time": 27599.844991,
          "volume_24h": 0.0,
          "volume_7d": 33.2242,
          "equity": 77613.438437
        },
        {
          "address": "6nkGPkKjJJqJRZQj1rCFUyfftFRzyKPGpfSZDXr5YuGd",
          "pnl_24h": 5414.720796,
          "pnl_7d": 15770.295952,
          "pnl_30d": 6541.51579,
          "pnl_all_time": 109172.321332,
          "volume_24h": 0.0,
          "volume_7d": 39960.852717,
          "equity": 164369.0426
        },
        {
          "address": "Eu12Nqn4v2atnTqNb8MwYnC4kxDpv7dVgnhxPcru1bGt",
          "pnl_24h": 5381.026332,
          "pnl_7d": 7461.736832,
          "pnl_30d": 24362.822434,
          "pnl_all_time": -356115.763445,
          "volume_24h": 241044.464274,
          "volume_7d": 2325835.441096,
          "equity": 943876.508229
        },
        {
          "address": "4X1i2FRVBH6gU3psoLW6AirJSCeRi8eKsBHTyrizL1gJ",
          "pnl_24h": 5036.401021,
          "pnl_7d": 6132.658231,
          "pnl_30d": -4922.990295,
          "pnl_all_time": 82893.138911,
          "volume_24h": 0.0,
          "volume_7d": 0.0,
          "equity": 158977.089083
        },
        {
          "address": "BtGmu8gixQcNzADq4JHy9qpHUfwXDNoAo6CvUwTMNA3D",
          "pnl_24h": 4843.673827,
          "pnl_7d": 8080.146785,
          "pnl_30d": 1907.782252,
          "pnl_all_time": 46913.46035,
          "volume_24h": 40111.67674,
          "volume_7d": 146863.57504,
          "equity": 146913.46035
        },
        {
          "address": "5RX2DD425DHj3VAouTbJWHtmBmzi2oUmuErwmfwgxs8n",
          "pnl_24h": 4802.091179,
          "pnl_7d": 13072.425713,
          "pnl_30d": 29839.026218,
          "pnl_all_time": 39427.718427,
          "volume_24h": 184212.0,
          "volume_7d": 315630.7309,
          "equity": 109759.752067
        },
        {
          "address": "JPLaNo52siAC6KDv66VP9y4eKKtNhwx6yKd8GFcjFGP",
          "pnl_24h": 4575.757517,
          "pnl_7d": 6885.111328,
          "pnl_30d": -8285.193829,
          "pnl_all_time": 93673.129763,
          "volume_24h": 0.0,
          "volume_7d": 0.0,
          "equity": 93246.530656
        },
        {
          "address": "CftUjvv5sEPrnUE8XBcXu4q4Mc88TqGtrfkwStCX6Ci3",
          "pnl_24h": 4336.633126,
          "pnl_7d": 18034.313069,
          "pnl_30d": 5678.876293,
          "pnl_all_time": -47871.681954,
          "volume_24h": 33127.709272,
          "volume_7d": 49900.551322,
          "equity": 119300.223481
        },
        {
          "address": "DQqre2oHthtWjLTGumJYL75muQFpjd2MsUcky2181uUQ",
          "pnl_24h": 4184.438335,
          "pnl_7d": -18402.258868,
          "pnl_30d": -28502.944112,
          "pnl_all_time": -56632.692338,
          "volume_24h": 6.9916,
          "volume_7d": 1102948.15625,
          "equity": 40902.825745
        },
        {
          "address": "7vGrhH228veSsrQ7rTQL2XUr3QdNgeuYDDngT7uCK2S4",
          "pnl_24h": 3556.875092,
          "pnl_7d": -1453.50154,
          "pnl_30d": 9428.681343,
          "pnl_all_time": 28927.442912,
          "volume_24h": 82962.87,
          "volume_7d": 581062.29798,
          "equity": 59542.543723
        },
        {
          "address": "PCF8xwewcLmibAPnJcvydHoJ4VKKoxkGdbcbJqRdUSx",
          "pnl_24h": 3491.747133,
          "pnl_7d": 666.137595,
          "pnl_30d": 933.710542,
          "pnl_all_time": 110853.365947,
          "volume_24h": 2053328.89677,
          "volume_7d": 17955652.547562,
          "equity": 181853.365947
        },
        {
          "address": "HDw3NtMgoEJHv8kcNqAfDWjPXhWW6nCwEVzA9aUcbw4L",
          "pnl_24h": 3171.619518,
          "pnl_7d": 15079.423163,
          "pnl_30d": 15079.423163,
          "pnl_all_time": 15079.423163,
          "volume_24h": 10650633.702636,
          "volume_7d": 35568387.396616,
          "equity": 92936.285522
        },
        {
          "address": "BdfP9hwXKyZMcKf99f2K6QWkU2bcEy5tmCBEG1RazEDx",
          "pnl_24h": 3169.140156,
          "pnl_7d": 4928.112172,
          "pnl_30d": -14188.302262,
          "pnl_all_time": -14188.302262,
          "volume_24h": 0.0,
          "volume_7d": 43.15288,
          "equity": 21420.490983
        },
        {
          "address": "7RGfPRVtWfB2DywdCEt6oz9Xk9Hyjjh8vUsTbcnizTJd",
          "pnl_24h": 3161.988197,
          "pnl_7d": -150.188129,
          "pnl_30d": 13483.233152,
          "pnl_all_time": 48274.398766,
          "volume_24h": 1187563.90868,
          "volume_7d": 3913803.48975,
          "equity": 349115.138766
        },
        {
          "address": "GowcbjHQosYvDT4BWSfvS7B76VrfKayq5AZocFeyCjrQ",
          "pnl_24h": 3042.208283,
          "pnl_7d": 8896.593515,
          "pnl_30d": -7778.671339,
          "pnl_all_time": 45638.161331,
          "volume_24h": 1.0115,
          "volume_7d": 66331.4654,
          "equity": 94482.340429
        },
        {
          "address": "49R9MFU7JopaCFXtpTwbaX8rkNW9wX6ddi7VtLUtMYJ1",
          "pnl_24h": 3009.755185,
          "pnl_7d": 2324.035805,
          "pnl_30d": 14793.78517,
          "pnl_all_time": 33403.873288,
          "volume_24h": 1e-06,
          "volume_7d": 21512.666701,
          "equity": 294158.776989
        },
        {
          "address": "ADrHFm9418oZcBAvaqdtnfkRCh8B2vThAe1eAdyhvxDM",
          "pnl_24h": 2955.207735,
          "pnl_7d": 4712.237972,
          "pnl_30d": -7766.708612,
          "pnl_all_time": 21537.957891,
          "volume_24h": 0.0,
          "volume_7d": 14630.55117,
          "equity": 42112.51933
        },
        {
          "address": "8hCTAcoQSRUtZkzcA76DaPYGE9V8jtFcftE2WmMxF4Se",
          "pnl_24h": 2673.951216,
          "pnl_7d": 4157.179932,
          "pnl_30d": -2930.984214,
          "pnl_all_time": 41315.692655,
          "volume_24h": 0.0,
          "volume_7d": 0.0,
          "equity": 48986.727737
        },
        {
          "address": "FA7pLr6XNF7JdSQzSWRe5GD3dyuRruAXiPWMnjP5y2up",
          "pnl_24h": 2575.356595,
          "pnl_7d": 3045.519623,
          "pnl_30d": -1651.233485,
          "pnl_all_time": -43081.366409,
          "volume_24h": 71182.35428,
          "volume_7d": 891338.63741,
          "equity": 42487.680422
        },
        {
          "address": "Fpo38LdtQQPxnr7DHxBESPtC6gwr18RwVvcxgLTra8fj",
          "pnl_24h": 2298.315768,
          "pnl_7d": -338.113573,
          "pnl_30d": -24613.362543,
          "pnl_all_time": -6207.551874,
          "volume_24h": 303759.91789,
          "volume_7d": 428221.70325,
          "equity": 20044.378838
        },
        {
          "address": "6GcT3aY8VcyaC6yBKewKQqLJekdnfkTv8J44Q58zTwYD",
          "pnl_24h": 2148.567561,
          "pnl_7d": 3579.702347,
          "pnl_30d": -3968.4118,
          "pnl_all_time": -31331.665111,
          "volume_24h": 0.0,
          "volume_7d": 0.0,
          "equity": 97667.334889
        },
        {
          "address": "CWaEyMSHwEQFqg8uYFk6rrKfgiVqNFkT4YcHWgPaixw4",
          "pnl_24h": 2026.886252,
          "pnl_7d": -3413.226725,
          "pnl_30d": -6974.005463,
          "pnl_all_time": -15316.475838,
          "volume_24h": 443348.6954,
          "volume_7d": 837642.719876,
          "equity": 23227.006623
        },
        {
          "address": "296PcXq7TUGrjzfBEjSFs3qrhNXiTxuteJKaoPDivo5e",
          "pnl_24h": 2022.679572,
          "pnl_7d": 3451.921273,
          "pnl_30d": -4288.37174,
          "pnl_all_time": -84253.312736,
          "volume_24h": 0.0,
          "volume_7d": 0.0,
          "equity": 88644.187264
        },
        {
          "address": "Ep1d8JdFw4FnB85XDgXGVabYutro4JzK285HQqW6TZE2",
          "pnl_24h": 1836.233471,
          "pnl_7d": 4996.468278,
          "pnl_30d": 20244.341471,
          "pnl_all_time": 61591.599079,
          "volume_24h": 1005492.92528,
          "volume_7d": 5661287.453623,
          "equity": 261591.599079
        },
        {
          "address": "97Nq39YDZq77pfPY97RLA8ScBbPapQEwkDUjYNZiuMUd",
          "pnl_24h": 1689.743621,
          "pnl_7d": 17306.728347,
          "pnl_30d": 85576.661111,
          "pnl_all_time": 50165.580111,
          "volume_24h": 0.0,
          "volume_7d": 14039.87033,
          "equity": 105316.441382
        },
        {
          "address": "BRZWPu71n5pAzs95TzkbfvBfzmCgKvq2oSFFAbi2uJsX",
          "pnl_24h": 1569.570219,
          "pnl_7d": 4952.037341,
          "pnl_30d": 1472.785218,
          "pnl_all_time": 18131.471879,
          "volume_24h": 0.0,
          "volume_7d": 71025.5,
          "equity": 59124.662364
        },
        {
          "address": "AXEVQqY6oj2doJpC6zR4esnEZcijWtn1G1E9MArmi2rj",
          "pnl_24h": 1569.570219,
          "pnl_7d": -1627.841635,
          "pnl_30d": -1515.840711,
          "pnl_all_time": -2491.647267,
          "volume_24h": 0.0,
          "volume_7d": 303268.4,
          "equity": 8486.106739
        },
        {
          "address": "P3BSKpoDFx7i9ioLchg7XZXGWATz1McaNy9t7oDo7LF",
          "pnl_24h": 1471.848472,
          "pnl_7d": 2517.885578,
          "pnl_30d": -2658.426432,
          "pnl_all_time": -124615.788104,
          "volume_24h": 23998.07672,
          "volume_7d": 77977.47235,
          "equity": 45373.668978
        },
        {
          "address": "HCAKppBaWY5HcmBrk8ALBUnsm9ZzvkoxpinAq9Je6ci1",
          "pnl_24h": 1417.377414,
          "pnl_7d": 2558.812038,
          "pnl_30d": 44.121865,
          "pnl_all_time": 85428.287027,
          "volume_24h": 5392.15044,
          "volume_7d": 37356.0481,
          "equity": 37316.749775
        },
        {
          "address": "DbB3TxHkGEA5jLY7DCbxbQWRNVrteUbHBhYwAgwL5TJh",
          "pnl_24h": 1367.341277,
          "pnl_7d": 2772.020253,
          "pnl_30d": 6153.558437,
          "pnl_all_time": 39463.615092,
          "volume_24h": 1174.7484,
          "volume_7d": 49122.33994,
          "equity": 180212.948144
        },
        {
          "address": "4pTfJtAQ2xPrrAAyULsJDgGc3YzGf1ZzqnUVnXdK6K3K",
          "pnl_24h": 1334.3347,
          "pnl_7d": 7916.102597,
          "pnl_30d": 15906.665586,
          "pnl_all_time": 41442.627433,
          "volume_24h": 12250.42199,
          "volume_7d": 30451.57171,
          "equity": 58452.87658
        },
        {
          "address": "GDoEJ87ezVKgFXQ9N4RpPuUVrPKfhitLQpgkHczJUPVL",
          "pnl_24h": 1321.583908,
          "pnl_7d": 2720.804415,
          "pnl_30d": -10527.810158,
          "pnl_all_time": 28107.650964,
          "volume_24h": 0.0,
          "volume_7d": 22768.40484,
          "equity": 128107.650964
        },
        {
          "address": "77d5VNEQcpiD3vfQDWZhxPy2nhSwaJtFCJJxLBy9kxn4",
          "pnl_24h": 1308.153899,
          "pnl_7d": 3523.543212,
          "pnl_30d": -2241.536331,
          "pnl_all_time": 33449.315604,
          "volume_24h": 0.0,
          "volume_7d": 0.0,
          "equity": 11102.466414
        },
        {
          "address": "Hr5WFpPR9xUwD5WVWYKoLYbNKUaTAx2mn3B147KDgMAc",
          "pnl_24h": 1307.917382,
          "pnl_7d": 2746.717488,
          "pnl_30d": -9354.504101,
          "pnl_all_time": 54283.599112,
          "volume_24h": 0.0,
          "volume_7d": 22768.40484,
          "equity": 154283.599112
        },
        {
          "address": "CcBkvidmanT6zHGQPRHXDHgLq7M6fazaAVajTEAGoCMf",
          "pnl_24h": 1277.364568,
          "pnl_7d": 2912.008645,
          "pnl_30d": -4299.187662,
          "pnl_all_time": 18956.957908,
          "volume_24h": 0.0,
          "volume_7d": 3483.2,
          "equity": 41482.249664
        },
        {
          "address": "EnyGXUNtJ2YwShtKzXqvRoE3jkcqzoekhP9BMm5f8EfY",
          "pnl_24h": 1229.242264,
          "pnl_7d": 3024.614247,
          "pnl_30d": -7838.45461,
          "pnl_all_time": -6297.523391,
          "volume_24h": 0.0,
          "volume_7d": 0.0,
          "equity": 17702.476609
        },
        {
          "address": "AqVGeyoFiMkgdXPZEDkXetXm2n1dNPEocfRpBwDUX4yn",
          "pnl_24h": 1213.105746,
          "pnl_7d": 513.194392,
          "pnl_30d": -28854.996191,
          "pnl_all_time": -78893.449438,
          "volume_24h": 0.0,
          "volume_7d": 2521742.303031,
          "equity": 49229.138357
        },
        {
          "address": "VkWqsftybVVBbRHcX36nB4CCiH4HDgKUPnv5U5Jv6a8",
          "pnl_24h": 1172.497251,
          "pnl_7d": 80.286211,
          "pnl_30d": -4445.441149,
          "pnl_all_time": 15229.825338,
          "volume_24h": 13.269,
          "volume_7d": 146754.9688,
          "equity": 25758.867583
        },
        {
          "address": "CfL5CLM67JHqqVgcnp4Pu6TTF8Krsv6Ck5KndYydzWkP",
          "pnl_24h": 1159.026231,
          "pnl_7d": 373.653963,
          "pnl_30d": -169.501692,
          "pnl_all_time": 8043.547067,
          "volume_24h": 1e-06,
          "volume_7d": 1339.019881,
          "equity": 33168.977558
        },
        {
          "address": "xTfdyNb16wMh7dAvCXHjAifj5bVFYv8URss1sXhuzdQ",
          "pnl_24h": 1128.462368,
          "pnl_7d": 4760.999832,
          "pnl_30d": 10478.906855,
          "pnl_all_time": 14937.439551,
          "volume_24h": 0.0,
          "volume_7d": 142193.84,
          "equity": 44780.220638
        },
        {
          "address": "EbaoY81MhbrXiP52Nk35XTeYDLwaiKooLMWgfNMBJnpf",
          "pnl_24h": 1084.578249,
          "pnl_7d": 2072.870748,
          "pnl_30d": 2768.062966,
          "pnl_all_time": 3637.063293,
          "volume_24h": 612.0036,
          "volume_7d": 17611.60209,
          "equity": 85591.779518
        },
        {
          "address": "49Gafuqnn7fDJFSpSJHvWW44fBvDQqNNmXq5Mhx7W1tH",
          "pnl_24h": 1052.158046,
          "pnl_7d": 2356.906146,
          "pnl_30d": 12645.897581,
          "pnl_all_time": 12645.897581,
          "volume_24h": 23155.82284,
          "volume_7d": 23155.82284,
          "equity": 16953.775785
        },
        {
          "address": "DtKUycJJbJZ1qyhYEMD2kQBYyouK74wFGmExjnoEBoGc",
          "pnl_24h": 1020.583565,
          "pnl_7d": 4045.574898,
          "pnl_30d": 4045.574899,
          "pnl_all_time": 1379.162486,
          "volume_24h": 0.0,
          "volume_7d": 92546.606358,
          "equity": 5888.336634
        },
        {
          "address": "92yvyDPdeZtpUh5gYhs1jbdtNdmGiYwsVJMaZ9PgEwio",
          "pnl_24h": 973.133536,
          "pnl_7d": 446.781616,
          "pnl_30d": -4592.867104,
          "pnl_all_time": -5049.221952,
          "volume_24h": 0.0,
          "volume_7d": 151985.42851,
          "equity": 4571.832896
        },
        {
          "address": "HUJ6vMaTTg9RXqWq9DcjXbgCryECzcz9SuCe1tLTZA95",
          "pnl_24h": 871.498632,
          "pnl_7d": 972.146402,
          "pnl_30d": 972.146402,
          "pnl_all_time": -394.969941,
          "volume_24h": 0.0,
          "volume_7d": 89059.88946,
          "equity": 17688.156402
        },
        {
          "address": "9vA7Wq4hY2eGa3CC1YkRqtMUMotxYfXnxwaJuFt58pm7",
          "pnl_24h": 867.149286,
          "pnl_7d": 1674.076456,
          "pnl_30d": -1150.42512,
          "pnl_all_time": 3922.24938,
          "volume_24h": 0.8715,
          "volume_7d": 5.0958,
          "equity": 40922.74938
        },
        {
          "address": "ATG1QadSgeGGTHvwHqBtcgjtnBYbB1Z3bDfBe5pwNgvy",
          "pnl_24h": 853.294129,
          "pnl_7d": 2897.638763,
          "pnl_30d": 2897.638763,
          "pnl_all_time": 2897.638763,
          "volume_24h": 2000.7762,
          "volume_7d": 181147.84463,
          "equity": 7297.638763
        }
      ],
      "top_losers": [
        {
          "address": "YjCD9Gek6MVY9t3MLEGYYdZLeaF6MZrpgZraayWsv9E",
          "pnl_24h": -25719.028177,
          "pnl_7d": -34491.619151,
          "pnl_30d": 73658.157276,
          "pnl_all_time": 1528387.186086,
          "volume_24h": 343088.11393,
          "volume_7d": 2031826.57203,
          "equity": 893626.788915
        },
        {
          "address": "BEE5U8G8KrYRagtnHcHqtDES9ygpg1k5JFiYLMwzF8MQ",
          "pnl_24h": -15051.2598,
          "pnl_7d": -20634.239933,
          "pnl_30d": -46255.093429,
          "pnl_all_time": -49860.766127,
          "volume_24h": 181418.687393,
          "volume_7d": 917074.836306,
          "equity": 174752.233873
        },
        {
          "address": "AEEqcwDj1fwEUBbCGuePSZMx8agW71zmWRGkfQ4a9uqW",
          "pnl_24h": -13765.634588,
          "pnl_7d": -35319.56983,
          "pnl_30d": 35887.254749,
          "pnl_all_time": -47631.765019,
          "volume_24h": 0.0,
          "volume_7d": 0.0,
          "equity": 285886.974749
        },
        {
          "address": "5RmsTTwkXQgKcTv5BK6CZEjHQMBVLVQVt8po3h5cQabB",
          "pnl_24h": -13711.40369,
          "pnl_7d": -30595.85742,
          "pnl_30d": 25067.779803,
          "pnl_all_time": 12969.878908,
          "volume_24h": 0.0,
          "volume_7d": 0.0,
          "equity": 294066.889803
        },
        {
          "address": "HbBtywk768hrZbUhYu5fEBEhQvMstb3PYTmj14WRfJ3p",
          "pnl_24h": -11940.845852,
          "pnl_7d": -40236.225224,
          "pnl_30d": -39942.513564,
          "pnl_all_time": -8364.863536,
          "volume_24h": 2720958.44381,
          "volume_7d": 7255627.36097,
          "equity": 18901.434558
        },
        {
          "address": "6uC2TdJxxqhWMPSjs7u9YE5rWMQs1yhxkvk8BmBTPrpV",
          "pnl_24h": -6121.606784,
          "pnl_7d": 5219.078925,
          "pnl_30d": 24672.043644,
          "pnl_all_time": 24672.043644,
          "volume_24h": 13.51945,
          "volume_7d": 402530.4079,
          "equity": 57229.187712
        },
        {
          "address": "HtC4WT6JhKz8eojNigfiqSWykG74kfQmyDeM9f753aPQ",
          "pnl_24h": -5471.584274,
          "pnl_7d": 18614.152136,
          "pnl_30d": -1663.018022,
          "pnl_all_time": 474955.675738,
          "volume_24h": 2309909.686025,
          "volume_7d": 20541326.830327,
          "equity": 436959.675738
        },
        {
          "address": "DaUvqv6tHCVtNtv73Fjzbzd3jQAif4bQBZX7yd72eNj",
          "pnl_24h": -4083.513181,
          "pnl_7d": -29188.579726,
          "pnl_30d": -60035.559499,
          "pnl_all_time": -158739.472322,
          "volume_24h": 0.0,
          "volume_7d": 0.0,
          "equity": 189964.150502
        },
        {
          "address": "9sdisaXk3eLnqdu2bu4Y5AQ2g14jPpXF8Jt3vjnUri3o",
          "pnl_24h": -4025.855562,
          "pnl_7d": -4546.463258,
          "pnl_30d": 5186.359665,
          "pnl_all_time": 2595.200103,
          "volume_24h": 21788.649005,
          "volume_7d": 260706.808315,
          "equity": 137753.882267
        },
        {
          "address": "DrNBiFihydX12wJ2mTdQrsiXfPvAnU9WfrYsSH5UDCvL",
          "pnl_24h": -3914.352492,
          "pnl_7d": -6640.270169,
          "pnl_30d": -2015.168724,
          "pnl_all_time": -20973.892187,
          "volume_24h": 182.3165,
          "volume_7d": 714.93393,
          "equity": 75015.450666
        },
        {
          "address": "BEE9evCYoXTQpVHjnLQsXVGi9ewe8dyp1rSejeDvKK8Q",
          "pnl_24h": -3727.670961,
          "pnl_7d": -3807.195933,
          "pnl_30d": -7180.015659,
          "pnl_all_time": -64525.490999,
          "volume_24h": 164134.663449,
          "volume_7d": 851524.312155,
          "equity": 60512.509001
        },
        {
          "address": "AoVHrciuHrqSsSty2wK7ZgVYscmiLNrGm1NXPPgdWaPf",
          "pnl_24h": -3496.530911,
          "pnl_7d": -4016.599704,
          "pnl_30d": 4580.206278,
          "pnl_all_time": -34912.95884,
          "volume_24h": 102.96,
          "volume_7d": 109438.1,
          "equity": 37922.089782
        },
        {
          "address": "9eSnj4TniTi1JkeeASTyzXWSCEzHM8DjNf7XhD1rQ6Qu",
          "pnl_24h": -2793.286998,
          "pnl_7d": -2852.56035,
          "pnl_30d": 3920.812154,
          "pnl_all_time": 54560.490371,
          "volume_24h": 71.92944,
          "volume_7d": 237203.32371,
          "equity": 46818.273317
        },
        {
          "address": "5tVFEuHYfcm9t4cy7jxdcaJvQLKAbvzUhAPcoea6KKxX",
          "pnl_24h": -2093.081001,
          "pnl_7d": -45330.101407,
          "pnl_30d": -77305.660924,
          "pnl_all_time": -98207.588719,
          "volume_24h": 0.0,
          "volume_7d": 0.0,
          "equity": 172694.049076
        },
        {
          "address": "yTTJHkW7t39KBLGquSV4thGscMmgRDAXhnyxGRGubay",
          "pnl_24h": -2080.652909,
          "pnl_7d": -2084.066334,
          "pnl_30d": 3204.984811,
          "pnl_all_time": -3812.753923,
          "volume_24h": -3500.116649,
          "volume_7d": 9020.851611,
          "equity": 25555.686778
        },
        {
          "address": "Ph9yECGodDAjiiSU9bpbJ8dds3ndWP1ngKo8h1K2QYv",
          "pnl_24h": -2059.990422,
          "pnl_7d": 29799.619682,
          "pnl_30d": 69268.76315,
          "pnl_all_time": 78988.967547,
          "volume_24h": 57409.59769,
          "volume_7d": 451371.871914,
          "equity": 162718.641302
        },
        {
          "address": "JBaQj9MPqrwykzCPR5Bnk89CHTGjgYCQdFhs4JPMADsL",
          "pnl_24h": -1990.809512,
          "pnl_7d": -13586.266815,
          "pnl_30d": -21921.665397,
          "pnl_all_time": -11549.848248,
          "volume_24h": 149047.6862,
          "volume_7d": 1999189.90971,
          "equity": 66370.151752
        },
        {
          "address": "J2bdNnwrfDUEm3gjpduWVWJNKvhEnu3EDo9EN2FsDj9d",
          "pnl_24h": -1744.202753,
          "pnl_7d": 989.272607,
          "pnl_30d": 11109.151796,
          "pnl_all_time": 40759.52279,
          "volume_24h": 0.0,
          "volume_7d": 17648.11681,
          "equity": 56808.523451
        },
        {
          "address": "pcdL1vBeCoYECXB86ZxsMfJNKzD3jYhATCbue6dhPdn",
          "pnl_24h": -1704.292159,
          "pnl_7d": -446.509156,
          "pnl_30d": -497.117943,
          "pnl_all_time": -657.705887,
          "volume_24h": 568603.72565,
          "volume_7d": 1151127.48067,
          "equity": 3334.890598
        },
        {
          "address": "DftLLtov8QdYUFFnV7z2nBrjUDUrMyojAD6h83BB545G",
          "pnl_24h": -1702.691442,
          "pnl_7d": 1983.473101,
          "pnl_30d": -2706.37759,
          "pnl_all_time": 26008.877334,
          "volume_24h": 12610.45749,
          "volume_7d": 125738.706812,
          "equity": 216007.088334
        },
        {
          "address": "4u3L6r3nyL9XfZ93gMeXb4eddUGAXAMK8Cqkj1pvCmZB",
          "pnl_24h": -1544.586729,
          "pnl_7d": 189.057284,
          "pnl_30d": 6371.643478,
          "pnl_all_time": -3517.426659,
          "volume_24h": 11728.19754,
          "volume_7d": 152393.85714,
          "equity": 296532.573341
        },
        {
          "address": "AQzj5vqR5LKQYNXTLxL1EKyY6tLaLNhNoDEBytpip9Tr",
          "pnl_24h": -1524.868862,
          "pnl_7d": -8119.306908,
          "pnl_30d": -14843.555726,
          "pnl_all_time": -15242.974597,
          "volume_24h": 0.0,
          "volume_7d": 213284.04333,
          "equity": 10855.016913
        },
        {
          "address": "GTU92nBC8LMyt9W4Qqc319BFR1vpkNNPAbt4QCnX7kZ6",
          "pnl_24h": -1511.442306,
          "pnl_7d": 1156.718587,
          "pnl_30d": 20031.381791,
          "pnl_all_time": 37923.119774,
          "volume_24h": 2131997.720143,
          "volume_7d": 19695359.208692,
          "equity": 487841.505312
        },
        {
          "address": "E8j5xSbGXEWtj7BQobPtiMAfh7CpqR8t1tXX7qtAWCiZ",
          "pnl_24h": -1509.134421,
          "pnl_7d": -403.098507,
          "pnl_30d": 11026.33703,
          "pnl_all_time": 198875.804102,
          "volume_24h": 4233940.773781,
          "volume_7d": 31258922.461603,
          "equity": 124075.304102
        },
        {
          "address": "BMQC6GP4t6Zk3q1FbF8g2cms8CuZuGu4RJeQHg8buXJx",
          "pnl_24h": -1490.564189,
          "pnl_7d": 436.008958,
          "pnl_30d": 1061.095184,
          "pnl_all_time": -77789.573634,
          "volume_24h": 0.0,
          "volume_7d": 74423.0856,
          "equity": 52210.448974
        },
        {
          "address": "12Ex9pzJ1wwKEbg1o9ugnvjuuLTM1w9Y3KX7ALFZt1n5",
          "pnl_24h": -1464.932204,
          "pnl_7d": -3688.384149,
          "pnl_30d": -17967.250541,
          "pnl_all_time": -181649.251551,
          "volume_24h": 0.0,
          "volume_7d": 276568.70325,
          "equity": 7630.364058
        },
        {
          "address": "G5GWsm3f9C2rztJNMAXZtEPqqrGED1dbAu8PS6V25MJB",
          "pnl_24h": -1330.110298,
          "pnl_7d": -7110.310516,
          "pnl_30d": -12915.349865,
          "pnl_all_time": 179970.726061,
          "volume_24h": 693170.730186,
          "volume_7d": 4990047.38016,
          "equity": 245969.896061
        },
        {
          "address": "3tAHUYWA8j143WrnahGTAYiQgnb5BcypfMUMmJYQLwyX",
          "pnl_24h": -1264.226029,
          "pnl_7d": -1966.055462,
          "pnl_30d": 4301.113057,
          "pnl_all_time": 27282.041763,
          "volume_24h": 0.0,
          "volume_7d": 1240.3536,
          "equity": 19770.891754
        },
        {
          "address": "dP8e6fKfx69RCRjTPNkHa5W5RbhTzvSoQkrJmr7MPfh",
          "pnl_24h": -1163.300857,
          "pnl_7d": 3343.656967,
          "pnl_30d": 1012.0271,
          "pnl_all_time": -6178.530657,
          "volume_24h": 0.0,
          "volume_7d": 0.0,
          "equity": 13172.277836
        },
        {
          "address": "Fqrep8G6BT5qRJGSyGtFhjVwPb1eK1kpwLeEdzaiZ1ub",
          "pnl_24h": -1075.466961,
          "pnl_7d": 2242.599924,
          "pnl_30d": -3250.773089,
          "pnl_all_time": -6739.201263,
          "volume_24h": 235015.73063,
          "volume_7d": 989167.73339,
          "equity": 4770.983154
        },
        {
          "address": "WPiaQ7Dnh4hcHJeaBFeYoB7m6QdK3HucgU1FCTSKWkH",
          "pnl_24h": -1072.037387,
          "pnl_7d": -1666.691705,
          "pnl_30d": 1175.086755,
          "pnl_all_time": -44576.646262,
          "volume_24h": 0.0,
          "volume_7d": 0.0,
          "equity": 18126.841642
        },
        {
          "address": "3M97o37xk1sWTvVhhPWLpVoxGktDaV1rBJABixQhXyk8",
          "pnl_24h": -1058.331652,
          "pnl_7d": -360.040017,
          "pnl_30d": -3461.346597,
          "pnl_all_time": -3461.346597,
          "volume_24h": 0.0,
          "volume_7d": 6334.98363,
          "equity": 7785.786605
        },
        {
          "address": "GNzSLjvyysA4AHEbXq1PgKm9oHqmqZmLdup9vH1z3Z3a",
          "pnl_24h": -991.578963,
          "pnl_7d": 2426.289957,
          "pnl_30d": 7217.496403,
          "pnl_all_time": 4154.176148,
          "volume_24h": 117094.90554,
          "volume_7d": 260133.56109,
          "equity": 16708.769362
        },
        {
          "address": "Gskf4VgodkUjKENhbJhfECqg37HYwqKGfDMZHrtWaVxW",
          "pnl_24h": -920.217097,
          "pnl_7d": -1012.966252,
          "pnl_30d": -3719.692065,
          "pnl_all_time": -7201.726566,
          "volume_24h": 166861.572133,
          "volume_7d": 634163.133392,
          "equity": 5624.909118
        },
        {
          "address": "C45As2diKNQHSARr5m16JLhA5iRPEhbGYvmxaF2ZihRM",
          "pnl_24h": -892.969551,
          "pnl_7d": -1966.380813,
          "pnl_30d": 16513.978513,
          "pnl_all_time": 25822.512033,
          "volume_24h": 8101.806,
          "volume_7d": 17957.0943,
          "equity": 75782.708644
        },
        {
          "address": "4q5AywsD1BU7i3nAx3GuTGSgpZkzaf14AiS1k2xx9oLD",
          "pnl_24h": -891.196561,
          "pnl_7d": 1178.528429,
          "pnl_30d": 7397.975831,
          "pnl_all_time": -32181.911539,
          "volume_24h": 0.0,
          "volume_7d": 6864.51467,
          "equity": 28112.088461
        },
        {
          "address": "5zPgTweyqVACTpaYdtdK6mpvduZucQcvgfuVwMUd2WeV",
          "pnl_24h": -867.602322,
          "pnl_7d": -8960.695972,
          "pnl_30d": -14270.605613,
          "pnl_all_time": -20359.444037,
          "volume_24h": 0.0,
          "volume_7d": 0.0,
          "equity": 11717.339724
        },
        {
          "address": "GGSPJKxVkPkurDZFGVW6inynPZ5T6SdsJ316vYKJGGsi",
          "pnl_24h": -784.1492,
          "pnl_7d": -1218.723612,
          "pnl_30d": 851.06407,
          "pnl_all_time": 2968.866665,
          "volume_24h": 200.60224,
          "volume_7d": 1699.24159,
          "equity": 12663.042058
        },
        {
          "address": "8wxZY37A6Qwf3zqWU4gfeoYY9N3Y1UWs7Kmsd8H3h9xm",
          "pnl_24h": -778.000769,
          "pnl_7d": 132.736871,
          "pnl_30d": -532.147165,
          "pnl_all_time": 51052.403647,
          "volume_24h": 456222.269374,
          "volume_7d": 3540633.805284,
          "equity": 55652.403647
        },
        {
          "address": "BBXooWjX71tmNMivEqvsmqDVzKQF7zfJPgEoZUsRXtPE",
          "pnl_24h": -714.984954,
          "pnl_7d": -37.071506,
          "pnl_30d": -4070.726619,
          "pnl_all_time": -10252.740657,
          "volume_24h": 0.0,
          "volume_7d": 0.0,
          "equity": 5434.468819
        },
        {
          "address": "7Z9j8dSyXApd71PEWuGRpV3puqZjQuFkG4jn9R1nakS8",
          "pnl_24h": -650.900883,
          "pnl_7d": -685.575254,
          "pnl_30d": -685.575254,
          "pnl_all_time": -681.079946,
          "volume_24h": 24926.66427,
          "volume_7d": 55101.15218,
          "equity": 2814.434747
        },
        {
          "address": "DryPWniuxDfeRnXKi89rNTCzEbiySWk4shZKi5senBF6",
          "pnl_24h": -632.640722,
          "pnl_7d": -632.640717,
          "pnl_30d": 1997.059699,
          "pnl_all_time": 889.592527,
          "volume_24h": 697340.97058,
          "volume_7d": 697340.97058,
          "equity": 11849.534144
        },
        {
          "address": "4hBqd9xTzQc4ZfcGHJAJUXuGWfgMq2ehhZQuuoakpkwL",
          "pnl_24h": -628.506259,
          "pnl_7d": -5402.445804,
          "pnl_30d": -180.252057,
          "pnl_all_time": -56660.295717,
          "volume_24h": 0.0,
          "volume_7d": 945213.664372,
          "equity": 7970.447116
        },
        {
          "address": "9UdMr8BXBpNLERWiVPq37owCcimyecLeuJXqBRUnaGj7",
          "pnl_24h": -627.828088,
          "pnl_7d": -1797.801823,
          "pnl_30d": 2666.668086,
          "pnl_all_time": -2216.584979,
          "volume_24h": 0.0,
          "volume_7d": 194076.91942,
          "equity": 4662.027129
        },
        {
          "address": "Cuk6tMV2LsSX5QfJC4NoCAzuXDX8T8s9E7dtPQJCH3Sg",
          "pnl_24h": -594.074432,
          "pnl_7d": -1439.507191,
          "pnl_30d": -2407.645536,
          "pnl_all_time": -2407.645536,
          "volume_24h": 18696.34221,
          "volume_7d": 279245.42473,
          "equity": 365.212054
        },
        {
          "address": "D1ARdC6skVJbH5AKnVDu9zLUuZrFn3t8M8KirvzzkUsP",
          "pnl_24h": -575.979951,
          "pnl_7d": -895.47344,
          "pnl_30d": 1511.669094,
          "pnl_all_time": -623.167799,
          "volume_24h": 0.0,
          "volume_7d": 0.0,
          "equity": 8803.206293
        },
        {
          "address": "FMhCxyGkfcFEyr7mRQ9qpGGqzk3BwvgXxQcCXunfwpA",
          "pnl_24h": -558.884107,
          "pnl_7d": 2940.893184,
          "pnl_30d": 4181.684476,
          "pnl_all_time": 55754.550614,
          "volume_24h": 0.0,
          "volume_7d": 62358.42315,
          "equity": 79783.179033
        },
        {
          "address": "DJBoAoMeRVpHxKePd8veuvm5B5arAJKN97PcaNog6skJ",
          "pnl_24h": -538.931234,
          "pnl_7d": -538.931234,
          "pnl_30d": -538.931234,
          "pnl_all_time": -538.931234,
          "volume_24h": 103247.87344,
          "volume_7d": 103247.87344,
          "equity": 1505.61431
        },
        {
          "address": "9j98EViWcsVX8tzf3QQ84ZK2jjsaDjMJmhj1AY8xv6DZ",
          "pnl_24h": -535.36311,
          "pnl_7d": 593.626277,
          "pnl_30d": 346.545711,
          "pnl_all_time": -83870.088046,
          "volume_24h": 0.0,
          "volume_7d": 8021.37685,
          "equity": 4579.286679
        },
        {
          "address": "CAHPdCrmxQyt8aGETr6cYedw3QvyqxWBRortR7ddN6bL",
          "pnl_24h": -523.190073,
          "pnl_7d": 2059.78355,
          "pnl_30d": -339.317126,
          "pnl_all_time": 1191.916266,
          "volume_24h": 0.0,
          "volume_7d": 68462.0,
          "equity": 22929.615651
        }
      ],
      "total_traders": 4475
    }
  }
}