{
  "updated_at": "2026-02-17T10:07:54.392683Z",
  "protocols": [
    {
      "protocol": "Drift Trade",
      "volume_24h": 71699425,
      "volume_7d": 793814970,
      "change_1d": -27.74,
      "change_7d": -29.51,
      "transactions": 0,
      "traders": 2083,
      "fees": 35849.7125
    },
    {
      "protocol": "Jupiter Perpetual Exchange",
      "volume_24h": 165386570,
      "volume_7d": 1584714842,
      "change_1d": -25.81,
      "change_7d": -37.85,
      "transactions": 807,
      "traders": 2788,
      "fees": 99231.942
    },
    {
      "protocol": "FlashTrade",
      "volume_24h": 10031026,
      "volume_7d": 103909496,
      "change_1d": -60.11,
      "change_7d": 8.56,
      "transactions": 0,
      "traders": 307,
      "fees": 5015.513
    },
    {
      "protocol": "Adrena Protocol",
      "volume_24h": 462551,
      "volume_7d": 48408644,
      "change_1d": -95.59,
      "change_7d": -95.74,
      "transactions": 0,
      "traders": 0,
      "fees": 231.2755
    },
    {
      "protocol": "Pacifica",
      "volume_24h": 670265904,
      "volume_7d": 4604000792,
      "change_1d": 73.15,
      "change_7d": -25.8,
      "transactions": 344,
      "traders": 2382,
      "fees": 335132.952
    },
    {
      "protocol": "Tread.fi Perps",
      "volume_24h": 39317781,
      "volume_7d": 512006538,
      "change_1d": 62.5,
      "change_7d": -61.33,
      "transactions": 0,
      "traders": 0,
      "fees": 19658.8905
    },
    {
      "protocol": "GMTrade",
      "volume_24h": 90099662,
      "volume_7d": 618995779,
      "change_1d": 93.53,
      "change_7d": 9.3,
      "transactions": 0,
      "traders": 0,
      "fees": 45049.831
    }
  ],
  "drift_markets": {
    "SOL-PERP": {
      "volume": 34910662.243802,
      "open_interest": 1016288.78,
      "funding_rate": -0.002535569,
      "next_funding_rate": -0.002178,
      "last_price": 85.781613,
      "price_high": 87.5715,
      "price_low": 82.456146,
      "index_price": 85.836125
    },
    "BTC-PERP": {
      "volume": 25138624.222943,
      "open_interest": 541.7337,
      "funding_rate": -1.52e-07,
      "next_funding_rate": -0.000102,
      "last_price": 67991.91001,
      "price_high": 70049.9,
      "price_low": 67284.3,
      "index_price": 68021.430467
    },
    "ETH-PERP": {
      "volume": 8114569.508815,
      "open_interest": 9075.125,
      "funding_rate": 0.00193435,
      "next_funding_rate": 0.003787,
      "last_price": 1974.620583,
      "price_high": 2021.55,
      "price_low": 1934.8,
      "index_price": 1973.583719
    },
    "APT-PERP": {
      "volume": 15314.002367,
      "open_interest": 40320.8,
      "funding_rate": 0.000516936,
      "next_funding_rate": 0.000534,
      "last_price": 0.923874,
      "price_high": 0.941,
      "price_low": 0.901,
      "index_price": 0.923926
    },
    "1MBONK-PERP": {
      "volume": 2293964.270501,
      "open_interest": 23733.4,
      "funding_rate": 0.001369822,
      "next_funding_rate": 0.0013,
      "last_price": 6.497386,
      "price_high": 6.718808,
      "price_low": 6.417468,
      "index_price": 6.495
    },
    "POL-PERP": {
      "volume": 4261.305037,
      "open_interest": 106661.0,
      "funding_rate": -0.003978357,
      "next_funding_rate": -0.003973,
      "last_price": 0.106454,
      "price_high": 0.108074,
      "price_low": 0.104772,
      "index_price": 0.106564
    },
    "ARB-PERP": {
      "volume": 7786.840275,
      "open_interest": 119268.0,
      "funding_rate": -0.003777421,
      "next_funding_rate": -0.003847,
      "last_price": 0.113077,
      "price_high": 0.115968,
      "price_low": 0.1114,
      "index_price": 0.113192
    },
    "DOGE-PERP": {
      "volume": 80106.007943,
      "open_interest": 4007868.0,
      "funding_rate": 0.003730157,
      "next_funding_rate": 0.003901,
      "last_price": 0.099137,
      "price_high": 0.103161,
      "price_low": 0.0986,
      "index_price": 0.099034
    },
    "BNB-PERP": {
      "volume": 41538.487872,
      "open_interest": 369.44,
      "funding_rate": -0.003366348,
      "next_funding_rate": -0.00332,
      "last_price": 618.020407,
      "price_high": 630.3,
      "price_low": 603.193985,
      "index_price": 618.642499
    },
    "SUI-PERP": {
      "volume": 586384.098992,
      "open_interest": 845396.0,
      "funding_rate": 0.000227553,
      "next_funding_rate": 0.000163,
      "last_price": 0.967276,
      "price_high": 1.001444,
      "price_low": 0.9476,
      "index_price": 0.967503
    },
    "1MPEPE-PERP": {
      "volume": 30202.287621,
      "open_interest": 8165.0,
      "funding_rate": -0.000522595,
      "next_funding_rate": -0.002216,
      "last_price": 4.327603,
      "price_high": 4.530072,
      "price_low": 4.349313,
      "index_price": 4.3322
    },
    "OP-PERP": {
      "volume": 5305.005339,
      "open_interest": 52406.0,
      "funding_rate": -0.003154375,
      "next_funding_rate": -0.003284,
      "last_price": 0.186961,
      "price_high": 0.1926,
      "price_low": 0.185714,
      "index_price": 0.18715
    },
    "RENDER-PERP": {
      "volume": 81765.858538,
      "open_interest": 89316.0,
      "funding_rate": -0.001519777,
      "next_funding_rate": -0.0023,
      "last_price": 1.452614,
      "price_high": 1.478077,
      "price_low": 1.429198,
      "index_price": 1.453969
    },
    "XRP-PERP": {
      "volume": 932507.766545,
      "open_interest": 602312.0,
      "funding_rate": -0.003381466,
      "next_funding_rate": -0.003147,
      "last_price": 1.454901,
      "price_high": 1.5128,
      "price_low": 1.455,
      "index_price": 1.456359
    },
    "HNT-PERP": {
      "volume": 25656.78318,
      "open_interest": 31326.0,
      "funding_rate": -0.009380339,
      "next_funding_rate": -0.009382,
      "last_price": 1.346151,
      "price_high": 1.541244,
      "price_low": 1.329775,
      "index_price": 1.349787
    },
    "INJ-PERP": {
      "volume": 55043.31299,
      "open_interest": 22548.0,
      "funding_rate": -0.002457562,
      "next_funding_rate": -0.001757,
      "last_price": 3.098468,
      "price_high": 3.214484,
      "price_low": 3.096,
      "index_price": 3.101574
    },
    "LINK-PERP": {
      "volume": 11524.878643,
      "open_interest": 22728.0,
      "funding_rate": 1.0855e-05,
      "next_funding_rate": 6.7e-05,
      "last_price": 8.791663,
      "price_high": 8.938,
      "price_low": 8.613,
      "index_price": 8.799454
    },
    "RLB-PERP": {
      "volume": 64.817978,
      "open_interest": 500.0,
      "funding_rate": -0.000247909,
      "next_funding_rate": 0.000887,
      "last_price": 0.061019,
      "price_high": 0.0,
      "price_low": 0.0,
      "index_price": 0.06102
    },
    "PYTH-PERP": {
      "volume": 11189.659371,
      "open_interest": 3277456.0,
      "funding_rate": -0.003694048,
      "next_funding_rate": -0.004575,
      "last_price": 0.05616,
      "price_high": 0.0568,
      "price_low": 0.0556,
      "index_price": 0.056218
    },
    "TIA-PERP": {
      "volume": 2109.351533,
      "open_interest": 11328.5,
      "funding_rate": -0.00351466,
      "next_funding_rate": -0.003621,
      "last_price": 0.338258,
      "price_high": 0.346,
      "price_low": 0.333633,
      "index_price": 0.338613
    },
    "JTO-PERP": {
      "volume": 87710.12127,
      "open_interest": 291614.0,
      "funding_rate": -0.00376764,
      "next_funding_rate": -0.003673,
      "last_price": 0.279453,
      "price_high": 0.281576,
      "price_low": 0.2606,
      "index_price": 0.27974
    },
    "SEI-PERP": {
      "volume": 1956.116985,
      "open_interest": 283136.0,
      "funding_rate": -0.003509827,
      "next_funding_rate": -0.003728,
      "last_price": 0.07444,
      "price_high": 0.0764,
      "price_low": 0.0746,
      "index_price": 0.074516
    },
    "AVAX-PERP": {
      "volume": 15338.538573,
      "open_interest": 6101.1,
      "funding_rate": 0.000279139,
      "next_funding_rate": 0.00011,
      "last_price": 9.11711,
      "price_high": 9.417,
      "price_low": 9.045359,
      "index_price": 9.119288
    },
    "WIF-PERP": {
      "volume": 684504.931775,
      "open_interest": 629647.0,
      "funding_rate": -0.000590993,
      "next_funding_rate": -8.9e-05,
      "last_price": 0.23237,
      "price_high": 0.237823,
      "price_low": 0.2275,
      "index_price": 0.232386
    },
    "JUP-PERP": {
      "volume": 438814.665261,
      "open_interest": 2841437.0,
      "funding_rate": -0.00115357,
      "next_funding_rate": -0.001454,
      "last_price": 0.1651,
      "price_high": 0.1692,
      "price_low": 0.1556,
      "index_price": 0.165356
    },
    "DYM-PERP": {
      "volume": 97.934407,
      "open_interest": 547.0,
      "funding_rate": -0.001130882,
      "next_funding_rate": -0.085317,
      "last_price": 0.053616,
      "price_high": 0.0,
      "price_low": 0.0,
      "index_price": 0.059791
    },
    "TAO-PERP": {
      "volume": 59576.389307,
      "open_interest": 1872.87,
      "funding_rate": -0.013621698,
      "next_funding_rate": -0.013645,
      "last_price": 188.599243,
      "price_high": 199.66,
      "price_low": 183.99,
      "index_price": 189.271268
    },
    "W-PERP": {
      "volume": 1683.626934,
      "open_interest": 739501.0,
      "funding_rate": -0.003227838,
      "next_funding_rate": -0.00484,
      "last_price": 0.020432,
      "price_high": 0.021,
      "price_low": 0.0206,
      "index_price": 0.020446
    },
    "KMNO-PERP": {
      "volume": 5234.721097,
      "open_interest": 2616074.0,
      "funding_rate": -0.005170701,
      "next_funding_rate": -0.005036,
      "last_price": 0.03196,
      "price_high": 0.034,
      "price_low": 0.0296,
      "index_price": 0.031998
    },
    "TNSR-PERP": {
      "volume": 8080.431702,
      "open_interest": 1453788.0,
      "funding_rate": 0.00750817,
      "next_funding_rate": 0.00752,
      "last_price": 0.055847,
      "price_high": 0.0576,
      "price_low": 0.055484,
      "index_price": 0.055747
    },
    "DRIFT-PERP": {
      "volume": 21702.937614,
      "open_interest": 4822472.0,
      "funding_rate": 0.000228255,
      "next_funding_rate": 0.000137,
      "last_price": 0.092523,
      "price_high": 0.0933,
      "price_low": 0.0849,
      "index_price": 0.09251
    },
    "CLOUD-PERP": {
      "volume": 18.823812,
      "open_interest": 76072.0,
      "funding_rate": -0.020806685,
      "next_funding_rate": -0.01986,
      "last_price": 0.039095,
      "price_high": 0.0,
      "price_low": 0.0,
      "index_price": 0.039363
    },
    "IO-PERP": {
      "volume": 1639.828223,
      "open_interest": 20.0,
      "funding_rate": 0.033784348,
      "next_funding_rate": -0.049476,
      "last_price": 0.142941,
      "price_high": 0.0,
      "price_low": 0.0,
      "index_price": 0.144478
    },
    "ZEX-PERP": {
      "volume": 7.84,
      "open_interest": 14.0,
      "funding_rate": -0.008775444,
      "next_funding_rate": 0.000789,
      "last_price": 0.073829,
      "price_high": 0.0,
      "price_low": 0.0,
      "index_price": 0.073914
    },
    "POPCAT-PERP": {
      "volume": 9730.252292,
      "open_interest": 951950.0,
      "funding_rate": -0.00488289,
      "next_funding_rate": -0.004798,
      "last_price": 0.052577,
      "price_high": 0.055504,
      "price_low": 0.053074,
      "index_price": 0.052632
    },
    "1KWEN-PERP": {
      "volume": 1159.733264,
      "open_interest": 460.0,
      "funding_rate": -0.001614511,
      "next_funding_rate": 0.000953,
      "last_price": 0.026203,
      "price_high": 0.0,
      "price_low": 0.0,
      "index_price": 0.026228
    },
    "TRUMP-WIN-2024-BET": {
      "volume": 1381506.479951,
      "open_interest": 0.0,
      "funding_rate": 0.0,
      "next_funding_rate": 0.000829,
      "last_price": 0.980427,
      "price_high": 0.0,
      "price_low": 0.0,
      "index_price": 0.979815
    },
    "KAMALA-POPULAR-VOTE-2024-BET": {
      "volume": 202.763016,
      "open_interest": 0.0,
      "funding_rate": 0.0,
      "next_funding_rate": 0.0,
      "last_price": 2e-06,
      "price_high": 0.0,
      "price_low": 0.0,
      "index_price": 2e-06
    },
    "FED-CUT-50-SEPT-2024-BET": {
      "volume": 61921.214356,
      "open_interest": 0.0,
      "funding_rate": 0.0,
      "next_funding_rate": 0.000833,
      "last_price": 0.990633,
      "price_high": 0.0,
      "price_low": 0.0,
      "index_price": 0.990015
    },
    "REPUBLICAN-POPULAR-AND-WIN-BET": {
      "volume": 793.263281,
      "open_interest": 0.0,
      "funding_rate": 0.0,
      "next_funding_rate": 0.000831,
      "last_price": 0.998245,
      "price_high": 0.0,
      "price_low": 0.0,
      "index_price": 0.997622
    },
    "BREAKPOINT-IGGYERIC-BET": {
      "volume": 3.894168,
      "open_interest": 0.0,
      "funding_rate": 0.0,
      "next_funding_rate": -0.320512,
      "last_price": 0.0,
      "price_high": 0.0,
      "price_low": 0.0,
      "index_price": 1e-06
    },
    "DEMOCRATS-WIN-MICHIGAN-BET": {
      "volume": 2234.536867,
      "open_interest": 0.0,
      "funding_rate": 0.0,
      "next_funding_rate": 0.0,
      "last_price": 0.0,
      "price_high": 0.0,
      "price_low": 0.0,
      "index_price": 1e-06
    },
    "TON-PERP": {
      "volume": 7012.720074,
      "open_interest": 9977.0,
      "funding_rate": -0.003408832,
      "next_funding_rate": -0.003353,
      "last_price": 1.428172,
      "price_high": 1.4564,
      "price_low": 1.4366,
      "index_price": 1.429602
    },
    "LANDO-F1-SGP-WIN-BET": {
      "volume": 99853.432168,
      "open_interest": 0.0,
      "funding_rate": 0.0,
      "next_funding_rate": 0.000829,
      "last_price": 0.974759,
      "price_high": 0.0,
      "price_low": 0.0,
      "index_price": 0.974151
    },
    "MOTHER-PERP": {
      "volume": 11723.884157,
      "open_interest": 3646.0,
      "funding_rate": 0.116474809,
      "next_funding_rate": -0.148657,
      "last_price": 0.001207,
      "price_high": 0.0,
      "price_low": 0.0,
      "index_price": 0.000945
    },
    "MOODENG-PERP": {
      "volume": 2497.306321,
      "open_interest": 3148.0,
      "funding_rate": 0.017000782,
      "next_funding_rate": -0.005796,
      "last_price": 0.0877,
      "price_high": 0.0,
      "price_low": 0.0,
      "index_price": 0.086109
    },
    "WARWICK-FIGHT-WIN-BET": {
      "volume": 2971.94903,
      "open_interest": 0.0,
      "funding_rate": 0.0,
      "next_funding_rate": 0.0,
      "last_price": 0.0,
      "price_high": 0.0,
      "price_low": 0.0,
      "index_price": 1e-06
    },
    "DBR-PERP": {
      "volume": 32.253978,
      "open_interest": 0.0,
      "funding_rate": -0.001345943,
      "next_funding_rate": 0.000702,
      "last_price": 0.023722,
      "price_high": 0.0,
      "price_low": 0.0,
      "index_price": 0.023723
    },
    "WLF-5B-1W-BET": {
      "volume": 2.45,
      "open_interest": 790.0,
      "funding_rate": 0.0,
      "next_funding_rate": 0.000829,
      "last_price": 1.102495,
      "price_high": 0.0,
      "price_low": 0.0,
      "index_price": 0.713525
    },
    "VRSTPN-WIN-F1-24-DRVRS-CHMP-BET": {
      "volume": 8068.712266,
      "open_interest": 0.0,
      "funding_rate": 0.0,
      "next_funding_rate": 0.000829,
      "last_price": 1.000623,
      "price_high": 0.0,
      "price_low": 0.0,
      "index_price": 0.999999
    },
    "LNDO-WIN-F1-24-US-GP-BET": {
      "volume": 16.516678,
      "open_interest": 0.0,
      "funding_rate": 0.0,
      "next_funding_rate": 0.0,
      "last_price": 0.0,
      "price_high": 0.0,
      "price_low": 0.0,
      "index_price": 1e-06
    },
    "1KMEW-PERP": {
      "volume": 245409.217363,
      "open_interest": 0.0,
      "funding_rate": 0.003754899,
      "next_funding_rate": -0.040113,
      "last_price": 0.936556,
      "price_high": 0.0,
      "price_low": 0.0,
      "index_price": 0.93655
    },
    "MICHI-PERP": {
      "volume": 0.0,
      "open_interest": 272.0,
      "funding_rate": 0.002807306,
      "next_funding_rate": 0.000826,
      "last_price": 0.025216,
      "price_high": 0.0,
      "price_low": 0.0,
      "index_price": 0.025217
    },
    "GOAT-PERP": {
      "volume": 8149.772287,
      "open_interest": 60.0,
      "funding_rate": 0.009174447,
      "next_funding_rate": -0.011507,
      "last_price": 0.039858,
      "price_high": 0.0,
      "price_low": 0.0,
      "index_price": 0.04042
    },
    "FWOG-PERP": {
      "volume": 7816.61287,
      "open_interest": 13687.0,
      "funding_rate": -0.006039425,
      "next_funding_rate": -0.012609,
      "last_price": 0.016252,
      "price_high": 0.0,
      "price_low": 0.0,
      "index_price": 0.015806
    },
    "PNUT-PERP": {
      "volume": 319.544061,
      "open_interest": 226.0,
      "funding_rate": 0.012804868,
      "next_funding_rate": -0.03081,
      "last_price": 0.065715,
      "price_high": 0.0,
      "price_low": 0.0,
      "index_price": 0.070149
    },
    "RAY-PERP": {
      "volume": 45661.111986,
      "open_interest": 304239.0,
      "funding_rate": 0.002468157,
      "next_funding_rate": 0.000973,
      "last_price": 0.70706,
      "price_high": 0.75,
      "price_low": 0.6085,
      "index_price": 0.707263
    },
    "SUPERBOWL-LIX-LIONS-BET": {
      "volume": 418.575512,
      "open_interest": 0.0,
      "funding_rate": 0.0,
      "next_funding_rate": 0.0,
      "last_price": 0.0,
      "price_high": 0.0,
      "price_low": 0.0,
      "index_price": 1e-06
    },
    "SUPERBOWL-LIX-CHIEFS-BET": {
      "volume": 1637.317715,
      "open_interest": 0.0,
      "funding_rate": 0.0,
      "next_funding_rate": 0.0,
      "last_price": 0.0,
      "price_high": 0.0,
      "price_low": 0.0,
      "index_price": 1e-06
    },
    "HYPE-PERP": {
      "volume": 3045432.075525,
      "open_interest": 44241.0,
      "funding_rate": 0.000886528,
      "next_funding_rate": 0.000953,
      "last_price": 29.787971,
      "price_high": 31.3323,
      "price_low": 29.6033,
      "index_price": 29.74084
    },
    "LTC-PERP": {
      "volume": 80913.931256,
      "open_interest": 1364.53,
      "funding_rate": 0.001669477,
      "next_funding_rate": 0.001487,
      "last_price": 54.880407,
      "price_high": 55.873,
      "price_low": 53.477,
      "index_price": 54.879757
    },
    "ME-PERP": {
      "volume": 228.297647,
      "open_interest": 114152.0,
      "funding_rate": 0.000644885,
      "next_funding_rate": 0.000675,
      "last_price": 0.135507,
      "price_high": 0.135,
      "price_low": 0.134,
      "index_price": 0.135505
    },
    "PENGU-PERP": {
      "volume": 4700.995408,
      "open_interest": 3301744.0,
      "funding_rate": -0.000573105,
      "next_funding_rate": -0.000582,
      "last_price": 0.007096,
      "price_high": 0.007333,
      "price_low": 0.00714,
      "index_price": 0.007098
    },
    "AI16Z-PERP": {
      "volume": 6793.415642,
      "open_interest": 1091.0,
      "funding_rate": 0.017565257,
      "next_funding_rate": -0.100437,
      "last_price": 0.015749,
      "price_high": 0.0,
      "price_low": 0.0,
      "index_price": 0.01625
    },
    "TRUMP-PERP": {
      "volume": 19851.359843,
      "open_interest": 9878.3,
      "funding_rate": 0.005406783,
      "next_funding_rate": 0.004654,
      "last_price": 3.357533,
      "price_high": 3.5116,
      "price_low": 3.3815,
      "index_price": 3.360958
    },
    "MELANIA-PERP": {
      "volume": 2811.061656,
      "open_interest": 0.0,
      "funding_rate": 0.002109164,
      "next_funding_rate": -0.001513,
      "last_price": 0.107262,
      "price_high": 0.0,
      "price_low": 0.0,
      "index_price": 0.107263
    },
    "BERA-PERP": {
      "volume": 125238.187806,
      "open_interest": 134182.1,
      "funding_rate": -0.025801191,
      "next_funding_rate": -0.02348,
      "last_price": 0.709895,
      "price_high": 0.705,
      "price_low": 0.634403,
      "index_price": 0.71925
    },
    "NBAFINALS25-OKC-BET": {
      "volume": 1439.398655,
      "open_interest": 20.0,
      "funding_rate": 0.0,
      "next_funding_rate": 0.00083,
      "last_price": 0.968746,
      "price_high": 0.0,
      "price_low": 0.0,
      "index_price": 0.968495
    },
    "NBAFINALS25-BOS-BET": {
      "volume": 1.971608,
      "open_interest": 97.0,
      "funding_rate": 0.0,
      "next_funding_rate": 0.0,
      "last_price": 0.0,
      "price_high": 0.0,
      "price_low": 0.0,
      "index_price": 1e-06
    },
    "KAITO-PERP": {
      "volume": 187.341391,
      "open_interest": 11710.0,
      "funding_rate": -0.001896221,
      "next_funding_rate": -0.001529,
      "last_price": 0.317349,
      "price_high": 0.323188,
      "price_low": 0.30962,
      "index_price": 0.317495
    },
    "IP-PERP": {
      "volume": 165537.929646,
      "open_interest": 20708.2,
      "funding_rate": -0.004061835,
      "next_funding_rate": -0.00423,
      "last_price": 1.152247,
      "price_high": 1.2576,
      "price_low": 1.121,
      "index_price": 1.153574
    },
    "FARTCOIN-PERP": {
      "volume": 112776.149156,
      "open_interest": 1240498.0,
      "funding_rate": 0.001446212,
      "next_funding_rate": 0.001744,
      "last_price": 0.194492,
      "price_high": 0.205403,
      "price_low": 0.1923,
      "index_price": 0.194432
    },
    "ADA-PERP": {
      "volume": 5227.803262,
      "open_interest": 126407.0,
      "funding_rate": -0.000102646,
      "next_funding_rate": 2.9e-05,
      "last_price": 0.28137,
      "price_high": 0.289441,
      "price_low": 0.277702,
      "index_price": 0.281411
    },
    "PAXG-PERP": {
      "volume": 697713.735971,
      "open_interest": 192.822,
      "funding_rate": 0.001823851,
      "next_funding_rate": 0.001604,
      "last_price": 4922.006743,
      "price_high": 5013.121352,
      "price_low": 4871.544,
      "index_price": 4921.37671
    },
    "LAUNCHCOIN-PERP": {
      "volume": 25287.201769,
      "open_interest": 0.0,
      "funding_rate": 0.33118948,
      "next_funding_rate": -0.415979,
      "last_price": 0.000588,
      "price_high": 0.0,
      "price_low": 0.0,
      "index_price": 0.000588
    },
    "PUMP-PERP": {
      "volume": 522367.104292,
      "open_interest": 0.0,
      "funding_rate": -0.275531724,
      "next_funding_rate": -0.015445,
      "last_price": 0.002133,
      "price_high": 0.0,
      "price_low": 0.0,
      "index_price": 0.002147
    },
    "ASTER-PERP": {
      "volume": 204124.045338,
      "open_interest": 164073.0,
      "funding_rate": 5.2643e-05,
      "next_funding_rate": 0.000362,
      "last_price": 0.709385,
      "price_high": 0.766,
      "price_low": 0.6994,
      "index_price": 0.70991
    },
    "XPL-PERP": {
      "volume": 12578.51247,
      "open_interest": 107934.0,
      "funding_rate": -0.012497366,
      "next_funding_rate": -0.014036,
      "last_price": 0.098856,
      "price_high": 0.1031,
      "price_low": 0.099132,
      "index_price": 0.099227
    },
    "2Z-PERP": {
      "volume": 207.722928,
      "open_interest": 95390.0,
      "funding_rate": -0.009442932,
      "next_funding_rate": -0.006717,
      "last_price": 0.076894,
      "price_high": 0.0768,
      "price_low": 0.076069,
      "index_price": 0.077099
    },
    "ZEC-PERP": {
      "volume": 142737.877155,
      "open_interest": 3514.44,
      "funding_rate": 0.000941477,
      "next_funding_rate": 0.000943,
      "last_price": 285.077187,
      "price_high": 330.0,
      "price_low": 286.0,
      "index_price": 285.111743
    },
    "MNT-PERP": {
      "volume": 255482.253331,
      "open_interest": 11544.0,
      "funding_rate": 0.001126785,
      "next_funding_rate": 0.001341,
      "last_price": 0.639468,
      "price_high": 0.647581,
      "price_low": 0.626355,
      "index_price": 0.638934
    },
    "1KPUMP-PERP": {
      "volume": 8163.628991,
      "open_interest": 24352.0,
      "funding_rate": 0.004530074,
      "next_funding_rate": 0.005323,
      "last_price": 2.146694,
      "price_high": 2.263544,
      "price_low": 2.1692,
      "index_price": 2.14691
    },
    "MET-PERP": {
      "volume": 475.629289,
      "open_interest": 126644.0,
      "funding_rate": 0.000243695,
      "next_funding_rate": 0.000281,
      "last_price": 0.221066,
      "price_high": 0.2244,
      "price_low": 0.2108,
      "index_price": 0.221065
    },
    "1KMON-PERP": {
      "volume": 1377653.264669,
      "open_interest": 3016.6,
      "funding_rate": -0.002464908,
      "next_funding_rate": -0.003236,
      "last_price": 22.303399,
      "price_high": 24.658716,
      "price_low": 22.443018,
      "index_price": 22.36356
    },
    "LIT-PERP": {
      "volume": 551689.096637,
      "open_interest": 44376.0,
      "funding_rate": -0.007960712,
      "next_funding_rate": -0.007931,
      "last_price": 1.575652,
      "price_high": 1.698774,
      "price_low": 1.573,
      "index_price": 1.580302
    }
  },
  "jupiter_markets": {
    "trades": {
      "SOL": 423,
      "BTC": 109,
      "OTHER": 67,
      "ETH": 44,
      "USDC": 3
    },
    "volumes": {
      "SOL": 108294921.22291023,
      "BTC": 27905783.482972138,
      "OTHER": 17153096.269349847,
      "ETH": 11264719.938080495,
      "USDC": 768049.0866873065
    }
  },
  "pacifica_markets": {
    "SOL": {
      "volume": 644065.3861106962,
      "trades": 0,
      "funding_rate": -2.981e-05,
      "max_leverage": 20
    },
    "ETH": {
      "volume": 644065.3861106962,
      "trades": 0,
      "funding_rate": -4.38e-06,
      "max_leverage": 50
    },
    "BTC": {
      "volume": 644065.3861106962,
      "trades": 0,
      "funding_rate": 2.05e-06,
      "max_leverage": 50
    },
    "PUMP": {
      "volume": 644065.3861106962,
      "trades": 0,
      "funding_rate": -3.109e-05,
      "max_leverage": 5
    },
    "XRP": {
      "volume": 644065.3861106962,
      "trades": 0,
      "funding_rate": -3.19e-06,
      "max_leverage": 20
    },
    "HYPE": {
      "volume": 644065.3861106962,
      "trades": 0,
      "funding_rate": 1.5e-05,
      "max_leverage": 20
    },
    "DOGE": {
      "volume": 644065.3861106962,
      "trades": 0,
      "funding_rate": 1.337e-05,
      "max_leverage": 15
    },
    "FARTCOIN": {
      "volume": 644065.3861106962,
      "trades": 0,
      "funding_rate": 1.5e-05,
      "max_leverage": 10
    },
    "ENA": {
      "volume": 644065.3861106962,
      "trades": 0,
      "funding_rate": 1.154e-05,
      "max_leverage": 10
    },
    "BNB": {
      "volume": 644065.3861106962,
      "trades": 0,
      "funding_rate": 1.5e-05,
      "max_leverage": 10
    },
    "SUI": {
      "volume": 644065.3861106962,
      "trades": 0,
      "funding_rate": 9.92e-06,
      "max_leverage": 10
    },
    "kBONK": {
      "volume": 644065.3861106962,
      "trades": 0,
      "funding_rate": -4.63e-06,
      "max_leverage": 10
    },
    "PENGU": {
      "volume": 644065.3861106962,
      "trades": 0,
      "funding_rate": 8.32e-06,
      "max_leverage": 5
    },
    "AAVE": {
      "volume": 644065.3861106962,
      "trades": 0,
      "funding_rate": 1.5e-05,
      "max_leverage": 10
    },
    "LINK": {
      "volume": 644065.3861106962,
      "trades": 0,
      "funding_rate": 2.86e-06,
      "max_leverage": 10
    },
    "kPEPE": {
      "volume": 644065.3861106962,
      "trades": 0,
      "funding_rate": 7.08e-06,
      "max_leverage": 10
    },
    "LTC": {
      "volume": 644065.3861106962,
      "trades": 0,
      "funding_rate": 1.051e-05,
      "max_leverage": 10
    },
    "LDO": {
      "volume": 644065.3861106962,
      "trades": 0,
      "funding_rate": 1.5e-05,
      "max_leverage": 10
    },
    "UNI": {
      "volume": 644065.3861106962,
      "trades": 0,
      "funding_rate": 1.5e-05,
      "max_leverage": 10
    },
    "CRV": {
      "volume": 644065.3861106962,
      "trades": 0,
      "funding_rate": -5.5e-06,
      "max_leverage": 10
    },
    "WLFI": {
      "volume": 644065.3861106962,
      "trades": 0,
      "funding_rate": -3.205e-05,
      "max_leverage": 5
    },
    "AVAX": {
      "volume": 644065.3861106962,
      "trades": 0,
      "funding_rate": 1.5e-05,
      "max_leverage": 10
    },
    "ASTER": {
      "volume": 644065.3861106962,
      "trades": 0,
      "funding_rate": -1.702e-05,
      "max_leverage": 5
    },
    "XPL": {
      "volume": 644065.3861106962,
      "trades": 0,
      "funding_rate": 1.5e-05,
      "max_leverage": 10
    },
    "2Z": {
      "volume": 644065.3861106962,
      "trades": 0,
      "funding_rate": -1.409e-05,
      "max_leverage": 3
    },
    "PAXG": {
      "volume": 644065.3861106962,
      "trades": 0,
      "funding_rate": 1.373e-05,
      "max_leverage": 10
    },
    "ZEC": {
      "volume": 644065.3861106962,
      "trades": 0,
      "funding_rate": 1.091e-05,
      "max_leverage": 10
    },
    "MON": {
      "volume": 644065.3861106962,
      "trades": 0,
      "funding_rate": 1.25e-06,
      "max_leverage": 3
    },
    "VIRTUAL": {
      "volume": 644065.3861106962,
      "trades": 0,
      "funding_rate": -1.921e-05,
      "max_leverage": 5
    },
    "TAO": {
      "volume": 644065.3861106962,
      "trades": 0,
      "funding_rate": 1.137e-05,
      "max_leverage": 10
    },
    "ZK": {
      "volume": 644065.3861106962,
      "trades": 0,
      "funding_rate": 1.5e-05,
      "max_leverage": 5
    },
    "STRK": {
      "volume": 644065.3861106962,
      "trades": 0,
      "funding_rate": 1.5e-05,
      "max_leverage": 5
    },
    "NEAR": {
      "volume": 644065.3861106962,
      "trades": 0,
      "funding_rate": 1.5e-05,
      "max_leverage": 10
    },
    "TRUMP": {
      "volume": 644065.3861106962,
      "trades": 0,
      "funding_rate": -1.788e-05,
      "max_leverage": 10
    },
    "ICP": {
      "volume": 644065.3861106962,
      "trades": 0,
      "funding_rate": 1.5e-05,
      "max_leverage": 5
    },
    "BCH": {
      "volume": 644065.3861106962,
      "trades": 0,
      "funding_rate": 1.5e-05,
      "max_leverage": 10
    },
    "XMR": {
      "volume": 644065.3861106962,
      "trades": 0,
      "funding_rate": 1.5e-05,
      "max_leverage": 10
    },
    "ADA": {
      "volume": 644065.3861106962,
      "trades": 0,
      "funding_rate": -9.57e-06,
      "max_leverage": 10
    },
    "ARB": {
      "volume": 644065.3861106962,
      "trades": 0,
      "funding_rate": 2.88e-06,
      "max_leverage": 10
    },
    "LIT": {
      "volume": 644065.3861106962,
      "trades": 0,
      "funding_rate": 1.5e-05,
      "max_leverage": 5
    },
    "NVDA": {
      "volume": 644065.3861106962,
      "trades": 0,
      "funding_rate": 1.5e-05,
      "max_leverage": 10
    },
    "XAG": {
      "volume": 644065.3861106962,
      "trades": 0,
      "funding_rate": 1.5e-05,
      "max_leverage": 10
    },
    "WLD": {
      "volume": 644065.3861106962,
      "trades": 0,
      "funding_rate": 6.2e-06,
      "max_leverage": 5
    },
    "JUP": {
      "volume": 644065.3861106962,
      "trades": 0,
      "funding_rate": 9.6e-07,
      "max_leverage": 10
    },
    "WIF": {
      "volume": 644065.3861106962,
      "trades": 0,
      "funding_rate": -2.7e-06,
      "max_leverage": 5
    },
    "PIPPIN": {
      "volume": 644065.3861106962,
      "trades": 0,
      "funding_rate": -0.0001759,
      "max_leverage": 3
    },
    "CL": {
      "volume": 644065.3861106962,
      "trades": 0,
      "funding_rate": 1.5e-05,
      "max_leverage": 10
    },
    "USDJPY": {
      "volume": 644065.3861106962,
      "trades": 0,
      "funding_rate": 1.5e-05,
      "max_leverage": 50
    },
    "TSLA": {
      "volume": 644065.3861106962,
      "trades": 0,
      "funding_rate": 1.5e-05,
      "max_leverage": 10
    },
    "MEGA": {
      "volume": 644065.3861106962,
      "trades": 0,
      "funding_rate": 1.5e-05,
      "max_leverage": 3
    },
    "BP": {
      "volume": 644065.3861106962,
      "trades": 0,
      "funding_rate": 1.5e-05,
      "max_leverage": 3
    },
    "ZRO": {
      "volume": 644065.3861106962,
      "trades": 0,
      "funding_rate": 1.5e-05,
      "max_leverage": 5
    },
    "GOOGL": {
      "volume": 644065.3861106962,
      "trades": 0,
      "funding_rate": 1.5e-05,
      "max_leverage": 10
    },
    "COPPER": {
      "volume": 644065.3861106962,
      "trades": 0,
      "funding_rate": 1.5e-05,
      "max_leverage": 10
    },
    "XAU": {
      "volume": 644065.3861106962,
      "trades": 0,
      "funding_rate": 1.5e-05,
      "max_leverage": 10
    },
    "EURUSD": {
      "volume": 644065.3861106962,
      "trades": 0,
      "funding_rate": 1.5e-05,
      "max_leverage": 50
    }
  },
  "total_open_interest": 151354451.56845245,
  "global_derivatives": [
    {
      "name": "Hyperliquid Perps",
      "chains": [
        "Hyperliquid L1"
      ],
      "volume_24h": 3519041177,
      "volume_7d": 35484361374,
      "change_1d": -1.51,
      "change_7d": -47.01
    },
    {
      "name": "Aster Perps",
      "chains": [
        "Off Chain"
      ],
      "volume_24h": 2377650364,
      "volume_7d": 19098035772,
      "change_1d": -9.95,
      "change_7d": -36.14
    },
    {
      "name": "Lighter Perps",
      "chains": [
        "zkLighter"
      ],
      "volume_24h": 2285553635,
      "volume_7d": 13879275500,
      "change_1d": 8.79,
      "change_7d": 2.23
    },
    {
      "name": "edgeX Perps",
      "chains": [
        "edgeX"
      ],
      "volume_24h": 2026903244,
      "volume_7d": 19197793541,
      "change_1d": -26.03,
      "change_7d": -38.5
    },
    {
      "name": "Apex Omni",
      "chains": [
        "Ethereum"
      ],
      "volume_24h": 1271375022,
      "volume_7d": 8996344599,
      "change_1d": -1.29,
      "change_7d": -0.65
    },
    {
      "name": "Grvt Perps",
      "chains": [
        "GRVT"
      ],
      "volume_24h": 1052760650,
      "volume_7d": 7767019876,
      "change_1d": 59.65,
      "change_7d": -40.1
    },
    {
      "name": "Variational",
      "chains": [
        "Arbitrum"
      ],
      "volume_24h": 971067153,
      "volume_7d": 5594660914,
      "change_1d": 6.87,
      "change_7d": 26.69
    },
    {
      "name": "Pacifica",
      "chains": [
        "Solana"
      ],
      "volume_24h": 670265904,
      "volume_7d": 4604000792,
      "change_1d": 73.15,
      "change_7d": -25.8
    },
    {
      "name": "Extended",
      "chains": [
        "Ethereum",
        "Starknet"
      ],
      "volume_24h": 650200536,
      "volume_7d": 4920943401,
      "change_1d": -11.21,
      "change_7d": -17.6
    },
    {
      "name": "StandX Perps",
      "chains": [
        "StandX"
      ],
      "volume_24h": 646558530,
      "volume_7d": 4041416134,
      "change_1d": 5.56,
      "change_7d": -0.15
    },
    {
      "name": "Paradex Perps",
      "chains": [
        "Paradex"
      ],
      "volume_24h": 407853310,
      "volume_7d": 3311325770,
      "change_1d": -22.41,
      "change_7d": -5.66
    },
    {
      "name": "Nado Perps",
      "chains": [
        "Ink"
      ],
      "volume_24h": 381791045,
      "volume_7d": 2574927787,
      "change_1d": 1.91,
      "change_7d": -6
    },
    {
      "name": "tradeXYZ",
      "chains": [
        "Hyperliquid L1"
      ],
      "volume_24h": 326008529,
      "volume_7d": 5167555635,
      "change_1d": 93.64,
      "change_7d": -70.57
    },
    {
      "name": "MYX Finance",
      "chains": [
        "Arbitrum",
        "Linea",
        "BSC"
      ],
      "volume_24h": 278230728,
      "volume_7d": 1979225257,
      "change_1d": 0.65,
      "change_7d": -4.77
    },
    {
      "name": "SYMMIO",
      "chains": [
        "Arbitrum",
        "Base",
        "BSC",
        "Mantle",
        "Berachain",
        "Mode",
        "Sonic",
        "Coti"
      ],
      "volume_24h": 277017102,
      "volume_7d": 1696961585,
      "change_1d": 0,
      "change_7d": -5.27
    }
  ],
  "time_windows": {
    "24h": {
      "pacifica_traders": 2382,
      "flashtrade_traders": 307,
      "wallet_overlap": {
        "drift_only": 3817,
        "jupiter_only": 2536,
        "pacifica_only": 7662,
        "drift_jupiter": 20,
        "drift_pacifica": 6,
        "jupiter_pacifica": 7,
        "all_three": 1,
        "multi_platform": 34
      },
      "jupiter_traders": 2788,
      "adrena_traders": 0,
      "drift_traders": 2083,
      "liquidations": {
        "count": 0,
        "txns": 0,
        "error": "No historical data"
      }
    },
    "1h": {
      "pacifica_traders": 238,
      "flashtrade_traders": 27,
      "jupiter_traders": 177,
      "adrena_traders": 3,
      "drift_traders": 332,
      "wallet_overlap": {
        "drift_only": 3817,
        "jupiter_only": 2536,
        "pacifica_only": 7662,
        "drift_jupiter": 20,
        "drift_pacifica": 6,
        "jupiter_pacifica": 7,
        "all_three": 1,
        "multi_platform": 34
      },
      "liquidations": {
        "count": 0,
        "txns": 0,
        "error": "Query timeout"
      }
    },
    "4h": {
      "pacifica_traders": 595,
      "flashtrade_traders": 64,
      "jupiter_traders": 597,
      "liquidations": {
        "count": 0,
        "txns": 0,
        "error": "HTTP Error 429: Too Many Requests"
      },
      "wallet_overlap": {
        "drift_only": 3817,
        "jupiter_only": 2536,
        "pacifica_only": 7662,
        "drift_jupiter": 20,
        "drift_pacifica": 6,
        "jupiter_pacifica": 7,
        "all_three": 1,
        "multi_platform": 34
      },
      "adrena_traders": 5,
      "drift_traders": 652
    },
    "8h": {
      "pacifica_traders": 952,
      "jupiter_traders": 1213,
      "flashtrade_traders": 112,
      "adrena_traders": 14,
      "wallet_overlap": {
        "drift_only": 3817,
        "jupiter_only": 2536,
        "pacifica_only": 7662,
        "drift_jupiter": 20,
        "drift_pacifica": 6,
        "jupiter_pacifica": 7,
        "all_three": 1,
        "multi_platform": 34
      },
      "drift_traders": 974,
      "liquidations": {
        "count": 0,
        "txns": 0,
        "error": "Query timeout"
      }
    }
  },
  "whale_activity": {
    "whales": [
      {
        "address": "4TYEjn9PSpxoBNBXufeuNDRbytzvyyZtEUgXYSk8kYLZ",
        "source": "pacifica",
        "pnl_24h": 14976.773935,
        "volume": 355201.527662,
        "recent_txns": [
          {
            "signature": "GKM1mSk822p5eZ2wBvFrNz16Wvj5gryaUr8c8S5NXquprNLzxsVEP9qD9t2XJf32hSpmKxzEf1HDxXYkye2rY6z",
            "timestamp": "2026-02-15T23:31:16",
            "success": true,
            "slot": 400529050
          },
          {
            "signature": "33so1YmvqdR2ogKT3PWY6ViKRgep4KYBQkkds7fwcnCvDD81VueVMJHy1jAeukCfkA7KSzMdSumFkzau8F5vE5f4",
            "timestamp": "2026-02-15T23:31:09",
            "success": true,
            "slot": 400529029
          },
          {
            "signature": "3B522P4KU8hvLQYeSD9AXHPMTSkvSsBaJXXN5AXdGt9GeL91fVyfa5eSfBF9R8VrBqFNA3rzGm4n228c9FJt8uFZ",
            "timestamp": "2026-02-15T23:31:09",
            "success": true,
            "slot": 400529029
          },
          {
            "signature": "gfHzf1juzciHQiCe2wVGhX9mhXKx8pZaqmmongCj4ETovioz1PFQ75QM25dZRSFWPH7hDnV6oAc9XkM7rm4tCaa",
            "timestamp": "2026-02-15T23:31:08",
            "success": true,
            "slot": 400529028
          },
          {
            "signature": "5UaTfUpAFSdcW8YULDtHVwyLHmjMe8HKMpG3NwmDnAkx1kDZFrUX8en1T5HDmEmVmv1sF7fxM94xPucYLcx9eE2E",
            "timestamp": "2026-02-15T23:31:01",
            "success": true,
            "slot": 400529008
          }
        ],
        "txn_count_1h": 0,
        "is_active": false
      },
      {
        "address": "8AsJfKorQc1Wz8DABe9FZH18cgLd43bYwFST5JBJYSit",
        "source": "pacifica",
        "pnl_24h": 8937.263256,
        "volume": 0.0,
        "recent_txns": [],
        "txn_count_1h": 0,
        "is_active": false
      },
      {
        "address": "Ph9yECGodDAjiiSU9bpbJ8dds3ndWP1ngKo8h1K2QYv",
        "source": "pacifica",
        "pnl_24h": 8077.077383,
        "volume": 52430.55626,
        "recent_txns": [],
        "txn_count_1h": 0,
        "is_active": false
      },
      {
        "address": "49R9MFU7JopaCFXtpTwbaX8rkNW9wX6ddi7VtLUtMYJ1",
        "source": "pacifica",
        "pnl_24h": 7956.598409,
        "volume": 183.706891,
        "recent_txns": [],
        "txn_count_1h": 0,
        "is_active": false
      },
      {
        "address": "G6gyqHzb1yM3zfCD8K12qxMkv3Q99Dzn1qYLff41n1vf",
        "source": "pacifica",
        "pnl_24h": 6032.847802,
        "volume": 0.0,
        "recent_txns": [],
        "txn_count_1h": 0,
        "is_active": false
      },
      {
        "address": "BtGmu8gixQcNzADq4JHy9qpHUfwXDNoAo6CvUwTMNA3D",
        "source": "pacifica",
        "pnl_24h": 5915.144906,
        "volume": 12267.60916,
        "recent_txns": [],
        "txn_count_1h": 0,
        "is_active": false
      },
      {
        "address": "24q6voXjHkM3hZmMJPikHTJ7KmEuYyr1tJGLrT8CNWe3",
        "source": "pacifica",
        "pnl_24h": 5907.343342,
        "volume": 0.0,
        "recent_txns": [],
        "txn_count_1h": 0,
        "is_active": false
      },
      {
        "address": "AqVGeyoFiMkgdXPZEDkXetXm2n1dNPEocfRpBwDUX4yn",
        "source": "pacifica",
        "pnl_24h": 5791.136993,
        "volume": 258389.703925,
        "recent_txns": [],
        "txn_count_1h": 0,
        "is_active": false
      },
      {
        "address": "Dkp7y8LP6MWFXe3KtvQW2mzwaeZyiFHG1xeg8zG2asPr",
        "source": "pacifica",
        "pnl_24h": 5596.980607,
        "volume": 270.586,
        "recent_txns": [],
        "txn_count_1h": 0,
        "is_active": false
      },
      {
        "address": "4X1i2FRVBH6gU3psoLW6AirJSCeRi8eKsBHTyrizL1gJ",
        "source": "pacifica",
        "pnl_24h": 5306.942906,
        "volume": 0.0,
        "recent_txns": [],
        "txn_count_1h": 0,
        "is_active": false
      }
    ],
    "total_whales": 10,
    "active_last_1h": 0,
    "timestamp": "2026-02-17T10:14:56.144528Z"
  },
  "liquidations_rpc": {
    "drift": {
      "liquidations": [],
      "count": 0,
      "count_1h": 0,
      "checked_transactions": 50,
      "timestamp": "2026-02-17T10:19:36.318767Z"
    },
    "jupiter": {
      "liquidations": [],
      "count": 0,
      "count_1h": 0,
      "checked_transactions": 21,
      "timestamp": "2026-02-17T10:22:07.592032Z"
    },
    "total_count": 0,
    "total_count_1h": 0,
    "timestamp": "2026-02-17T10:22:07.592399Z"
  },
  "drift_traders_1h": 332,
  "jupiter_traders_1h": 177,
  "liquidations_1h": {
    "count": 0,
    "txns": 0,
    "error": "Query timeout"
  },
  "wallet_overlap": {
    "drift_only": 3817,
    "jupiter_only": 2536,
    "pacifica_only": 7662,
    "drift_jupiter": 20,
    "drift_pacifica": 6,
    "jupiter_pacifica": 7,
    "all_three": 1,
    "multi_platform": 34
  },
  "pnl_leaderboard": {
    "jupiter": {
      "top_winners": [
        {
          "address": "GraZv7zu9vGiqg5KCZeHkrKX2abvZi4Rm7NfZXxM6p1h",
          "pnl_weekly": 25541.608522,
          "volume_weekly": 3417388.567362,
          "markets": [
            "SOL"
          ]
        },
        {
          "address": "9UoLUdQDY3NcrP66uw7Y41o2GVQQqysWecaj1pNQaQuW",
          "pnl_weekly": 13901.451835,
          "volume_weekly": 5796758.32484,
          "markets": [
            "SOL"
          ]
        },
        {
          "address": "H7599BJG5Je8aCwrV2p8mK7mpwNe3e9PzZ78vwXuJEQ2",
          "pnl_weekly": 12846.245618,
          "volume_weekly": 1149518.060734,
          "markets": [
            "SOL"
          ]
        },
        {
          "address": "3dqwqVUpc3y4L9ESryUfAr6ouUDTsZs3VEj25iEoXhcm",
          "pnl_weekly": 10569.627603,
          "volume_weekly": 3438977.432819,
          "markets": [
            "SOL",
            "BTC"
          ]
        },
        {
          "address": "5TdTFGzKKmjQ1XEenkjwg8mEB4D9g3hwtXHDxoVtNLYU",
          "pnl_weekly": 10414.254732,
          "volume_weekly": 2327728.921544,
          "markets": [
            "SOL"
          ]
        },
        {
          "address": "yCv867J26x1VfDqADavi2o6A364Z4YJ644YBD7eLrc1",
          "pnl_weekly": 4636.514832,
          "volume_weekly": 1419970.744538,
          "markets": [
            "BTC"
          ]
        },
        {
          "address": "8i9AEWwYqedyL6Jbth5ZvMuEjov5y6D1t5asWQRo32bP",
          "pnl_weekly": 4618.871107,
          "volume_weekly": 1302358.113926,
          "markets": [
            "SOL"
          ]
        },
        {
          "address": "ZGKRm6RCeXPd1zDZJpwYL4mHMdGKg4Rv1Yh21JjaKNS",
          "pnl_weekly": 4369.573704,
          "volume_weekly": 2610441.4267720003,
          "markets": [
            "BTC",
            "ETH"
          ]
        },
        {
          "address": "GqQWxXmrix5beLio1XpdEibjXsQWrYLesy7bHjT7zRPb",
          "pnl_weekly": 4325.019877000001,
          "volume_weekly": 8083244.691339999,
          "markets": [
            "SOL",
            "BTC"
          ]
        },
        {
          "address": "EkWGeTV6giB28V6X3vCbzGT9oUCUVN5UFLQa4s82JB6Q",
          "pnl_weekly": 4302.047235,
          "volume_weekly": 193034.995943,
          "markets": [
            "SOL"
          ]
        },
        {
          "address": "AiDNweo9kCJcrAQKM7DXYT5EoSpcyU9iH7zAEDaiaboE",
          "pnl_weekly": 4243.37365,
          "volume_weekly": 75482.994895,
          "markets": [
            "SOL"
          ]
        },
        {
          "address": "5yJsWusop4D6b5xQ7f8FMqNyzFNU2PvXcJGfqTA33XNz",
          "pnl_weekly": 3404.530041,
          "volume_weekly": 1339934.2486,
          "markets": [
            "SOL",
            "BTC"
          ]
        },
        {
          "address": "B8X36GEFkdv7NyHkeXh4Wd8zyxhXcVfHnZgYw5iVyWYP",
          "pnl_weekly": 3313.105324,
          "volume_weekly": 847468.795958,
          "markets": [
            "BTC"
          ]
        },
        {
          "address": "ERDwzNb2vZ3VfPrNEiBMXC5E1EqtwFNfVjB142DSyn4U",
          "pnl_weekly": 3046.793405,
          "volume_weekly": 663011.348049,
          "markets": [
            "SOL"
          ]
        },
        {
          "address": "HUQ5EJcqcXEM9ohNfFxu53yA6gnpujAEbqgUYm8wyhcn",
          "pnl_weekly": 2492.795118,
          "volume_weekly": 73316.961863,
          "markets": [
            "SOL"
          ]
        },
        {
          "address": "2N27oPaMe5DFFQECznAqTvbNLMApjd3HEhHTAB9XYETS",
          "pnl_weekly": 2419.398286,
          "volume_weekly": 2452201.476656,
          "markets": [
            "SOL"
          ]
        },
        {
          "address": "GuvvKenQqwydPpL6weF6pypscXgnEbbqyZBkBJ9rjeSk",
          "pnl_weekly": 2172.455804,
          "volume_weekly": 977657.38935,
          "markets": [
            "SOL"
          ]
        },
        {
          "address": "emagyoxQTibVQ4j9P9qfFAaxV1ai3SULhkSwkACmuEP",
          "pnl_weekly": 2069.902837,
          "volume_weekly": 439650.045278,
          "markets": [
            "BTC"
          ]
        },
        {
          "address": "9epADqAxdrt1itzjU6hndq3SCqYF48k5S65SiGuhUihW",
          "pnl_weekly": 2057.486819,
          "volume_weekly": 265499.308347,
          "markets": [
            "BTC"
          ]
        },
        {
          "address": "64NqLKgMPQvcJoD27Mu9Zzb6s5dBpmTWR9JnCjNSgvKJ",
          "pnl_weekly": 1770.559386,
          "volume_weekly": 280034.862595,
          "markets": [
            "SOL",
            "BTC"
          ]
        },
        {
          "address": "7V3khWndkx94NKJGn4YcEi8VJGufes8sjKvCmMX5VK9h",
          "pnl_weekly": 1769.601438,
          "volume_weekly": 137000.0,
          "markets": [
            "SOL"
          ]
        },
        {
          "address": "BhqzZP2YkL4GUUL3ujkkauoSPmqKqAFhH8Xq3zWunTn6",
          "pnl_weekly": 1746.404952,
          "volume_weekly": 90764.511804,
          "markets": [
            "SOL"
          ]
        },
        {
          "address": "6VBLkoPNL2RYMdnmxfaWs56edEKAQUc3uNcZGbY2U3mu",
          "pnl_weekly": 1729.603581,
          "volume_weekly": 1837053.71704,
          "markets": [
            "SOL"
          ]
        },
        {
          "address": "HhnQE3zKBE2gmbFpFVrNdyFb4U1nWbqyK9ZxCxKq7WWT",
          "pnl_weekly": 1659.748915,
          "volume_weekly": 1050238.199433,
          "markets": [
            "SOL"
          ]
        },
        {
          "address": "9pd44yw5Hy42HTAXwWraRGdQXqPvogcCrCPU1CEFadN7",
          "pnl_weekly": 1641.299538,
          "volume_weekly": 396249.996872,
          "markets": [
            "SOL"
          ]
        },
        {
          "address": "A3uoq6zxz6cUBaiKoDK9iAKQ64WoTSyqfswN7cqvSvfV",
          "pnl_weekly": 1635.72879,
          "volume_weekly": 80031.795145,
          "markets": [
            "SOL"
          ]
        },
        {
          "address": "3DNgYB3kVoo6eAPr8jYdCoMwtnjiteeNf3Voam8ybzME",
          "pnl_weekly": 1622.225365,
          "volume_weekly": 262905.881083,
          "markets": [
            "SOL"
          ]
        },
        {
          "address": "AQEHYbF9qGxh5c8Q8iAmNQ24JXxFebvjXgpZjzSFm8in",
          "pnl_weekly": 1610.622222,
          "volume_weekly": 145377.316822,
          "markets": [
            "SOL"
          ]
        },
        {
          "address": "9CRZXUJfNx2JW4topakpa7yGEiijVodw3UXvXvEa4dEj",
          "pnl_weekly": 1544.255146,
          "volume_weekly": 268957.794624,
          "markets": [
            "SOL"
          ]
        },
        {
          "address": "6SQPAbuiyKq35dXc97zHUZcjPfe67zCCn8rCX5ysycNe",
          "pnl_weekly": 1535.950794,
          "volume_weekly": 38571.583304,
          "markets": [
            "SOL"
          ]
        },
        {
          "address": "5ZuV8eqkvzYFVEKbLvGBdexL2tFv7E5BCd2HZpjqbdg",
          "pnl_weekly": 1461.36612,
          "volume_weekly": 6237096.577378,
          "markets": [
            "SOL"
          ]
        },
        {
          "address": "3YcggnrbwxABVnhqtdHmLo8KC1EPcJtLCLsRrnV6VXvs",
          "pnl_weekly": 1432.334328,
          "volume_weekly": 936546.225683,
          "markets": [
            "SOL"
          ]
        },
        {
          "address": "5AhQynjYgTmM2D3J6eQFUCByyeWgcBohhGrkmLiDW1ib",
          "pnl_weekly": 1380.041487,
          "volume_weekly": 375093.138456,
          "markets": [
            "SOL"
          ]
        },
        {
          "address": "AkNn6UUMY5PgN2bcMYSCuLpMheYxBRDSh5W1wG9ZXtEq",
          "pnl_weekly": 1351.824015,
          "volume_weekly": 71841.973518,
          "markets": [
            "SOL"
          ]
        },
        {
          "address": "Fyc38gFEPqQJqgT2qb6cZ28GPgRp16f2fLw3dK8fK2eV",
          "pnl_weekly": 1350.399458,
          "volume_weekly": 705681.432161,
          "markets": [
            "SOL"
          ]
        },
        {
          "address": "72LVTNEoRPrC6QnWeoWTznxkcnbU5PXu2GL7tFQ5mF77",
          "pnl_weekly": 1283.57877,
          "volume_weekly": 395576.495566,
          "markets": [
            "SOL"
          ]
        },
        {
          "address": "3JswLZRXpATqzPtZedEyKw3wPd2ncH2UetpWptPCy8du",
          "pnl_weekly": 1264.115956,
          "volume_weekly": 870909.843198,
          "markets": [
            "BTC"
          ]
        },
        {
          "address": "DHRd4vQ3JwJtS1TZ5kbdYaXP72juNzABtz2Bvee8AUoz",
          "pnl_weekly": 1251.238941,
          "volume_weekly": 402339.171415,
          "markets": [
            "SOL"
          ]
        },
        {
          "address": "rQEH5ZsJ6ztjffKWfWmnDtHRMJ82zqdmWiH2motmvwr",
          "pnl_weekly": 1227.308511,
          "volume_weekly": 210810.189639,
          "markets": [
            "SOL"
          ]
        },
        {
          "address": "4wtXYahhz7CJHzuUWoURd76ixdYSZp3Y17hwLbPZJpdo",
          "pnl_weekly": 1208.411039,
          "volume_weekly": 100000.0,
          "markets": [
            "BTC"
          ]
        },
        {
          "address": "7fYZ1xjcT6gJ9gYDuchy4dEoS5jrt128LrMvd2BcVGf4",
          "pnl_weekly": 1152.2675049999998,
          "volume_weekly": 633199.825034,
          "markets": [
            "BTC",
            "ETH"
          ]
        },
        {
          "address": "EWyLu1E62iNLoXnimbjpwknwiJ1zLo9pyYzw32o5fpPB",
          "pnl_weekly": 1151.803526,
          "volume_weekly": 390685.707896,
          "markets": [
            "SOL"
          ]
        },
        {
          "address": "BVZa992V4hbixxoBApgR9ZLiMjgKT24SqCsDvYRmA87K",
          "pnl_weekly": 1132.501701,
          "volume_weekly": 7166.932812,
          "markets": [
            "SOL"
          ]
        },
        {
          "address": "J4aGiHemVzcxxjcwMKm77A9uUpB4Yf32KbEBrwtKG31a",
          "pnl_weekly": 1113.3405,
          "volume_weekly": 72082.758461,
          "markets": [
            "SOL"
          ]
        },
        {
          "address": "Gj5DYFS6q3EfNraFhoj2uR77yb1DPLFumJkFEUzNgh33",
          "pnl_weekly": 1095.351647,
          "volume_weekly": 38517.745234,
          "markets": [
            "SOL"
          ]
        },
        {
          "address": "DjcKkKxt69qvvVNhqTfmCs6JsQWZLL786jopFemSyTRV",
          "pnl_weekly": 1094.957699,
          "volume_weekly": 49906.747085,
          "markets": [
            "SOL"
          ]
        },
        {
          "address": "AsGeA2dPYjE51wuvA1PJZQjgRfYCgCrfKgtjUJPykojB",
          "pnl_weekly": 1075.409509,
          "volume_weekly": 5634.790137,
          "markets": [
            "SOL"
          ]
        },
        {
          "address": "8rf6y6HURgWShRQhAzMXQmGn9tt15bZ6XSi5T7coRjpw",
          "pnl_weekly": 1066.845738,
          "volume_weekly": 173480.85719,
          "markets": [
            "SOL"
          ]
        },
        {
          "address": "WHuRRbiaUCw7CivXcFUeWjM8pVTpVidhNinMeaBDJWT",
          "pnl_weekly": 1043.467519,
          "volume_weekly": 187624.219752,
          "markets": [
            "SOL"
          ]
        },
        {
          "address": "7AVfkAXAQ5ZjBDCT2tXoqhnXy57MMMaunHKh1ec1DpdA",
          "pnl_weekly": 1020.839974,
          "volume_weekly": 366692.87479,
          "markets": [
            "SOL"
          ]
        }
      ],
      "top_losers": [],
      "total_traders": 140
    },
    "pacifica": {
      "top_winners": [
        {
          "address": "4TYEjn9PSpxoBNBXufeuNDRbytzvyyZtEUgXYSk8kYLZ",
          "pnl_24h": 14976.773935,
          "pnl_7d": 10252.568579,
          "pnl_30d": 1365106.2922,
          "pnl_all_time": 1945452.208395,
          "volume_24h": 355201.527662,
          "volume_7d": 5714890.033081,
          "equity": 414753.040419
        },
        {
          "address": "8AsJfKorQc1Wz8DABe9FZH18cgLd43bYwFST5JBJYSit",
          "pnl_24h": 8937.263256,
          "pnl_7d": -1820.774862,
          "pnl_30d": -42830.426341,
          "pnl_all_time": -43966.509417,
          "volume_24h": 0.0,
          "volume_7d": 585001.37186,
          "equity": 55880.592811
        },
        {
          "address": "Ph9yECGodDAjiiSU9bpbJ8dds3ndWP1ngKo8h1K2QYv",
          "pnl_24h": 8077.077383,
          "pnl_7d": -12237.780104,
          "pnl_30d": 4419.125126,
          "pnl_all_time": 4051.519991,
          "volume_24h": 52430.55626,
          "volume_7d": 87598.9652,
          "equity": 87741.239403
        },
        {
          "address": "49R9MFU7JopaCFXtpTwbaX8rkNW9wX6ddi7VtLUtMYJ1",
          "pnl_24h": 7956.598409,
          "pnl_7d": -18171.983783,
          "pnl_30d": 22237.899829,
          "pnl_all_time": -4294.159991,
          "volume_24h": 183.706891,
          "volume_7d": 32221.367475,
          "equity": 256460.74371
        },
        {
          "address": "G6gyqHzb1yM3zfCD8K12qxMkv3Q99Dzn1qYLff41n1vf",
          "pnl_24h": 6032.847802,
          "pnl_7d": 1662.700031,
          "pnl_30d": -21232.599709,
          "pnl_all_time": 733.419003,
          "volume_24h": 0.0,
          "volume_7d": 135.9868,
          "equity": 77611.570587
        },
        {
          "address": "BtGmu8gixQcNzADq4JHy9qpHUfwXDNoAo6CvUwTMNA3D",
          "pnl_24h": 5915.144906,
          "pnl_7d": 8793.231355,
          "pnl_30d": 51451.146347,
          "pnl_all_time": 51451.146347,
          "volume_24h": 12267.60916,
          "volume_7d": 169452.01276,
          "equity": 151451.146347
        },
        {
          "address": "24q6voXjHkM3hZmMJPikHTJ7KmEuYyr1tJGLrT8CNWe3",
          "pnl_24h": 5907.343342,
          "pnl_7d": 6912.653459,
          "pnl_30d": 38294.011561,
          "pnl_all_time": 38294.011561,
          "volume_24h": 0.0,
          "volume_7d": 0.0,
          "equity": 88307.605007
        },
        {
          "address": "AqVGeyoFiMkgdXPZEDkXetXm2n1dNPEocfRpBwDUX4yn",
          "pnl_24h": 5791.136993,
          "pnl_7d": -5244.322526,
          "pnl_30d": -58333.133931,
          "pnl_all_time": -60477.814414,
          "volume_24h": 258389.703925,
          "volume_7d": 1953221.191085,
          "equity": 55904.273424
        },
        {
          "address": "Dkp7y8LP6MWFXe3KtvQW2mzwaeZyiFHG1xeg8zG2asPr",
          "pnl_24h": 5596.980607,
          "pnl_7d": 1379.851549,
          "pnl_30d": -25959.215439,
          "pnl_all_time": -21812.117416,
          "volume_24h": 270.586,
          "volume_7d": 352.0376,
          "equity": 82604.490331
        },
        {
          "address": "4X1i2FRVBH6gU3psoLW6AirJSCeRi8eKsBHTyrizL1gJ",
          "pnl_24h": 5306.942906,
          "pnl_7d": 7916.777371,
          "pnl_30d": 95800.681446,
          "pnl_all_time": 93575.236806,
          "volume_24h": 0.0,
          "volume_7d": 0.0,
          "equity": 169659.186978
        },
        {
          "address": "5RX2DD425DHj3VAouTbJWHtmBmzi2oUmuErwmfwgxs8n",
          "pnl_24h": 4739.424539,
          "pnl_7d": -2552.593049,
          "pnl_30d": 11461.70378,
          "pnl_all_time": 5053.237243,
          "volume_24h": 0.0,
          "volume_7d": 164121.888474,
          "equity": 76385.270883
        },
        {
          "address": "HgHdeVbDJyd5nvcfd4odxtUoKdHeKsEzAjQFsyp48uX6",
          "pnl_24h": 4616.493657,
          "pnl_7d": 9323.924728,
          "pnl_30d": 11410.766461,
          "pnl_all_time": -139.59109,
          "volume_24h": 0.0,
          "volume_7d": 0.0,
          "equity": 69852.41051
        },
        {
          "address": "6nkGPkKjJJqJRZQj1rCFUyfftFRzyKPGpfSZDXr5YuGd",
          "pnl_24h": 4611.80536,
          "pnl_7d": -20171.795214,
          "pnl_30d": 78879.25586,
          "pnl_all_time": 78879.372739,
          "volume_24h": 0.0,
          "volume_7d": 134757.104862,
          "equity": 134067.572934
        },
        {
          "address": "296PcXq7TUGrjzfBEjSFs3qrhNXiTxuteJKaoPDivo5e",
          "pnl_24h": 4085.548286,
          "pnl_7d": -180.193029,
          "pnl_30d": -64650.738356,
          "pnl_all_time": -84469.909984,
          "volume_24h": 0.0,
          "volume_7d": 0.0,
          "equity": 88427.590016
        },
        {
          "address": "6GcT3aY8VcyaC6yBKewKQqLJekdnfkTv8J44Q58zTwYD",
          "pnl_24h": 3669.585804,
          "pnl_7d": 429.919987,
          "pnl_30d": -35293.734966,
          "pnl_all_time": -30618.435047,
          "volume_24h": 0.0,
          "volume_7d": 0.0,
          "equity": 98380.564953
        },
        {
          "address": "6uC2TdJxxqhWMPSjs7u9YE5rWMQs1yhxkvk8BmBTPrpV",
          "pnl_24h": 3470.202703,
          "pnl_7d": 450.312509,
          "pnl_30d": 450.312509,
          "pnl_all_time": 450.312509,
          "volume_24h": 12.97491,
          "volume_7d": 266171.07801,
          "equity": 37391.546577
        },
        {
          "address": "P3BSKpoDFx7i9ioLchg7XZXGWATz1McaNy9t7oDo7LF",
          "pnl_24h": 3178.726266,
          "pnl_7d": 428.15878,
          "pnl_30d": -25871.055652,
          "pnl_all_time": -124919.28331,
          "volume_24h": 0.0,
          "volume_7d": 109511.1674,
          "equity": 45070.173772
        },
        {
          "address": "HtC4WT6JhKz8eojNigfiqSWykG74kfQmyDeM9f753aPQ",
          "pnl_24h": 3022.844308,
          "pnl_7d": -37871.02116,
          "pnl_30d": 188331.928448,
          "pnl_all_time": 427204.511835,
          "volume_24h": 3563808.734013,
          "volume_7d": 33007825.014161,
          "equity": 509208.511835
        },
        {
          "address": "97Nq39YDZq77pfPY97RLA8ScBbPapQEwkDUjYNZiuMUd",
          "pnl_24h": 2754.155687,
          "pnl_7d": 35753.949621,
          "pnl_30d": 37209.951464,
          "pnl_all_time": 15824.375832,
          "volume_24h": 46597.66755,
          "volume_7d": 74006.00276,
          "equity": 160966.974316
        },
        {
          "address": "JPLaNo52siAC6KDv66VP9y4eKKtNhwx6yKd8GFcjFGP",
          "pnl_24h": 2580.770441,
          "pnl_7d": 7758.382668,
          "pnl_30d": 109014.090419,
          "pnl_all_time": 109636.819313,
          "volume_24h": 0.0,
          "volume_7d": 0.0,
          "equity": 109210.220206
        },
        {
          "address": "26t38jFHWn42aDxREXC8FuWsPMgRGDp623PUErhU6knW",
          "pnl_24h": 2526.909837,
          "pnl_7d": 2956.857479,
          "pnl_30d": 2527.617077,
          "pnl_all_time": 2527.617077,
          "volume_24h": 0.0,
          "volume_7d": 9.75688,
          "equity": 22628.82367
        },
        {
          "address": "ACJKQ3AAsSb59BkcHRa4EVLYHCNPRiVrTQr9odBXrzZ4",
          "pnl_24h": 2501.18826,
          "pnl_7d": 3474.468744,
          "pnl_30d": 105064.941,
          "pnl_all_time": 67658.13938,
          "volume_24h": 19989.000001,
          "volume_7d": 414437.214967,
          "equity": 65098.567411
        },
        {
          "address": "8ef7254GSfFERTRUK8PtVSoVPU96NSmjzEat1adpkHgs",
          "pnl_24h": 2329.763191,
          "pnl_7d": 5821.741113,
          "pnl_30d": 106505.941683,
          "pnl_all_time": 95579.544272,
          "volume_24h": 161080.52553,
          "volume_7d": 427373.05089,
          "equity": 17314.473191
        },
        {
          "address": "8hCTAcoQSRUtZkzcA76DaPYGE9V8jtFcftE2WmMxF4Se",
          "pnl_24h": 2273.823782,
          "pnl_7d": 2660.782508,
          "pnl_30d": 39785.399503,
          "pnl_all_time": 45430.645406,
          "volume_24h": 0.0,
          "volume_7d": 0.0,
          "equity": 54101.680488
        },
        {
          "address": "9qrE5vcpWVghGLn8j9ju2jGrHXFVfbN2Jrus2nX6qNGH",
          "pnl_24h": 2013.150873,
          "pnl_7d": -1165.580788,
          "pnl_30d": 1224.005507,
          "pnl_all_time": -2518.024112,
          "volume_24h": 2499.84569,
          "volume_7d": 43760.2819,
          "equity": 8695.500746
        },
        {
          "address": "BkUTkCt4JwQQwczibKkP5TEjTCHkSogR44ppvQReTt5B",
          "pnl_24h": 1825.544195,
          "pnl_7d": -908.545758,
          "pnl_30d": -2624.822393,
          "pnl_all_time": -11467.238586,
          "volume_24h": 1486.05,
          "volume_7d": 47530.01511,
          "equity": 46777.231897
        },
        {
          "address": "7xGRx5WWsK91xv9YayPVzC3jXuULXUvcoMJkWacbQd6U",
          "pnl_24h": 1743.497309,
          "pnl_7d": -830.545287,
          "pnl_30d": -59873.103284,
          "pnl_all_time": -53632.187379,
          "volume_24h": 30.765,
          "volume_7d": 171.10736,
          "equity": 46360.858234
        },
        {
          "address": "ERhpzhe75aASxM6GSAvKigz22bMoHUZGm3FQu6zyQ3MP",
          "pnl_24h": 1592.743519,
          "pnl_7d": -220.334761,
          "pnl_30d": -4582.234307,
          "pnl_all_time": -6397.017688,
          "volume_24h": 0.0,
          "volume_7d": 275020.2102,
          "equity": 11122.689563
        },
        {
          "address": "C45As2diKNQHSARr5m16JLhA5iRPEhbGYvmxaF2ZihRM",
          "pnl_24h": 1552.355961,
          "pnl_7d": -3875.813091,
          "pnl_30d": -12150.358203,
          "pnl_all_time": 4813.452001,
          "volume_24h": 219.6,
          "volume_7d": 28428.608946,
          "equity": 54773.648612
        },
        {
          "address": "DdKAcvndDca5i7Xfk7aUa65dMKoDFPCp7hnzGoCnnmRa",
          "pnl_24h": 1535.099607,
          "pnl_7d": -2669.235879,
          "pnl_30d": 25627.263674,
          "pnl_all_time": 25514.458092,
          "volume_24h": 18.482,
          "volume_7d": 1024839.14832,
          "equity": 24179.297983
        },
        {
          "address": "HCAKppBaWY5HcmBrk8ALBUnsm9ZzvkoxpinAq9Je6ci1",
          "pnl_24h": 1486.637212,
          "pnl_7d": 1110.188597,
          "pnl_30d": 49694.676283,
          "pnl_all_time": 85794.544321,
          "volume_24h": 6692.11452,
          "volume_7d": 22174.325812,
          "equity": 42683.007069
        },
        {
          "address": "2oGPYzo7eLuKKYVZjUM2jQgbZqpA75sWLeuhBTSoSiqJ",
          "pnl_24h": 1464.689208,
          "pnl_7d": -9755.412049,
          "pnl_30d": 24931.178373,
          "pnl_all_time": 19139.348316,
          "volume_24h": 19833.90927,
          "volume_7d": 136813.271902,
          "equity": 40675.480502
        },
        {
          "address": "Ad2sZAQ1YexTwSkeSaf5bfXrdAKn99QRWKhn4Hd9tysR",
          "pnl_24h": 1382.355561,
          "pnl_7d": 1233.41274,
          "pnl_30d": 1233.41274,
          "pnl_all_time": 1223.830223,
          "volume_24h": 0.0,
          "volume_7d": 19394.00723,
          "equity": 41232.82274
        },
        {
          "address": "AQzj5vqR5LKQYNXTLxL1EKyY6tLaLNhNoDEBytpip9Tr",
          "pnl_24h": 1379.191314,
          "pnl_7d": 4720.095324,
          "pnl_30d": 2934.025893,
          "pnl_all_time": 3396.017059,
          "volume_24h": 0.0,
          "volume_7d": 214883.44977,
          "equity": 12765.576001
        },
        {
          "address": "DWGnkP4BCn4ZVfgZ9U9QZf5n5D9me7hAgj9r72m42uqT",
          "pnl_24h": 1283.524253,
          "pnl_7d": -51.239267,
          "pnl_30d": 13836.084764,
          "pnl_all_time": 14716.768558,
          "volume_24h": 19888.06203,
          "volume_7d": 41047.98465,
          "equity": 5717.488558
        },
        {
          "address": "A5crqomMVH3tnCEmnjwpST2kxA2YwMMpm9NH8vUE2sSn",
          "pnl_24h": 1206.915982,
          "pnl_7d": 1993.055156,
          "pnl_30d": 3886.787709,
          "pnl_all_time": 3886.787709,
          "volume_24h": 571412.1621,
          "volume_7d": 2430629.3335,
          "equity": 16993.055709
        },
        {
          "address": "3jcFqKerxpqEg1PSPEKcpcPxT3PyhD1tMT1Cre44J4Ea",
          "pnl_24h": 1205.641665,
          "pnl_7d": 1243.804782,
          "pnl_30d": 1243.804782,
          "pnl_all_time": 1243.804782,
          "volume_24h": 0.0,
          "volume_7d": 48766.49957,
          "equity": 26243.561968
        },
        {
          "address": "A6W5iDnsjkE5UbUnmfNi2dJHJHEo27VszXTwyah5tCT4",
          "pnl_24h": 1198.75421,
          "pnl_7d": -9324.495626,
          "pnl_30d": 8884.498284,
          "pnl_all_time": 5620.301478,
          "volume_24h": 0.0,
          "volume_7d": 10909.63059,
          "equity": 23120.301478
        },
        {
          "address": "6obfdGue9qWANxVMdXz9Zyxh3Jn1kHM1YmVVBQnT4NuL",
          "pnl_24h": 1181.90503,
          "pnl_7d": 2085.119659,
          "pnl_30d": 4979.708408,
          "pnl_all_time": -16547.561975,
          "volume_24h": 21794.24115,
          "volume_7d": 51585.61231,
          "equity": 6085.931934
        },
        {
          "address": "4pTfJtAQ2xPrrAAyULsJDgGc3YzGf1ZzqnUVnXdK6K3K",
          "pnl_24h": 1033.554079,
          "pnl_7d": -209.835172,
          "pnl_30d": 31492.855086,
          "pnl_all_time": 26471.696729,
          "volume_24h": 17405.12011,
          "volume_7d": 32924.321,
          "equity": 56479.136504
        },
        {
          "address": "EfLVCLeC64YVm4Kt4NusfacvxQoDew4acpReBuCdk2wB",
          "pnl_24h": 974.48437,
          "pnl_7d": 941.6348,
          "pnl_30d": 13327.866899,
          "pnl_all_time": -41665.759562,
          "volume_24h": 744635.99004,
          "volume_7d": 4131682.575083,
          "equity": 219077.28659
        },
        {
          "address": "4q5AywsD1BU7i3nAx3GuTGSgpZkzaf14AiS1k2xx9oLD",
          "pnl_24h": 856.571359,
          "pnl_7d": 1596.642944,
          "pnl_30d": -31229.050129,
          "pnl_all_time": -37810.930867,
          "volume_24h": 0.0,
          "volume_7d": 117307.09537,
          "equity": 10183.069133
        },
        {
          "address": "BEE2vnGCXdt8x1PyaKBjghBEKJhzsnHEXLAkBkvbTFL4",
          "pnl_24h": 823.871689,
          "pnl_7d": -21205.468632,
          "pnl_30d": -42813.865176,
          "pnl_all_time": -122680.534427,
          "volume_24h": 399098.552078,
          "volume_7d": 2227227.870758,
          "equity": 222196.565573
        },
        {
          "address": "DftLLtov8QdYUFFnV7z2nBrjUDUrMyojAD6h83BB545G",
          "pnl_24h": 786.039311,
          "pnl_7d": 2763.654153,
          "pnl_30d": 22337.664152,
          "pnl_all_time": 29480.87143,
          "volume_24h": 114.51639,
          "volume_7d": 18090.941299,
          "equity": 219479.08243
        },
        {
          "address": "2SX4dGazRgxiNAsZYP4wmUE1N4RkAPbFLir2Y28HRwSu",
          "pnl_24h": 697.756026,
          "pnl_7d": 314.972276,
          "pnl_30d": -2379.321284,
          "pnl_all_time": 18.042117,
          "volume_24h": 5584.91261,
          "volume_7d": 377538.533818,
          "equity": 15744.849408
        },
        {
          "address": "9ixkJDcrveSQ9CqUhCt6iviqBpSGieNuWPWuEVDQtVja",
          "pnl_24h": 697.435568,
          "pnl_7d": -5940.923378,
          "pnl_30d": -7054.129318,
          "pnl_all_time": -20498.890849,
          "volume_24h": 57718.9818,
          "volume_7d": 626258.46711,
          "equity": 29301.109151
        },
        {
          "address": "FXKVt4ncjrj9WtgUStGPafPYtin1rNkT4Ba12e4s47U5",
          "pnl_24h": 666.974226,
          "pnl_7d": 780.221355,
          "pnl_30d": -1548.728638,
          "pnl_all_time": 8035.266648,
          "volume_24h": 215.6347,
          "volume_7d": 1264.45666,
          "equity": 8414.149106
        },
        {
          "address": "HKfd1is4v2kKsPMT3aoAEiKYbGbCVvsxjr3AXc83QXLF",
          "pnl_24h": 662.40209,
          "pnl_7d": 2490.909373,
          "pnl_30d": 3892.908637,
          "pnl_all_time": -11247.565553,
          "volume_24h": 1463.617835,
          "volume_7d": 79679.677306,
          "equity": 10763.42905
        },
        {
          "address": "CcBkvidmanT6zHGQPRHXDHgLq7M6fazaAVajTEAGoCMf",
          "pnl_24h": 634.394225,
          "pnl_7d": -2346.772827,
          "pnl_30d": 21102.401403,
          "pnl_all_time": 20245.870539,
          "volume_24h": 0.0,
          "volume_7d": 10168.0,
          "equity": 22771.762295
        },
        {
          "address": "9UdMr8BXBpNLERWiVPq37owCcimyecLeuJXqBRUnaGj7",
          "pnl_24h": 622.860594,
          "pnl_7d": 887.996795,
          "pnl_30d": 1603.639207,
          "pnl_all_time": -2701.700205,
          "volume_24h": 0.0,
          "volume_7d": 187837.36551,
          "equity": 3776.089735
        }
      ],
      "top_losers": [
        {
          "address": "BEE5U8G8KrYRagtnHcHqtDES9ygpg1k5JFiYLMwzF8MQ",
          "pnl_24h": -11636.256631,
          "pnl_7d": 14084.364743,
          "pnl_30d": 12418.856031,
          "pnl_all_time": 12418.856031,
          "volume_24h": 235740.908522,
          "volume_7d": 1863185.818065,
          "equity": 173874.856031
        },
        {
          "address": "DbB3TxHkGEA5jLY7DCbxbQWRNVrteUbHBhYwAgwL5TJh",
          "pnl_24h": -10982.946886,
          "pnl_7d": -9777.163205,
          "pnl_30d": 73990.255398,
          "pnl_all_time": 29273.672435,
          "volume_24h": 0.0,
          "volume_7d": 229706.02472,
          "equity": 172023.005487
        },
        {
          "address": "GDoEJ87ezVKgFXQ9N4RpPuUVrPKfhitLQpgkHczJUPVL",
          "pnl_24h": -9365.477442,
          "pnl_7d": -9972.278003,
          "pnl_30d": 39311.961234,
          "pnl_all_time": 34139.951011,
          "volume_24h": 0.0,
          "volume_7d": 640.775,
          "equity": 134139.951011
        },
        {
          "address": "Hr5WFpPR9xUwD5WVWYKoLYbNKUaTAx2mn3B147KDgMAc",
          "pnl_24h": -8960.194025,
          "pnl_7d": -10506.634347,
          "pnl_30d": 44285.555094,
          "pnl_all_time": 58949.818426,
          "volume_24h": 0.0,
          "volume_7d": 681.1196,
          "equity": 158949.818426
        },
        {
          "address": "4G6XZC176LK96i5pMwNEvdhgH6HstkNhRJqFmiGssdNp",
          "pnl_24h": -8896.329395,
          "pnl_7d": -26280.681008,
          "pnl_30d": -160648.643412,
          "pnl_all_time": -158991.855073,
          "volume_24h": 86.03,
          "volume_7d": 3749439.00774,
          "equity": 53148.966588
        },
        {
          "address": "J2bdNnwrfDUEm3gjpduWVWJNKvhEnu3EDo9EN2FsDj9d",
          "pnl_24h": -5619.789562,
          "pnl_7d": 13920.757733,
          "pnl_30d": 32629.518975,
          "pnl_all_time": 47749.675126,
          "volume_24h": 0.0,
          "volume_7d": 0.0,
          "equity": 63798.675787
        },
        {
          "address": "YjCD9Gek6MVY9t3MLEGYYdZLeaF6MZrpgZraayWsv9E",
          "pnl_24h": -4872.235748,
          "pnl_7d": 16544.064153,
          "pnl_30d": -200428.492555,
          "pnl_all_time": 1474781.54817,
          "volume_24h": 159852.72236,
          "volume_7d": 4208563.22126,
          "equity": 840021.150999
        },
        {
          "address": "DrNBiFihydX12wJ2mTdQrsiXfPvAnU9WfrYsSH5UDCvL",
          "pnl_24h": -4496.524363,
          "pnl_7d": -9806.494569,
          "pnl_30d": -26366.451794,
          "pnl_all_time": -26868.581208,
          "volume_24h": 16.16112,
          "volume_7d": 3730667.73652,
          "equity": 34121.061645
        },
        {
          "address": "BdQi2GU4Zx4Em1SuGuLeAigys9jgLxdiicmohWsP2J3x",
          "pnl_24h": -4405.737999,
          "pnl_7d": -44551.126143,
          "pnl_30d": -54718.856229,
          "pnl_all_time": -56915.851615,
          "volume_24h": 115739.861374,
          "volume_7d": 354871.177854,
          "equity": 63575.083416
        },
        {
          "address": "Eu12Nqn4v2atnTqNb8MwYnC4kxDpv7dVgnhxPcru1bGt",
          "pnl_24h": -4330.73835,
          "pnl_7d": 57457.771607,
          "pnl_30d": -350164.455769,
          "pnl_all_time": -316407.813084,
          "volume_24h": 332606.864795,
          "volume_7d": 4402384.662192,
          "equity": 983584.45859
        },
        {
          "address": "9eSnj4TniTi1JkeeASTyzXWSCEzHM8DjNf7XhD1rQ6Qu",
          "pnl_24h": -3664.02729,
          "pnl_7d": 261.744278,
          "pnl_30d": 48633.59794,
          "pnl_all_time": 53170.682988,
          "volume_24h": 41.96394,
          "volume_7d": 262827.03116,
          "equity": 28400.915934
        },
        {
          "address": "2rEEo6bXeXLacwAnQwtw5YEz8CdnTGrQ2LQ2banK4mRw",
          "pnl_24h": -3630.892227,
          "pnl_7d": 17185.976552,
          "pnl_30d": -54164.709351,
          "pnl_all_time": -49126.537964,
          "volume_24h": 781496.994486,
          "volume_7d": 10841984.752855,
          "equity": 163568.921903
        },
        {
          "address": "E1vcL1c7Q2AZ15zb5iFNNtEhVSzSzmMF55y3zEhYJcSG",
          "pnl_24h": -3217.667232,
          "pnl_7d": 2060.521445,
          "pnl_30d": 35907.452749,
          "pnl_all_time": 35907.452749,
          "volume_24h": 19.476,
          "volume_7d": 142.8565,
          "equity": 117741.485553
        },
        {
          "address": "8Xqw1VU9qwY3vrtqQoWaGziMKoGdpv2CN6VXzg8ReHvV",
          "pnl_24h": -3114.384496,
          "pnl_7d": 1675.105055,
          "pnl_30d": 30212.848621,
          "pnl_all_time": 31497.957752,
          "volume_24h": 136.317,
          "volume_7d": 116548.63534,
          "equity": 27105.361554
        },
        {
          "address": "BBXooWjX71tmNMivEqvsmqDVzKQF7zfJPgEoZUsRXtPE",
          "pnl_24h": -3066.536699,
          "pnl_7d": 5887.810172,
          "pnl_30d": -124.300363,
          "pnl_all_time": -230.137922,
          "volume_24h": 0.0,
          "volume_7d": 30489.27609,
          "equity": 11460.022609
        },
        {
          "address": "BEE9evCYoXTQpVHjnLQsXVGi9ewe8dyp1rSejeDvKK8Q",
          "pnl_24h": -2964.728727,
          "pnl_7d": -238.059961,
          "pnl_30d": -67371.48683,
          "pnl_all_time": -55272.784619,
          "volume_24h": 143712.62708,
          "volume_7d": 1213173.048521,
          "equity": 44765.215382
        },
        {
          "address": "GTU92nBC8LMyt9W4Qqc319BFR1vpkNNPAbt4QCnX7kZ6",
          "pnl_24h": -2537.456768,
          "pnl_7d": 1624.691071,
          "pnl_30d": -109192.734287,
          "pnl_all_time": 13991.396866,
          "volume_24h": 4507358.42839,
          "volume_7d": 43491852.641343,
          "equity": 463909.782404
        },
        {
          "address": "AoVHrciuHrqSsSty2wK7ZgVYscmiLNrGm1NXPPgdWaPf",
          "pnl_24h": -2533.011171,
          "pnl_7d": -3958.995673,
          "pnl_30d": -39837.630425,
          "pnl_all_time": -41379.67994,
          "volume_24h": 795.3568,
          "volume_7d": 3058.5408,
          "equity": 21457.631733
        },
        {
          "address": "BcDgu34n4JtSraG429avhokt2EedbprDFWB3BuD6etLy",
          "pnl_24h": -1990.422212,
          "pnl_7d": 2086.391757,
          "pnl_30d": 4349.439738,
          "pnl_all_time": 34837.696879,
          "volume_24h": 0.0,
          "volume_7d": 102375.91611,
          "equity": 54837.696879
        },
        {
          "address": "ADrHFm9418oZcBAvaqdtnfkRCh8B2vThAe1eAdyhvxDM",
          "pnl_24h": -1990.422212,
          "pnl_7d": 2086.3311,
          "pnl_30d": 6539.958858,
          "pnl_all_time": 31790.681626,
          "volume_24h": 0.0,
          "volume_7d": 102375.91611,
          "equity": 60780.657632
        },
        {
          "address": "EbaoY81MhbrXiP52Nk35XTeYDLwaiKooLMWgfNMBJnpf",
          "pnl_24h": -1990.422212,
          "pnl_7d": 2086.391757,
          "pnl_30d": 12202.59741,
          "pnl_all_time": 3355.076107,
          "volume_24h": 0.0,
          "volume_7d": 102375.91611,
          "equity": 85309.792332
        },
        {
          "address": "S9mRpbkJpgstvaVYireoKygjMkW2rs9kZg4baG4ieZn",
          "pnl_24h": -1824.268956,
          "pnl_7d": 953.603476,
          "pnl_30d": 40617.719181,
          "pnl_all_time": 40617.719181,
          "volume_24h": 16.922,
          "volume_7d": 132.64,
          "equity": 80639.708556
        },
        {
          "address": "HQWz5Pje7tbqJVTy7ES41P4moxQWHXhCqMYGnsQirzq9",
          "pnl_24h": -1771.485211,
          "pnl_7d": 910.959017,
          "pnl_30d": 11565.644239,
          "pnl_all_time": -20702.958519,
          "volume_24h": 0.0,
          "volume_7d": 14195.43005,
          "equity": 112997.041481
        },
        {
          "address": "6npgtLJ7hTyyyEU2J5fcoATsC8FqN1UvzafGMmKQDAii",
          "pnl_24h": -1724.742599,
          "pnl_7d": -2555.061479,
          "pnl_30d": 42070.44495,
          "pnl_all_time": 53082.480503,
          "volume_24h": 6.88,
          "volume_7d": 61.9587,
          "equity": 41567.475012
        },
        {
          "address": "F5BcMNcVyxeWqXyEivRc5NuUrFMZgNxnmwVvLpRKLdaf",
          "pnl_24h": -1717.741271,
          "pnl_7d": 1080.485379,
          "pnl_30d": -23319.777448,
          "pnl_all_time": 26956.3553,
          "volume_24h": 1096434.50233,
          "volume_7d": 10904685.226427,
          "equity": 90956.3553
        },
        {
          "address": "CftUjvv5sEPrnUE8XBcXu4q4Mc88TqGtrfkwStCX6Ci3",
          "pnl_24h": -1591.276135,
          "pnl_7d": -8916.461791,
          "pnl_30d": -18603.824928,
          "pnl_all_time": -63446.37319,
          "volume_24h": 0.0,
          "volume_7d": 162627.23385,
          "equity": 77730.885936
        },
        {
          "address": "DCmDxhZ6Tz8k46th3aEQrMHPGmRXeKrrakBitMm4V9mz",
          "pnl_24h": -1578.716602,
          "pnl_7d": 295.345834,
          "pnl_30d": -18811.683053,
          "pnl_all_time": 4935.158651,
          "volume_24h": 1735441.117929,
          "volume_7d": 12428934.103522,
          "equity": 114934.658651
        },
        {
          "address": "EbQ9Vw7QcuX6x3MxXhh34xGA9gV4kC6QVREZy7WGDuAW",
          "pnl_24h": -1548.495018,
          "pnl_7d": -1548.495018,
          "pnl_30d": -1548.495018,
          "pnl_all_time": -1548.495018,
          "volume_24h": 22312.92638,
          "volume_7d": 22312.92638,
          "equity": 4590.093131
        },
        {
          "address": "6ihYAA1rpjVfdfBwjC27zwc7Ygc5JLtbN8QGZKtSvWG3",
          "pnl_24h": -1368.353541,
          "pnl_7d": 1434.351688,
          "pnl_30d": -11171.419395,
          "pnl_all_time": -7155.173675,
          "volume_24h": 0.0,
          "volume_7d": 70381.15024,
          "equity": 57186.501099
        },
        {
          "address": "3XPbDDeNm1GYzeVt4gYz9rsLgXVpQcWYJb145W5fNe8y",
          "pnl_24h": -1325.948665,
          "pnl_7d": -1794.127356,
          "pnl_30d": -4178.173788,
          "pnl_all_time": -28073.122926,
          "volume_24h": 0.0,
          "volume_7d": 171883.23514,
          "equity": 59496.672671
        },
        {
          "address": "92QGYEYWEjnwUZc3iEPn1jP6puaj9RaMitybBmichFXL",
          "pnl_24h": -1265.867533,
          "pnl_7d": 740.080939,
          "pnl_30d": 27969.443752,
          "pnl_all_time": 27969.443752,
          "volume_24h": 65.4016,
          "volume_7d": 158.2482,
          "equity": 123835.836692
        },
        {
          "address": "GNhkTxcaPskFesxh5XEaKTXgQrLxKu5CHT5ggRAqSBFz",
          "pnl_24h": -1254.866288,
          "pnl_7d": 1950.460236,
          "pnl_30d": -8242.984834,
          "pnl_all_time": -7822.683852,
          "volume_24h": 0.0,
          "volume_7d": 35180.9243,
          "equity": 9190.116148
        },
        {
          "address": "5zPgTweyqVACTpaYdtdK6mpvduZucQcvgfuVwMUd2WeV",
          "pnl_24h": -1199.922771,
          "pnl_7d": 2477.394297,
          "pnl_30d": -405.046941,
          "pnl_all_time": -4967.027915,
          "volume_24h": 1999.964,
          "volume_7d": 1999.964,
          "equity": 15806.301902
        },
        {
          "address": "CamaoEE51ftJaC61WkUxSDfBMoWshGL33c3eQzewDsLM",
          "pnl_24h": -1185.338877,
          "pnl_7d": -2996.665246,
          "pnl_30d": -3729.659997,
          "pnl_all_time": -11226.846277,
          "volume_24h": 70711.0606,
          "volume_7d": 1815567.0463,
          "equity": 1779.34424
        },
        {
          "address": "Gskf4VgodkUjKENhbJhfECqg37HYwqKGfDMZHrtWaVxW",
          "pnl_24h": -1181.891488,
          "pnl_7d": -2841.137312,
          "pnl_30d": -5640.258612,
          "pnl_all_time": -6078.672751,
          "volume_24h": 684534.432116,
          "volume_7d": 3116664.442397,
          "equity": 6747.962933
        },
        {
          "address": "Fh2itfDv6sybs6RCFAKWtuBqdo1JCTjskoWCQ9KAdXvN",
          "pnl_24h": -1078.003261,
          "pnl_7d": -1320.047918,
          "pnl_30d": -13791.057633,
          "pnl_all_time": -15377.226738,
          "volume_24h": 0.0,
          "volume_7d": 34856.77448,
          "equity": 4290.498318
        },
        {
          "address": "93g46jr8vpvjabSkkw7AKkV6DjFkfcMY2USdqcED1vzu",
          "pnl_24h": -1044.617611,
          "pnl_7d": -2547.286145,
          "pnl_30d": 127742.267882,
          "pnl_all_time": 44941.232114,
          "volume_24h": 1576738.17894,
          "volume_7d": 3828872.46439,
          "equity": 1528.419156
        },
        {
          "address": "BrUbTySdkBjkd7L9yjCqbSpVEehb2SeAyXCdZLYoAVL",
          "pnl_24h": -1025.196325,
          "pnl_7d": -1200.647218,
          "pnl_30d": -11899.745104,
          "pnl_all_time": -20641.173937,
          "volume_24h": 52358.420634,
          "volume_7d": 257926.944101,
          "equity": 14635.653406
        },
        {
          "address": "Hh1eBG6FVRXr5g7iobRLyd4yctLhDC3EDDMN3pSDgyfc",
          "pnl_24h": -995.099881,
          "pnl_7d": 1043.090912,
          "pnl_30d": 7332.498724,
          "pnl_all_time": -11505.93818,
          "volume_24h": 0.0,
          "volume_7d": 51182.31922,
          "equity": 43462.18481
        },
        {
          "address": "72Jy6vA8FDayniwyeuh8LrfePd3ASrDvV2aj3JeS1fYm",
          "pnl_24h": -969.731169,
          "pnl_7d": -1449.873119,
          "pnl_30d": 1368.609453,
          "pnl_all_time": 198.527652,
          "volume_24h": 206008.89685,
          "volume_7d": 564488.17645,
          "equity": 5.988479
        },
        {
          "address": "6xQmCzMwMpGhouMip57hy9NGrtGKwz2kv2ZtdhjhXh1K",
          "pnl_24h": -962.223249,
          "pnl_7d": 568.888998,
          "pnl_30d": -38478.112877,
          "pnl_all_time": -32729.539891,
          "volume_24h": 101729.92795,
          "volume_7d": 1023843.800439,
          "equity": 13483.74495
        },
        {
          "address": "FA7pLr6XNF7JdSQzSWRe5GD3dyuRruAXiPWMnjP5y2up",
          "pnl_24h": -945.764755,
          "pnl_7d": 532.844705,
          "pnl_30d": -38805.190802,
          "pnl_all_time": -44670.453498,
          "volume_24h": 294834.19609,
          "volume_7d": 1181819.0417,
          "equity": 40898.593333
        },
        {
          "address": "7QhDEJXmwb412upsKxpMpXSHx77w57yh9sVEkuuNRf9D",
          "pnl_24h": -941.145685,
          "pnl_7d": 1493.409658,
          "pnl_30d": -9462.278305,
          "pnl_all_time": -10651.57838,
          "volume_24h": 0.0,
          "volume_7d": 51.84745,
          "equity": 7261.52162
        },
        {
          "address": "WPiaQ7Dnh4hcHJeaBFeYoB7m6QdK3HucgU1FCTSKWkH",
          "pnl_24h": -911.618765,
          "pnl_7d": -1066.757804,
          "pnl_30d": -28176.894459,
          "pnl_all_time": -46226.408295,
          "volume_24h": 0.0,
          "volume_7d": 0.0,
          "equity": 16477.079609
        },
        {
          "address": "5mv4aVNLx3TJAbUjZw39xY9NvBBZXehzTffxsEJrxwHK",
          "pnl_24h": -873.045898,
          "pnl_7d": -1021.620617,
          "pnl_30d": 9296.290355,
          "pnl_all_time": 4449.631515,
          "volume_24h": 0.0,
          "volume_7d": 0.0,
          "equity": 13640.631515
        },
        {
          "address": "5RckUnSrHfJsfcX2y8tqVawPfGD3ngdh95vgZYpEnDRt",
          "pnl_24h": -869.183304,
          "pnl_7d": -2300.852632,
          "pnl_30d": -758.251707,
          "pnl_all_time": -4430.947712,
          "volume_24h": 207244.68301,
          "volume_7d": 1762881.79106,
          "equity": 3089.017069
        },
        {
          "address": "4u3L6r3nyL9XfZ93gMeXb4eddUGAXAMK8Cqkj1pvCmZB",
          "pnl_24h": -847.706176,
          "pnl_7d": 2437.004644,
          "pnl_30d": -4560.266013,
          "pnl_all_time": -5887.119691,
          "volume_24h": 2163.2015,
          "volume_7d": 48962.10773,
          "equity": 294162.880309
        },
        {
          "address": "9sdisaXk3eLnqdu2bu4Y5AQ2g14jPpXF8Jt3vjnUri3o",
          "pnl_24h": -824.520367,
          "pnl_7d": 5455.400713,
          "pnl_30d": 12804.663305,
          "pnl_all_time": 3208.069392,
          "volume_24h": 22793.493658,
          "volume_7d": 188904.372711,
          "equity": 103367.571556
        },
        {
          "address": "2Eh4crW2FRDQ7TGmWN2824qRVkBCoFWFL4LAd77zCESP",
          "pnl_24h": -769.816135,
          "pnl_7d": 743.38324,
          "pnl_30d": -4086.929809,
          "pnl_all_time": -1773.620973,
          "volume_24h": 248493.96283,
          "volume_7d": 2091990.57794,
          "equity": 4709.925878
        },
        {
          "address": "PCF8xwewcLmibAPnJcvydHoJ4VKKoxkGdbcbJqRdUSx",
          "pnl_24h": -756.098522,
          "pnl_7d": -70.541843,
          "pnl_30d": 40174.596496,
          "pnl_all_time": 115071.444222,
          "volume_24h": 4479894.607282,
          "volume_7d": 33990759.746803,
          "equity": 186071.444222
        }
      ],
      "total_traders": 4403
    }
  }
}